Workbook

Sheet PROCEDURE — Verify a PDF
A1: STANDARD PROCEDURE — RECONCILING A NEW BUDGET PDF INTO THIS WORKBOOK
B3: Replicated from the FY27 North Shore Wins reconciliation (Jul 8). Run these steps for every new source document so all figures stay consistent and tie to a verifiable total.
A5: 1 | B5: EXTRACT EVERY LINE — pull all organization/project rows, not just section totals (pdfplumber, all pages). Capture pot/category, organization, program note, source page ref, and amount.
A6: 2 | B6: VERIFY INTERNAL ARITHMETIC FIRST — before trusting any figure, confirm each subtotal sums to what the PDF prints, and that the sections sum to the grand total. Only proceed once every subtotal ties to the penny.
A7: 3 | B7: CROSS-REFERENCE TO THE MASTER — match the new rows against Master Line Items at pot/org level. Identical row-count + identical dollars + matching pots = consistent. Label-only differences (e.g. "Aging" vs "Aging Discretionary") are noted, not corrected.
A8: 4 | B8: APPLY D49 ATTRIBUTION (location-first, per standing EIN policy) — for each row: resolve the organization's location. If the facility is physically in a D49 zip (10301/02/03/04/10) it is IN D49 even when funded via Speaker/Delegation/non-city channels. If out-of-district but the purpose text says "Council District 49," it is TO D49. Flag corrections with a ✎ and a citation.
A9: 5 | B9: LABEL THE PROVENANCE TIER — ADOPTED (printed record) / ADOPTED-IMPLEMENTATION (allocated, clearing) / DELIBERATIVE (pending verification) / CONTEXT. Never mix tiers in one total; never merge separate bases (e.g. North-Shore citywide subset vs full-SI citywide).
A10: 6 | B10: RECONCILE TO THE INDEPENDENT FIGURE — confirm the grand ties to any external check (e.g. the colleague's ChatGPT North Shore Total $35,903,925). A TIES ✓ formula records the match so it re-checks on every open.
A11: 7 | B11: LOG ANY SCOPE DIFFERENCES AS F-ITEMS — differences that are scope not error (e.g. F11 Speaker $900K North-Shore view vs $825K strict tag; F12 Delegation $7.0M NS vs $7,418,000 full-SI) go in the Discrepancy Log with a resolution note, so they are never mistaken for mistakes.
A12: 8 | B12: PROPAGATE EVERYWHERE — write the detail tab, update Master/Reconcile/Finder, and re-run recalc.py to confirm zero formula errors before shipping.
B14: RESULT STANDARD: every figure carries a source page, a provenance tier, and a D49 status; every subtotal ties by formula; and the grand reconciles to an independent total. This is the house method for all budget documents going forward.

Sheet Grand Total — Combined (Jul 7)
A1: FY27 STATEN ISLAND — COMBINED GRAND TOTAL, ALL CHANGES APPLIED, TIED TO PDF
A2: Every figure below is a live formula pulling from the PDF detail tabs in this workbook. Column B = corrected (ruling F1). Column C = as printed in the All-Funding PDF. TIES checks confirm the numbers meet the PDF.
A4: SECTION 1 — CAPITAL (identical in both columns)
A5: Component | B5: Corrected | C5: As printed (PDF) | D5: Basis / source
A6: Hanks — 22 lines | B6: ='PDF Capital Detail'!D26 -> 17750000 | C6: ='PDF Capital Detail'!D26 -> 17750000 | D6: PDF Capital Detail tab, section total
A7: Carr — 34 lines | B7: ='PDF Capital Detail'!D62 -> 15600000 | C7: ='PDF Capital Detail'!D62 -> 15600000 | D7: PDF Capital Detail tab
A8: Morano — 30 lines | B8: ='PDF Capital Detail'!D94 -> 10536000 | C8: ='PDF Capital Detail'!D94 -> 10536000 | D8: PDF Capital Detail tab
A9: SI Delegation — 3 lines | B9: ='PDF Capital Detail'!D99 -> 7418000 | C9: ='PDF Capital Detail'!D99 -> 7418000 | D9: PDF Capital Detail tab
A10: Speaker (pure) — 5 lines incl. MA1004 | B10: ='PDF Capital Detail'!D106 -> 26046000 | C10: ='PDF Capital Detail'!D106 -> 26046000 | D10: PDF Capital Detail tab
A11: CAPITAL TOTAL | B11: =SUM(B6:B10) -> 77350000 | C11: =SUM(C6:C10) -> 77350000 | D11: PDF states $77,350,000
A13: SECTION 2 — EXPENSE
A14: Baseline CM allocated pots (45 rows) | B14: ='PDF Member Pots'!C55 -> 6773000 | C14: ='PDF Member Pots'!C55 -> 6773000 | D14: PDF Member Pots tab: Hanks $2,295,000 + Carr $2,270,000 + Morano $2,208,000
A15: Speaker initiatives — corrected (34 rows) | B15: ='Speaker Reconcile (Jul 7)'!D42 -> 2817880 | C15: ='Speaker Reconcile (Jul 7)'!D40 -> 2867880 | D15: Corrected = PDF $2,867,880 less Ulqin $25,000 + Project Hospitality $25,000 (ruling F1)
A16: Citywide initiatives (90 rows) | B16: ='PDF Citywide Lines'!C95 -> 8341467 | C16: ='PDF Citywide Lines'!C95 -> 8341467 | D16: PDF Citywide Lines tab
A17: EXPENSE TOTAL | B17: =SUM(B14:B16) -> 17932347 | C17: =SUM(C14:C16) -> 17982347 | D17: PDF states $17,982,347 (as-printed) · corrected $17,932,347
A19: SECTION 3 — GRAND TOTAL & TIE TO PDF
A20: CAPITAL + EXPENSE — GRAND TOTAL | B20: =B11+B17 -> 95282347 | C20: =C11+C17 -> 95332347
A21: PDF target — as printed | C21: 95332347 | D21: All-Funding PDF, page 1: "All-In Total: $95,332,347"
A22: TIE CHECK — as printed vs PDF | C22: =IF(C20=C21,"TIES ✓","CHECK Δ "&TEXT(C20-C21,"$#,##0")) -> TIES ✓
A23: Corrected grand total (ruling F1 applied) | B23: =B20 -> 95282347 | D23: Equals as-printed $95,332,347 less $50,000 (Ulqin + Project Hospitality out of Speaker)
A24: TIE CHECK — corrected = printed − $50,000 | B24: =IF(B23=C21-50000,"TIES ✓","CHECK") -> TIES ✓
A26: SECTION 4 — BRIDGE: WORKBOOK BASIS → PDF BASIS (every dollar of difference accounted)
A27: Workbook printed SI grand total (Grand Total tab basis) | B27: 93661240 | D27: Capital $77,350,000 + MDI $6,638,000 + Delegation $120,000 + Speaker $2,817,880 + other-CM MDI $92,000 + Citywide $6,553,360 + SU-CASA $90,000
A28: + Citywide dollars in PDF basis only (13 org groups $1,603,107 + IlluminArt partial $75,000 − workbook-only row $10,000) | B28: 1668107 | D28: Citywide Reconcile tab decomposition
A29: − Pot-allocation basis vs MDI-scan basis (pots $6,773,000 vs MDI $6,638,000 + other-CM $92,000 + SU-CASA $90,000 = $6,820,000) | B29: -47000 | D29: PDF counts pot allocations; workbook counts designated lines + DB items
A30: EQUALS: CORRECTED PDF-BASIS GRAND TOTAL | B30: =SUM(B27:B29) -> 95282347
A31: + Restore F1 rows (Ulqin $25,000 + Project Hospitality $25,000) → as printed | B31: =B30+50000 -> 95332347
A32: TIE CHECK — bridge reproduces PDF printed total | B32: =IF(B31=95332347,"TIES ✓","CHECK") -> TIES ✓
A33: TIE CHECK — bridge corrected = Section 3 corrected | B33: =IF(B30=B23,"TIES ✓","CHECK") -> TIES ✓
A35: Standing rule: the three bases (PDF as-printed, PDF corrected, workbook scan) remain separate measures. This tab exists to prove they meet — not to merge them. Official measures unchanged: A $74,812,000 · B $78,348,000 · C ≈$84,018,000.
A37: THE −$47,000 — DECOMPOSED AND RESOLVED (Jul 7, Hanks DB export)
A38: + SU-CASA allocations counted in PDF pot basis ($45,000 × 3 members) | B38: 135000
A39: − SU-CASA designated per July DB (Carr $45,000 + Morano $45,000) | B39: -90000
A40: − Other-CM dollars reaching SI, invisible to a pots view (MAS Bklyn&SI $85,000 + Vernikov→JCC Sunrise $7,000) | B40: -92000
A41: EQUALSnet pot-basis vs scan-basis difference | B41: =SUM(B38:B40) -> -47000
A42: RESOLVED: the Hanks 07-07-26 designation export contains ZERO SU-CASA rows — the undesignated $45,000 is CM HANKS’S. Action: designate before the window closes. See D49 Funding Finder tab.

Sheet D49 Attribution (corrected)
A1: DISTRICT 49 ATTRIBUTION — CORRECTED (Jul 8, per Omar) & LOCATION-VERIFIED
A2: Applies three D49 corrections and re-combs every North Shore component for in-district location. North Shore Total $35,903,925 confirmed = colleague's ChatGPT figure.
A4: Component | B4: Amount | C4: Category | D4: Location / Evidence | E4: D49 status
A5: Hanks Expense — 183 base orgs | B5: 2250000 | C5: MDI expense | D5: All rows tagged Council District 49 | E5: IN D49
A6: Hanks SU-CASA | B6: 45000 | C6: MDI expense | D6: Post-adoption; senior sites in D49 | E6: IN D49 (undesignated flag)
A7: Speaker — NYCID Credible Messengers | B7: 500000 | C7: Speaker | D7: SI-wide, HQ New Brighton 10310 | E7: IN D49
A8: Speaker — Chamber "49th Council District" | B8: 75000 | C8: Speaker | D8: CORRECTED: labeled 49th CD → Hanks/D49 (was blank sponsor) | E8: IN D49 ✎
A9: Speaker — Universal Temple Love In Bloom | B9: 50000 | C9: Speaker | D9: Stapleton 10304 | E9: IN D49
A10: Speaker — On Your Mark | B10: 35000 | C10: Speaker | D10: Pleasant Plains — serves D49 program | E10: TO D49
A11: Speaker — Atlas Foundation | B11: 30000 | C11: Speaker | D11: West Brighton 10310 | E11: IN D49
A12: Speaker — Dibra Community Org | B12: 25000 | C12: Speaker | D12: SI immigrant services | E12: TO D49
A13: Speaker — City Parks SummerStage CD49 | B13: 110000 | C13: Speaker | D13: p.358 — explicitly CD49 | E13: IN D49
A14: Speaker — JCC Social Adult Day Care | B14: 25000 | C14: Speaker | D14: p.392 — Stapleton | E14: IN D49
A15: Speaker — SI Immigrant Center | B15: 50000 | C15: Speaker | D15: p.441 — St. George | E15: IN D49
A16: Hanks Capital — 22 projects | B16: 17750000 | C16: Capital | D16: All §254 projects in CD49 | E16: IN D49
... A19: Non-City Capital — St. George Theatre | B19: 5850000 | C19: Non-city capital | D19: CORRECTED: 35 Hyatt St 10301 → IN D49 (MA1004) | E19: IN D49 ✎
A20: D49-LOCATED SUBTOTAL (all directly in/to District 49) | B20: =SUM(B5:B19) -> 33795000
A21: + Citywide initiatives to D49/NS orgs (separate basis) | B21: 2108925
A22: EQUALS NORTH SHORE TOTAL | B22: =B20+B21 -> 35903925
A23: ChatGPT / colleague figure $35,903,925 — tie check | B23: =IF(B22=35903925,"TIES ✓","CHECK") -> TIES ✓
A25: ✎ = corrected D49 attribution this pass. Snug Harbor, SI Zoo, and St. George Theatre are all physically within District 49 (North Shore), so their capital is D49-located even though sponsored via Delegation/non-city channels. The $75K Chamber "49th Council District" speaker item is Hanks/D49 despite a blank sponsor tag.

Sheet D49 Citywide — Missed Lines
A1: DISTRICT 49 CITYWIDE FUNDING — LINES BEYOND THE COLLEAGUE'S $2,108,925
A2: Colleague's 22-line figure is a defensible conservative floor (program-specific D49). This tab adds what his method missed, in two clearly-separated tiers so the two rules are never conflated.
A4: THE THREE DEFENSIBLE D49 CITYWIDE NUMBERS
A5: A · Colleague conservative — program names/serves D49 specifically (22 lines) | B5: 2108925 | C5: FLOOR — safest for mailer/oversight
A6: B · + Tier 1: program-specific lines he missed by his own rule (2 lines) | B6: 2144925 | C6: his rule, applied consistently
A7: C · + Tier 2: all D49-anchored orgs, any program scope (27 lines) | B7: 5807090 | C7: org-location rule — broadest defensible
A9: TIER 1 — MISSED BY HIS OWN RULE (program explicitly names a D49 school)
A10: Organization / Program | B10: Amount | C10: Initiative | D10: D49 marker
A11: Sundog Theatre, Inc. - Curtis High School (31R450) | B11: 18000 | C11: Violence Prevention and Intervention for Youth | D11: names a D49 school (Curtis HS / I.S. 49R)
A12: Sundog Theatre, Inc. - I.S. 49R Berta A. Dreyfus (31R049) | B12: 18000 | C12: Violence Prevention and Intervention for Youth | D12: names a D49 school (Curtis HS / I.S. 49R)
A13: TIER 1 SUBTOTAL | B13: =SUM(B11:B12) -> 36000
A15: TIER 2 — D49-ANCHORED ORG, BOROUGH/CITYWIDE PROGRAM SCOPE (org-location rule)
A16: These orgs are physically in D49 but the program serves the whole borough/city. Include only if using an org-location definition, not the program-scope rule.
A17: Organization | B17: Amount | C17: Initiative | D17: D49 location
A18: Pride Center of Staten Island, Inc. | B18: 444375 | C18: LGBTQIA+ Community Services | D18: St. George 10301
A19: Community Health Action of Staten Island, Inc. | B19: 363752 | C19: HIV/AIDS Pathways to Care | D19: Stapleton 10304
A20: Community Health Action of Staten Island, Inc. | B20: 350000 | C20: Opioid Prevention and Treatment | D20: Stapleton 10304
A21: Pride Center of Staten Island, Inc. | B21: 320000 | C21: Trans Equity Programs | D21: St. George 10301
A22: Richmond Medical Center | B22: 259000 | C22: Court-Involved Youth Mental Health Initiative | D22: West Brighton 10310
A23: Community Health Center of Richmond, Inc. | B23: 233523 | C23: Healthy Beginnings | D23: West Brighton 10310
A24: Pride Center of Staten Island, Inc. | B24: 130000 | C24: LGBTQIA+ Youth Support and Services | D24: St. George 10301
A25: Richmond Medical Center | B25: 107103 | C25: Developmental, Psychological and Behavioral Health Services | D25: West Brighton 10310
A26: Staten Island Community Job Center, Inc. | B26: 100000 | C26: Culturally Specific Gender Based Violence | D26: Port Richmond 10302
A27: Project Hospitality, Inc. | B27: 100000 | C27: LGBTQIA+ Youth Support and Services | D27: Stapleton 10304
A28: Richmond Medical Center | B28: 100000 | C28: Initiative to Combat Sexual Assault | D28: West Brighton 10310
A29: Pride Center of Staten Island, Inc. | B29: 100000 | C29: LGBTQIA+ Older Adult Services in Every Borough | D29: St. George 10301
... A45: Camelot of Staten Island, Inc. | B45: 10000 | C45: Boroughwide Needs | D45: Stapleton 10304
A46: TIER 2 SUBTOTAL | B46: =SUM(B18:B45) -> 3662165
A48: RECOMMENDATION: cite $2,108,925 (A) as the conservative "District 49 citywide wins" figure — every dollar is a program that names/serves D49, the safest claim. Use $5,807,090 (C) only for an internal "D49-anchored org" tally, always labeled as org-location basis. Never state a bare number without its rule.

Sheet D49 Evidence & Pages
A1: DISTRICT 49 — WHERE EVERY DOLLAR LIVES: SCHEDULE C PAGES, LOCATION, AND THE PRINTED D49 EVIDENCE
A2: Four channels, labeled separately. Expense channels locate in Schedule C by page; capital locates in Section 254 by CC/MA project ID (different document). Location from MOCS DB addresses; evidence quoted from CM Purpose / Program / printed org strings.
A4: A · HANKS FY27 MDI DESIGNATIONS — BY ORGANIZATION
A5: Organization | B5: EIN | C5: FY27 $ | D5: Sched C page(s) | E5: Zip | F5: Location classification | G5: Evidence keywords | H5: Evidence quote (CM Purpose / Program)
A6: Department of Parks and Recreation | B6: 13-6400434 | C6: 274000 | D6: App B p.107; App B p.110; App B p.111; App B p.112; App B p.62; App B p.63; App B p.64; App B p.65; App B p.66; App B p.67; App B p.69; p.112; p.191 | E6: 10007 | F6: OUTSIDE SI — WORKING IN D49 (text evidence) | G6: port richmond | H6: …Funding will support Port Richmond High School (31R445) Parent Tenant Association. | Port Richmond High Sc…
A7: Staten Island Chamber of Commerce Foundati | B7: 13-4069282 | C7: 95000 | D7: App B p.136; p.115; p.214 | E7: 10314 | F7: SI — OTHER DISTRICT AREA | G7: district 49, rosebank | H7: …ess Expo & Rosebank Holiday Event in Council District 49. | Women in Business Expo & Rosebank Holiday Event - Council District 49…
A8: Staten Island Economic Development Corpora | B8: 13-3706442 | C8: 85000 | D8: App B p.136; p.115; p.214 | E8: 10314 | F8: SI — OTHER DISTRICT AREA | G8: district 49 | H8: …port clean ups and beautification in Council District 49 | Council District 49 | Staten Island Economic Development Corporation…
A9: Community Agency for Senior Citizens, Inc. | B9: 13-3263537 | C9: 80000 | D9: App A p.6; p.176; p.77 | E9: 10301 | F9: LOCATED IN D49 (North Shore zip) | G9: district 49 | H9: …tywide domestic violence services. | Council District 49 | Community Agency for Senior Citizens, Inc.…
A10: New York Center for Interpersonal Developm | B10: 23-7085239 | C10: 80000 | D10: PDF p.58 (member listing) | E10: 10301 | F10: LOCATED IN D49 (North Shore zip) | G10: district 49 | H10: …rt the Credible Messenger program in Council District 49. | Council District 49 | New York Center for Interpersonal Development, I…
A11: Dr. Theodore A. Atlas Foundation, Inc. | B11: 13-4012789 | C11: 70000 | D11: App B p.70; App C p.163; PDF p.12 (member listing) | E11: 10310 | F11: LOCATED IN D49 (North Shore zip) | G11: district 49 | H11: …ion and turkey giveaways services in Council District 49. | Food Distribution - Council District 49 | Dr. Theodore A. Atlas Founda…
A12: City Parks Foundation | B12: 13-3561657 | C12: 61000 | D12: App B p.54; p.100; p.189 | E12: 10065 | F12: OUTSIDE SI — WORKING IN D49 (text evidence) | G12: district 49 | H12: …CityParks Learn & CityParks Build - Council District 49 | City Parks Foundation…
A13: Catholic Charities of Staten Island | B13: 13-5562286 | C13: 60000 | D13: App A p.5; p.175 | E13: 10309 | F13: SI — OTHER DISTRICT AREA | G13: district 49 | H13: …derson Neighborhood Senior Center in Council District 49. | Anderson Neighborhood Older Adult Center | Catholic Charities of State…
A14: Justice Innovation, Inc. | B14: 85-2810883 | C14: 60000 | D14: App C p.174; p.81 | E14: 10018 | F14: OUTSIDE SI — WORKING IN D49 (text evidence) | G14: district 49 | H14: …tywide domestic violence services. | Council District 49 | Justice Innovation, Inc.…
A15: Jewish Community Center of Staten Island, | B15: 13-5562256 | C15: 50000 | D15: App A p.14; p.103; p.180; p.67 | E15: 10314 | F15: SI — OTHER DISTRICT AREA | G15: stapleton | H15: …ng will support programs and services at the Stapleton Older Adult Center. | Stapleton Older Adult Center | Jewish Community Cente…
A16: Snug Harbor Cultural Center and Botanical | B16: 80-0193388 | C16: 50000 | D16: p.106; p.56; p.70 | E16: 10301 | F16: LOCATED IN D49 (North Shore zip) | G16: district 49, snug harbor | H16: …ce Development & Education Program - Council District 49 | Snug Harbor Cultural Center and Botanical Garden…
A17: Association of Community Employment Progra | B17: 13-3846431 | C17: 50000 | D17: p.189 | E17: 11101 | F17: OUTSIDE SI — WORKING IN D49 (text evidence) | G17: district 49 | H17: …eer groups. | Tappen Park Clean Up - Council District 49 | Association of Community Employment Programs for the Homeless, Inc.…
A18: Ballroom Basix USA, Inc. | B18: 27-3218865 | C18: 40000 | D18: App B p.35; p.32; p.61 | E18: 10035 | F18: OUTSIDE SI — WORKING IN D49 (text evidence) | G18: port richmond | H18: …to support programming in Public School 020R Port Richmond (31R020). | Public School 020R Port Richmond (31R020) | Ballroom Basix…
A19: Staten Island Institute of Arts and Scienc | B19: 13-5564127 | C19: 40000 | D19: p.56; p.57 | E19: 10301 | F19: LOCATED IN D49 (North Shore zip)
A20: West Brighton Community Local Development | B20: 13-3046424 | C20: 35000 | D20: App B p.145; p.15; p.215 | E20: 10310 | F20: LOCATED IN D49 (North Shore zip) | G20: west brighton | H20: …mall Business Technical Assistance Program | West Brighton Community Local Development Corporation…
A21: Citizens Committee for New York City, Inc. | B21: 51-0171818 | C21: 30000 | D21: PDF p.10 (member listing); p.100 | E21: 10035 | F21: OUTSIDE SI — WORKING IN D49 (text evidence) | G21: district 49 | H21: …spaces, and other vital resources. | Council District 49 | Citizens Committee for New York City, Inc.…
A22: Staten Island Community Services Friendshi | B22: 13-2778244 | C22: 30000 | D22: App A p.23; p.185 | E22: 10308 | F22: SI — OTHER DISTRICT AREA
A23: Canvas Institute | B23: 82-4902021 | C23: 30000 | D23: p.35; p.63 | E23: 10301 | F23: LOCATED IN D49 (North Shore zip) | G23: district 49 | H23: …that focus on immigrant heritages. | Council District 49 | Canvas Institute…
A24: Children's Aid Society, The | B24: 13-5562191 | C24: 30000 | D24: App C p.159; p.36 | E24: 10027 | F24: OUTSIDE SI — NO EXPLICIT D49 TEXT
A25: IlluminArt Productions | B25: 42-1727647 | C25: 30000 | D25: p.41; p.66 | E25: 10301 | F25: LOCATED IN D49 (North Shore zip)
A26: National Lighthouse Museum | B26: 13-4055215 | C26: 30000 | D26: p.49; p.68 | E26: 10301 | F26: LOCATED IN D49 (North Shore zip)
A27: Roundabout Theatre Company, Inc. | B27: 13-6192346 | C27: 30000 | D27: App B p.130; p.55 | E27: 10018 | F27: OUTSIDE SI — WORKING IN D49 (text evidence) | G27: port richmond | H27: …to students through after-school programs. | Port Richmond High School (31R445) | Roundabout Theatre Company, Inc.…
A28: Universal Temple of the Arts, Inc. | B28: 13-3335286 | C28: 30000 | D28: p.72 | E28: 10301 | F28: LOCATED IN D49 (North Shore zip) | G28: district 49 | H28: …that focus on immigrant heritages. | Council District 49 | Universal Temple of the Arts, Inc.…
A29: Staten Island Industrial Alliance/Northsho | B29: 92-2412852 | C29: 30000 | D29: p.15 | E29: 10303 | F29: LOCATED IN D49 (North Shore zip) | G29: district 49 | H29: …services. | Workforce Training Hub - Council District 49 | Staten Island Industrial Alliance/Northshore Leadership Alliance Corp.…
A30: Lifestyles for the Disabled, Inc. | B30: 13-3740011 | C30: 25000 | D30: App A p.15; App B p.94; p.181 | E30: 10314 | F30: SI — OTHER DISTRICT AREA | G30: district 49 | H30: …t the Serving Our Seniors program in Council District 49. | Serving Our Seniors - Council District 49 | Lifestyles for the Disable…
A31: Legal Services NYC | B31: 13-2600199 | C31: 25000 | D31: p.82 | E31: 10301 | F31: LOCATED IN D49 (North Shore zip) | G31: district 49 | H31: …tywide domestic violence services. | Council District 49 | Legal Services NYC…
A32: Seamen's Society for Children and Families | B32: 13-5563010 | C32: 25000 | D32: p.87 | E32: 10301 | F32: LOCATED IN D49 (North Shore zip) | G32: district 49 | H32: …tywide domestic violence services. | Council District 49 | Seamen's Society for Children and Families…
A33: Center For Hope Services, Inc. | B33: 88-2507208 | C33: 20000 | D33: App A p.5; p.175 | E33: 10305 | F33: D49 EDGE — 10305 (verify block) | G33: district 49 | H33: …ort the Age-Friendly Care program in Council District 49. | Age-Friendly Care Program - Council District 49 | Center For Hope Serv…
A34: On Your Mark, Inc. | B34: 13-3128315 | C34: 20000 | D34: PDF p.58 (member listing) | E34: 10301 | F34: LOCATED IN D49 (North Shore zip)
A35: Center for Educational Innovation | B35: 13-4113613 | C35: 20000 | D35: p.36 | E35: 10017 | F35: OUTSIDE SI — NO EXPLICIT D49 TEXT
A36: Marquis Studios, Ltd. | B36: 13-3047206 | C36: 20000 | D36: p.44 | E36: 11201 | F36: OUTSIDE SI — NO EXPLICIT D49 TEXT
A37: Noel Pointer Foundation, Inc. | B37: 11-3271472 | C37: 20000 | D37: p.50 | E37: 11216 | F37: OUTSIDE SI — NO EXPLICIT D49 TEXT
A38: Projectivity Group, Inc. | B38: 47-5358971 | C38: 20000 | D38: p.51 | E38: 10310 | F38: LOCATED IN D49 (North Shore zip)
A39: Staten Island Children's Museum | B39: 23-7379930 | C39: 20000 | D39: p.56 | E39: 10301 | F39: LOCATED IN D49 (North Shore zip)
A40: Staten Island Philharmonic Orchestra, Inc. | B40: 20-2732542 | C40: 20000 | D40: p.57 | E40: 10301 | F40: LOCATED IN D49 (North Shore zip) | G40: port richmond | H40: …to students through after-school programs. | Port Richmond High School (31R445) | Staten Island Philharmonic Orchestra, Inc.…
A41: Sundog Theatre, Inc. | B41: 45-0476945 | C41: 20000 | D41: p.58 | E41: 10301 | F41: LOCATED IN D49 (North Shore zip)
A42: TADA! Theatre and Dance Alliance, Inc. | B42: 13-3311294 | C42: 20000 | D42: p.58 | E42: 10001 | F42: OUTSIDE SI — NO EXPLICIT D49 TEXT
A43: Casa Belvedere, The Italian Cultural Found | B43: 26-4411728 | C43: 20000 | D43: App B p.48; p.63 | E43: 10301 | F43: LOCATED IN D49 (North Shore zip) | G43: district 49 | H43: …vedere. | Nonno's Community Garden - Council District 49 | Casa Belvedere, The Italian Cultural Foundation…
A44: Mouse, Inc. | B44: 13-3973196 | C44: 20000 | D44: p.12 | E44: 10004 | F44: OUTSIDE SI — NO EXPLICIT D49 TEXT
A45: PowerMyLearning, Inc. | B45: 13-3935309 | C45: 20000 | D45: p.14 | E45: 10003 | F45: OUTSIDE SI — NO EXPLICIT D49 TEXT
A46: Community Health Action of Staten Island, | B46: 13-3556132 | C46: 20000 | D46: p.78 | E46: 10301 | F46: LOCATED IN D49 (North Shore zip) | G46: district 49 | H46: …tywide domestic violence services. | Council District 49 | Community Health Action of Staten Island, Inc.…
A47: Legal Aid Society | B47: 13-5562265 | C47: 20000 | D47: p.82 | E47: 10038 | F47: OUTSIDE SI — WORKING IN D49 (text evidence) | G47: district 49 | H47: …tywide domestic violence services. | Council District 49 | Legal Aid Society…
A48: Metropolitan New York Coordinating Council | B48: 13-2738818 | C48: 20000 | D48: p.83 | E48: 10004 | F48: OUTSIDE SI — WORKING IN D49 (text evidence) | G48: district 49 | H48: …tywide domestic violence services. | Council District 49 | Metropolitan New York Coordinating Council on Jewish Poverty, Inc.…
A49: Grace Foundation of New York | B49: 13-4131863 | C49: 20000 | D49: App B p.79 | E49: 10314 | F49: SI — OTHER DISTRICT AREA | G49: district 49 | H49: …ll support programs and services for Council District 49 constituents. | Council District 49 | Grace Foundation of New York…
A50: Richmond County Orchestra, Inc. | B50: 13-4063615 | C50: 20000 | D50: App B p.128 | E50: 10304 | F50: LOCATED IN D49 (North Shore zip)
A51: Staten Island Zoological Society, Inc. | B51: 13-5680691 | C51: 20000 | D51: App B p.137 | E51: 10310 | F51: LOCATED IN D49 (North Shore zip)
A52: Community Health Center of Richmond, Inc. | B52: 51-0567466 | C52: 20000 | D52: p.176 | E52: 10302 | F52: LOCATED IN D49 (North Shore zip) | G52: district 49 | H52: …strict-based older adult services. | Council District 49 | Community Health Center of Richmond, Inc.…
A53: New York City H2O | B53: 45-3860014 | C53: 15000 | D53: App B p.106; p.104 | E53: 10009 | F53: OUTSIDE SI — WORKING IN D49 (text evidence) | G53: district 49 | H53: …Ecology & Engineering Programming - Council District 49 | New York City H2O…
A54: Waterfront Alliance, Inc. | B54: 13-4355067 | C54: 15000 | D54: p.106 | E54: 10018 | F54: OUTSIDE SI — WORKING IN D49 (text evidence) | G54: district 49 | H54: …sources. | Education & Programming - Council District 49 | Waterfront Alliance, Inc.…
A55: Eden II School for Autistic Children, Inc. | B55: 13-2872916 | C55: 15000 | D55: App B p.72; App C p.164 | E55: 10304 | F55: LOCATED IN D49 (North Shore zip) | G55: district 49 | H55: …ort to the Family Support Program in Council District 49. | Family Support Program - Council District 49 | Eden II School for Auti…
A56: Literacy Partners, Inc. | B56: 51-0180665 | C56: 15000 | D56: App B p.94 | E56: 10038 | F56: OUTSIDE SI — WORKING IN D49 (text evidence) | G56: district 49 | H56: …Funding to support programming in Council District 49. | Council District 49 | Literacy Partners, Inc.…
A57: Kresischer Mansion Historical Preservation | B57: 33-3459695 | C57: 15000 | D57: App C p.175 | E57: 10309 | F57: SI — OTHER DISTRICT AREA
A58: PowerPlay NYC, Inc. | B58: 13-4045021 | C58: 15000 | D58: App C p.183 | E58: 10005 | F58: OUTSIDE SI — WORKING IN D49 (text evidence) | G58: district 49 | H58: …ls for Success (STARS) initiative in Council District 49. | Sports Training and Role-models for Success (STARS) | PowerPlay NYC, I…
A59: Staten Island Hurricanes Organization, Inc | B59: 87-1793853 | C59: 15000 | D59: App C p.187 | E59: 10310 | F59: LOCATED IN D49 (North Shore zip) | G59: district 49 | H59: …Staten Island Youth Football Team. | Council District 49 | Staten Island Hurricanes Organization, Inc.…
A60: Billion Oyster Project, Inc. | B60: 27-2918478 | C60: 10000 | D60: p.99 | E60: 10004 | F60: OUTSIDE SI — NO EXPLICIT D49 TEXT
A61: Friends of Alice Austen House, Inc. | B61: 13-3248928 | C61: 10000 | D61: p.65 | E61: 10305 | F61: D49 EDGE — 10305 (verify block) | G61: port richmond | H61: …on immigrant heritages. | Public School 020R Port Richmond (31R020) | Friends of Alice Austen House, Inc.…
A62: Midtown Management Group, Inc. | B62: 13-3192793 | C62: 10000 | D62: p.68 | E62: 10036 | F62: OUTSIDE SI — NO EXPLICIT D49 TEXT
A63: Noble Maritime Collection, The | B63: 13-3351673 | C63: 10000 | D63: p.69 | E63: 10301 | F63: LOCATED IN D49 (North Shore zip)
A64: Jewish Board of Family and Children's Serv | B64: 13-5564937 | C64: 10000 | D64: p.81 | E64: 10018 | F64: OUTSIDE SI — NO EXPLICIT D49 TEXT
A65: Pride Center of Staten Island, Inc. | B65: 46-3358895 | C65: 10000 | D65: p.86 | E65: 10305 | F65: D49 EDGE — 10305 (verify block) | G65: district 49 | H65: …tywide domestic violence services. | Council District 49 | Pride Center of Staten Island, Inc.…
A66: A Chance In Life | B66: 13-1835632 | C66: 10000 | D66: App B p.27 | E66: 10310 | F66: LOCATED IN D49 (North Shore zip) | G66: district 49 | H66: …uth center and community services in Council District 49. | Council District 49 | A Chance In Life…
A67: Bee U, Inc. | B67: 88-1156617 | C67: 10000 | D67: App B p.36 | E67: 10304 | F67: LOCATED IN D49 (North Shore zip) | G67: district 49 | H67: …rt community workshops and visits in Council District 49. | Community Workshops - Council District 49 | Bee U, Inc.…
A68: City University of New York | B68: 13-3893536 | C68: 10000 | D68: App B p.54 | E68: 10065 | F68: OUTSIDE SI — WORKING IN D49 (text evidence) | G68: district 49 | H68: …rtnership Student Success Program in Council District 49. | College of Staten Island - Liberty Partnership Student Success Program…
A69: Jeremiah Program | B69: 41-1801834 | C69: 10000 | D69: App B p.87 | E69: 11217 | F69: OUTSIDE SI — WORKING IN D49 (text evidence) | G69: district 49, north shore | H69: …orth Shore Single Mother Students in Council District 49. | | Jeremiah Program…
A70: Maker Park Radio, Inc. | B70: 82-1397822 | C70: 10000 | D70: App B p.96 | E70: 10301 | F70: LOCATED IN D49 (North Shore zip) | G70: district 49 | H70: …SonicLab program and other events in Council District 49. | Council District 49 | Maker Park Radio, Inc.…
A71: Friends of Abandoned Cemeteries, Inc. | B71: 13-3176456 | C71: 10000 | D71: p.113 | E71: 10310 | F71: LOCATED IN D49 (North Shore zip) | G71: district 49 | H71: …to maintain abandoned cemeteries. | Council District 49 | Friends of Abandoned Cemeteries, Inc.…
A72: Silver Mount Cemetery Association, Inc. | B72: 13-5579013 | C72: 10000 | D72: p.115 | E72: 10301 | F72: LOCATED IN D49 (North Shore zip)
A73: Fund for the City of New York, Inc. | B73: 13-2612524 | C73: 10000 | D73: p.194 | E73: 11691 | F73: OUTSIDE SI — NO EXPLICIT D49 TEXT
A74: Meals on Wheels of Staten Island, Inc. | B74: 13-2894978 | C74: 10000 | D74: p.181 | E74: 10302 | F74: LOCATED IN D49 (North Shore zip) | G74: district 49 | H74: …strict-based older adult services. | Council District 49 | Meals on Wheels of Staten Island, Inc.…
A75: Eagle Academy Foundation, Inc. | B75: 20-1532382 | C75: 10000 | D75: App C p.164 | E75: 10027 | F75: OUTSIDE SI — WORKING IN D49 (text evidence) | G75: district 49 | H75: …he Eagles Soaring Beyond programs in Council District 49. | Post-Secondary Success Initiative (PSSI) & Eagles Soaring Beyond (ESB)…
A76: Integrated Athletic Initiative Corp | B76: 87-3354678 | C76: 10000 | D76: App C p.172 | E76: 10314 | F76: SI — OTHER DISTRICT AREA | G76: district 49 | H76: …h programs and services for youth in Council District 49. | Council District 49 | Integrated Athletic Initiative Corp…
A77: Mrs. Fairy Grandz, Inc. | B77: 33-1833069 | C77: 5000 | D77: PDF p.16 (member listing) | F77: NO ADDRESS IN DB | G77: district 49 | H77: …and homeless prevention services in Council District 49. | Council District 49 | Mrs. Fairy Grandz, Inc.…
A78: University of Notre Dame Alumni Club of St | B78: 31-1344537 | C78: 5000 | D78: PDF p.21 (member listing) | E78: 10309 | F78: SI — OTHER DISTRICT AREA | G78: district 49, 49th | H78: …strict. | Bread of Life Food Drive - Council District 49. | University of Notre Dame Alumni Club of Staten Island…
A79: Arab-American Family Support Center, Inc., | B79: 11-3167245 | C79: 5000 | D79: p.76 | E79: 11201 | F79: OUTSIDE SI — WORKING IN D49 (text evidence) | G79: district 49 | H79: …ices. | Domestic Violence Services - Council District 49 | Arab-American Family Support Center, Inc., The…
A80: Art Lab, Inc. | B80: 13-2977495 | C80: 5000 | D80: App B p.33 | E80: 10301 | F80: LOCATED IN D49 (North Shore zip) | G80: district 49 | H80: …ing will support community events in Council District 49. | Community Events - Council District 49 | Art Lab, Inc.…
A81: Emergency Children's Help Organization, In | B81: 11-3828185 | C81: 5000 | D81: App B p.73 | E81: 10309 | F81: SI — OTHER DISTRICT AREA | G81: district 49 | H81: …sistance programming and services in Council District 49. | Emergency Assistance Program - Council District 49 | Emergency Childre…
A82: Forest Avenue District Management Associat | B82: 14-1933279 | C82: 5000 | D82: App B p.75 | E82: 10310 | F82: LOCATED IN D49 (North Shore zip) | G82: district 49 | H82: …ty outreach programs and services in Council District 49. | Council District 49 | Forest Avenue District Management Association, I…
A83: Garibaldi-Meucci Museum | B83: 06-1725844 | C83: 5000 | D83: App B p.78 | E83: 10305 | F83: D49 EDGE — 10305 (verify block)
A84: Northeast Corridor Freedom Network, Inc. | B84: 41-2828867 | C84: 5000 | D84: App B p.115 | E84: 07878 | F84: OUTSIDE SI — WORKING IN D49 (text evidence) | G84: district 49 | H84: …o support historical preservation in Council District 49. | Council District 49 | Northeast Corridor Freedom Network, Inc.…
A85: Port Richmond CERT & Rescue, Inc. | B85: 20-5073806 | C85: 5000 | D85: App B p.120 | E85: 10314 | F85: SI — OTHER DISTRICT AREA | G85: district 49, port richmond | H85: …upport various emergency services in Council District 49. | Council District 49 | Port Richmond CERT & Rescue, Inc.…
A86: Staten Island Sports Hall of Fame, Inc. | B86: 13-3833390 | C86: 5000 | D86: App B p.137 | E86: 10312 | F86: SI — OTHER DISTRICT AREA
A87: Van Duzer Street Area Civic Association | B87: 20-0818886 | C87: 5000 | D87: App B p.142 | E87: 10304 | F87: LOCATED IN D49 (North Shore zip) | G87: district 49 | H87: …g, Toy Giveaway, and Light Parade in Council District 49. | Annual Holiday Tree Lighting, Toy Giveaway & Staten Island Light Parad…
A88: Young Airmans Association, The | B88: 83-2005292 | C88: 5000 | D88: App B p.148 | E88: 11692 | F88: OUTSIDE SI — WORKING IN D49 (text evidence) | G88: district 49 | H88: …ding to support youth instruction in Council District 49. | Youth Instruction - Council District 49 | Young Airmans Association,…
A89: Boy Scouts of America - Greater New York C | B89: 13-1624015 | C89: 5000 | D89: App C p.155 | E89: 10022 | F89: OUTSIDE SI — WORKING IN D49 (text evidence) | G89: district 49 | H89: …e Scouting and Exploring programs in Council District 49. | Scouting & Exploring - Council District 49 | Boy Scouts of America - G…
A90: Hish Family | B90: 92-2127573 | C90: 5000 | D90: App C p.171 | E90: 10301 | F90: LOCATED IN D49 (North Shore zip) | G90: district 49 | H90: …To support youth programming in Council District 49. | Council District 49 | Hish Family…
A91: Police Athletic League, Inc. | B91: 13-5596811 | C91: 5000 | D91: App C p.183 | E91: 10003 | F91: OUTSIDE SI — WORKING IN D49 (text evidence) | G91: district 49 | H91: …t community youth recreation days in Council District 49. | Community Youth Sports, Culture & Recreation - Council District 49 | P…
A92: Read Alliance, Inc. | B92: 13-4091062 | C92: 5000 | D92: App C p.184 | E92: 10038 | F92: OUTSIDE SI — WORKING IN D49 (text evidence) | G92: district 49 | H92: …l Year and Summer READing program in Council District 49. | School Year & Summer READing Program - Council District 49 | Read Alli…
A93: Soroptimist International Association Club | B93: 20-0895316 | C93: 5000 | D93: App C p.186 | E93: 10314 | F93: SI — OTHER DISTRICT AREA | G93: district 49 | H93: …t the Dream It, Be It programming in Council District 49. | Dream It, Be It Program | Soroptimist International Association Club o…
A94: Student Leadership Network, Inc. | B94: 06-1517218 | C94: 5000 | D94: App C p.187 | E94: 10001 | F94: OUTSIDE SI — WORKING IN D49 (text evidence) | G94: district 49 | H94: …port the College Bound Initiative in Council District 49. | College Bound Initiative (CBI) | Student Leadership Network, Inc.…
A95: Wagner College | B95: 13-5604699 | C95: 5000 | D95: App C p.190 | E95: 10301 | F95: LOCATED IN D49 (North Shore zip)
A96: Young Men's Christian Association of Great | B96: 13-1624228 | C96: 5000 | D96: App C p.192 | E96: 10023 | F96: OUTSIDE SI — NO EXPLICIT D49 TEXT
A97: SECTION A TOTAL — 91 organizations | C97: =SUM(C6:C96) -> 2250000 | D97: ties DB FY27 $2,250,000
A99: B · SPEAKER ITEMS TO SI (34 retained) — SPONSOR TAG IS THE D49/SI RATIONALE
A100: Organization — Program | B100: EIN/page | C100: Amount | D100: Sched C page | E100: Zip | F100: Why considered | G100: Sponsor tag
A101: African Refuge, Inc. - Community and Police Mental H | C101: 50000 | D101: Speaker itemization (PDF p.260) | E101: 10304 | F101: SI-serving org, untagged sponsor · org located in D49 zip 10304 | G101: untagged — SI-serving
A102: Canvas Institute - Media mentorship programs for loc | C102: 75000 | D102: — | E102: 10301 | F102: SI Delegation-sponsored → borough-wide · org located in D49 zip 10301 | G102: Staten Island
...

Sheet D49 Funding Finder
A1: DISTRICT 49 FUNDING FINDER — ALL CM HANKS / D49 DOLLARS, ONE PLACE
A2: Type any organization keyword in the yellow cell; every figure below it is a live formula over the FY25–27 designation register, the FY27 capital detail, and the Speaker lines. Components stay labeled separately per house rule.
A4: TYPE ORG KEYWORD → | B4: ZOOLOGICAL
A6: Result for keyword | B6: FY27 $ | C6: FY26 $ | D6: FY25 $ | E6: FY27 capital $ | F6: FY27 Speaker $ | G6: Lines matched | H6: Note
A7: Designations (MOCS DB 7-7) + FY27 capital + Speaker | B7: =SUMPRODUCT(--ISNUMBER(SEARCH($B$4,'Hanks D49 FY25–27 (DB 7-7)'!$C$4:$C$186&"")),'Hanks D49 FY25–27 (DB 7-7)'!$E$4:$E$186) -> 20000 | C7: =SUMPRODUCT(--ISNUMBER(SEARCH($B$4,'Hanks D49 FY25–27 (DB 7-7)'!$C$188:$C$389&"")),'Hanks D49 FY25–27 (DB 7-7)'!$E$188:$E$389) -> 20000 | D7: =SUMPRODUCT(--ISNUMBER(SEARCH($B$4,'Hanks D49 FY25–27 (DB 7-7)'!$C$391:$C$601&"")),'Hanks D49 FY25–27 (DB 7-7)'!$E$391:$E$601) -> 5000 | E7: =SUMPRODUCT(--ISNUMBER(SEARCH($B$4,'PDF Capital Detail'!$C$6:$C$107&"")),--('PDF Capital Detail'!$A$6:$A$107="HANKS"),'PDF Capital Detail'!$D$6:$D$107) -> 120000 | F7: =SUMPRODUCT(--ISNUMBER(SEARCH($B$4,'Speaker Reconcile (Jul 7)'!$C$4:$C$39&"")),--ISNUMBER(SEARCH("HANKS",'Speaker Reconcile (Jul 7)'!$A$4:$A$39&"")),--('Speaker Reconcile (Jul 7)'!$E$4:$E$39="Retained"),'Speaker Reconcile (Jul 7)'!$D$4:$D$39) -> 0 | G7: =SUMPRODUCT(--ISNUMBER(SEARCH($B$4,'Hanks D49 FY25–27 (DB 7-7)'!$C$4:$C$601&""))) -> 3 | H7: Capital/Speaker match on project/org text; verify EIN before citing
A10: DISTRICT 49 — FY27 ALL-IN STACK (components labeled; SI-shared pools listed but not district-split)
A11: Component | B11: Amount | C11: Basis
A12: Hanks MDI designations — 183 lines | B12: ='Hanks D49 FY25–27 (DB 7-7)'!E187 -> 2250000 | C12: MOCS/Council DB 07-07-26
A13: Hanks SU-CASA allocation — UNDESIGNATED | B13: 45000 | C13: $135,000 SI allocations − $90,000 DB = Hanks $45,000 with zero rows in export — ACTION: designate
A14: Hanks capital — 22 lines | B14: ='PDF Capital Detail'!D26 -> 17750000 | C14: Section 254 / All-Funding PDF
A15: Hanks-sponsored Speaker items | B15: 825000 | C15: $825K strict 6-item tag · North-Shore view $900K incl. Chamber 49th $75K, City Parks $110K, JCC SADC $25K, SI Immigrant $50K (corrected Jul 8) — see D49 Attribution tab
A16: D49 DIRECT TOTAL | B16: =SUM(B12:B15) -> 20870000 | C16: sum of the four lines above
A17: Memo — SI Delegation capital (shared, 3 lines) | B17: 7418000 | C17: serves all SI; not district-split
A18: Memo — SI Delegation expense pot (shared) | B18: 120000 | C18: Boroughwide Needs 11 rows
A19: Memo — Citywide-to-SI expense (shared) | B19: 8341467 | C19: PDF basis; org-level D49 reach via search box above
A20: Memo — Speaker pure capital + SI-tagged items (shared) | C20: Willowbrook, Bloomingdale, SIUH Prince, CSI lot, MA1004
A23: D49 ORGANIZATION ROLLUP — EVERY ORG FUNDED BY CM HANKS, FY25–FY27 (designation basis) + FY27 SPEAKER
A24: Organization (per DB) | B24: EIN | C24: FY27 $ | D24: FY26 $ | E24: FY25 $ | F24: FY27 Speaker $ | G24: 3-yr total $ | H24: Pots seen
A25: New York Center for Interpersonal Developmen | B25: 23-7085239 | C25: 80000 | D25: 80000 | E25: 80000 | F25: 500000 | G25: =SUM(C25:F25) -> 740000 | H25: Community Safety a
A26: Department of Sanitation | B26: 13-6400434 | C26: 180000 | D26: 150000 | E26: 200000 | G26: =SUM(C26:F26) -> 530000 | H26: NYC Cleanup
A27: Dr. Theodore A. Atlas Foundation, Inc. | B27: 13-4012789 | C27: 70000 | D27: 124500 | E27: 97500 | F27: 30000 | G27: =SUM(C27:F27) -> 322000 | H27: Aging; Anti-Poverty; Food Pantries; Lo
A28: City Parks Foundation | B28: 13-3561657 | C28: 61000 | D28: 45000 | E28: 25000 | F28: 110000 | G28: =SUM(C28:F28) -> 241000 | H28: A Greener NYC; Local; Parks Equity Ini
A29: Community Agency for Senior Citizens, Inc. | B29: 13-3263537 | C29: 80000 | D29: 70000 | E29: 90000 | G29: =SUM(C29:F29) -> 240000 | H29: Aging; Domestic Violence ; Support Our
A30: Staten Island Chamber of Commerce Foundation | B30: 13-4069282 | C30: 95000 | D30: 75000 | E30: 50000 | G30: =SUM(C30:F30) -> 220000 | H30: Local; NYC Cleanup; Neighborhood Devel
A31: Justice Innovation, Inc. | B31: 85-2810883 | C31: 60000 | D31: 60000 | E31: 60000 | G31: =SUM(C31:F31) -> 180000 | H31: Domestic Violence ; Youth
A32: Jewish Community Center of Staten Island, In | B32: 13-5562256 | C32: 50000 | D32: 50000 | E32: 50000 | F32: 25000 | G32: =SUM(C32:F32) -> 175000 | H32: A Greener NYC; Aging; Cultural Immigra
A33: Association of Community Employment Programs | B33: 13-3846431 | C33: 50000 | D33: 90000 | E33: 10000 | G33: =SUM(C33:F33) -> 150000 | H33: NYC Cleanup; Parks Equity Initi
A34: Department of Education | B34: 13-6400434 | C34: 49000 | D34: 49000 | E34: 44000 | G34: =SUM(C34:F34) -> 142000 | H34: Local
A35: IlluminArt Productions | B35: 42-1727647 | C35: 30000 | D35: 55000 | E35: 55000 | G35: =SUM(C35:F35) -> 140000 | H35: Cultural After-Sch; Cultural Immigrant
A36: Universal Temple of the Arts, Inc. | B36: 13-3335286 | C36: 30000 | D36: 30000 | E36: 28000 | F36: 50000 | G36: =SUM(C36:F36) -> 138000 | H36: Cultural Immigrant; Local
A37: Staten Island Economic Development Corporati | B37: 13-3706442 | C37: 85000 | D37: 35000 | E37: 15000 | G37: =SUM(C37:F37) -> 135000 | H37: Local; NYC Cleanup; Neighborhood Devel
A38: Snug Harbor Cultural Center & Botanical Gard | B38: 80-0193388 | D38: 65000 | E38: 65000 | G38: =SUM(C38:F38) -> 130000 | H38: A Greener NYC; Cultural After-Sch; Cul
A39: Seamen's Society for Children and Families | B39: 13-5563010 | C39: 25000 | D39: 25000 | E39: 75000 | G39: =SUM(C39:F39) -> 125000 | H39: Domestic Violence ; Local
A40: Catholic Charities of Staten Island | B40: 13-5562286 | C40: 60000 | D40: 30000 | E40: 30000 | G40: =SUM(C40:F40) -> 120000 | H40: Aging; Support Our Older
A41: Staten Island Institute of Arts and Sciences | B41: 13-5564127 | C41: 40000 | D41: 40000 | E41: 40000 | G41: =SUM(C41:F41) -> 120000 | H41: Cultural After-Sch
A42: Ballroom Basix USA, Inc. | B42: 27-3218865 | C42: 40000 | D42: 40000 | E42: 30000 | G42: =SUM(C42:F42) -> 110000 | H42: Cultural After-Sch; Cultural Immigrant
A43: West Brighton Community Local Development Co | B43: 13-3046424 | C43: 35000 | D43: 35000 | E43: 35000 | G43: =SUM(C43:F43) -> 105000 | H43: Digital Inclusion ; Local; Neighborhoo
A44: Staten Island Community Services Friendship | B44: 13-2778244 | C44: 30000 | D44: 30000 | E44: 30000 | G44: =SUM(C44:F44) -> 90000 | H44: Aging; Support Our Older
A45: Canvas Institute | B45: 82-4902021 | C45: 30000 | D45: 30000 | E45: 30000 | G45: =SUM(C45:F45) -> 90000 | H45: Cultural After-Sch; Cultural Immigrant
A46: Children's Aid Society, The | B46: 13-5562191 | C46: 30000 | D46: 30000 | E46: 30000 | G46: =SUM(C46:F46) -> 90000 | H46: Cultural After-Sch; Youth
A47: National Lighthouse Museum | B47: 13-4055215 | C47: 30000 | D47: 30000 | E47: 30000 | G47: =SUM(C47:F47) -> 90000 | H47: Cultural After-Sch; Cultural Immigrant
A48: Sundog Theatre, Inc. | B48: 45-0476945 | C48: 20000 | D48: 35000 | E48: 35000 | G48: =SUM(C48:F48) -> 90000 | H48: Cultural After-Sch; SU-CASA
A49: Roundabout Theatre Company, Inc. | B49: 13-6192346 | C49: 30000 | D49: 30000 | E49: 20000 | G49: =SUM(C49:F49) -> 80000 | H49: Cultural After-Sch; Local
A50: Community Health Action of Staten Island, In | B50: 13-3556132 | C50: 20000 | D50: 20000 | E50: 35000 | G50: =SUM(C50:F50) -> 75000 | H50: Domestic Violence
... A54: Lifestyles for the Disabled, Inc. | B54: 13-3740011 | C54: 25000 | D54: 20000 | E54: 20000 | G54: =SUM(C54:F54) -> 65000 | H54: Aging; Local; Support Our Older
A55: On Your Mark, Inc. | B55: 13-3128315 | C55: 20000 | D55: 5000 | E55: 5000 | F55: 35000 | G55: =SUM(C55:F55) -> 65000 | H55: Community Safety a; Local
A56: Marquis Studios, Ltd. | B56: 13-3047206 | C56: 20000 | D56: 20000 | E56: 20000 | G56: =SUM(C56:F56) -> 60000 | H56: Cultural After-Sch
A57: Noel Pointer Foundation, Inc. | B57: 11-3271472 | C57: 20000 | D57: 20000 | E57: 20000 | G57: =SUM(C57:F57) -> 60000 | H57: Cultural After-Sch
A58: Staten Island Children's Museum | B58: 23-7379930 | C58: 20000 | D58: 20000 | E58: 20000 | G58: =SUM(C58:F58) -> 60000 | H58: Cultural After-Sch
A59: Staten Island Philharmonic Orchestra, Inc. | B59: 20-2732542 | C59: 20000 | D59: 20000 | E59: 20000 | G59: =SUM(C59:F59) -> 60000 | H59: Cultural After-Sch
A60: TADA! Theatre and Dance Alliance, Inc. | B60: 13-3311294 | C60: 20000 | D60: 20000 | E60: 20000 | G60: =SUM(C60:F60) -> 60000 | H60: Cultural After-Sch
A61: Casa Belvedere, The Italian Cultural Foundat | B61: 26-4411728 | C61: 20000 | D61: 20000 | E61: 20000 | G61: =SUM(C61:F61) -> 60000 | H61: Cultural Immigrant; Local
A62: Mouse, Inc. | B62: 13-3973196 | C62: 20000 | D62: 20000 | E62: 20000 | G62: =SUM(C62:F62) -> 60000 | H62: Digital Inclusion
A63: PowerMyLearning, Inc. | B63: 13-3935309 | C63: 20000 | D63: 20000 | E63: 20000 | G63: =SUM(C63:F63) -> 60000 | H63: Digital Inclusion
A64: Legal Aid Society | B64: 13-5562265 | C64: 20000 | D64: 20000 | E64: 20000 | G64: =SUM(C64:F64) -> 60000 | H64: Domestic Violence
A65: Metropolitan New York Coordinating Council o | B65: 13-2738818 | C65: 20000 | D65: 20000 | E65: 20000 | G65: =SUM(C65:F65) -> 60000 | H65: Domestic Violence
A66: Literacy Partners, Inc. | B66: 51-0180665 | C66: 15000 | D66: 15000 | E66: 30000 | G66: =SUM(C66:F66) -> 60000 | H66: Digital Inclusion ; Local
A67: Fund for the City of New York, Inc. | B67: 13-2612524 | C67: 10000 | D67: 30000 | E67: 20000 | G67: =SUM(C67:F67) -> 60000 | H67: Parks Equity Initi
A68: Meals on Wheels of Staten Island, Inc. | B68: 13-2894978 | C68: 10000 | D68: 20000 | E68: 25000 | G68: =SUM(C68:F68) -> 55000 | H68: Food Pantries; Support Our Older
A69: Food Bank For New York City | B69: 13-3179546 | E69: 55000 | G69: =SUM(C69:F69) -> 55000 | H69: Food Pantries
A70: Snug Harbor Cultural Center and Botanical Ga | B70: 80-0193388 | C70: 50000 | G70: =SUM(C70:F70) -> 50000 | H70: A Greener NYC; Cultural After-Sch; Cul
A71: Center For Hope Services, Inc. | B71: 88-2507208 | C71: 20000 | D71: 20000 | E71: 10000 | G71: =SUM(C71:F71) -> 50000 | H71: Aging; Local; Support Our Older
A72: Staten Island Immigrant Center, Inc. | B72: — | F72: 50000 | G72: =SUM(C72:F72) -> 50000
A73: New York City Housing Authority | B73: 13-6400434 | C73: 16000 | D73: 16000 | E73: 16000 | G73: =SUM(C73:F73) -> 48000 | H73: Local
A74: Waterfront Alliance, Inc. | B74: 13-4355067 | C74: 15000 | D74: 15000 | E74: 15000 | G74: =SUM(C74:F74) -> 45000 | H74: A Greener NYC
A75: Staten Island Zoological Society, Inc. | B75: 13-5680691 | C75: 20000 | D75: 20000 | E75: 5000 | G75: =SUM(C75:F75) -> 45000 | H75: Local
A76: Staten Island Hurricanes Organization, Inc. | B76: 87-1793853 | C76: 15000 | D76: 15000 | E76: 15000 | G76: =SUM(C76:F76) -> 45000 | H76: Youth
A77: Richmond County Black & Minority Chamber Com | B77: 47-4178194 | D77: 30000 | E77: 15000 | G77: =SUM(C77:F77) -> 45000 | H77: Digital Inclusion ; Local
A78: Center for Educational Innovation | B78: 13-4113613 | C78: 20000 | D78: 20000 | G78: =SUM(C78:F78) -> 40000 | H78: Cultural After-Sch
A79: Staten Island Industrial Alliance/Northshore | B79: 92-2412852 | C79: 30000 | E79: 10000 | G79: =SUM(C79:F79) -> 40000 | H79: Digital Inclusion ; Neighborhood Devel
A80: Emergency Children's Help Organization, Inc. | B80: 11-3828185 | C80: 5000 | D80: 20000 | E80: 15000 | G80: =SUM(C80:F80) -> 40000 | H80: Community Safety a; Local
A81: Richmond County Orchestra, Inc. | B81: 13-4063615 | C81: 20000 | D81: 20000 | G81: =SUM(C81:F81) -> 40000 | H81: Local
A82: Community Health Center of Richmond, Inc. | B82: 51-0567466 | C82: 20000 | D82: 20000 | G82: =SUM(C82:F82) -> 40000 | H82: Support Our Older
A83: Educational Video Center, Inc. | B83: 13-3378456 | D83: 20000 | E83: 20000 | G83: =SUM(C83:F83) -> 40000 | H83: Cultural Immigrant
A84: Staten Island Urban Center | B84: 37-1833463 | E84: 40000 | G84: =SUM(C84:F84) -> 40000 | H84: Cultural After-Sch; Domestic Violence
A85: New York City H2O | B85: 45-3860014 | C85: 15000 | D85: 10000 | E85: 10000 | G85: =SUM(C85:F85) -> 35000 | H85: A Greener NYC; Local
A86: Maker Park Radio, Inc. | B86: 82-1397822 | C86: 10000 | D86: 15000 | E86: 10000 | G86: =SUM(C86:F86) -> 35000 | H86: Local
A87: Billion Oyster Project, Inc. | B87: 27-2918478 | C87: 10000 | D87: 10000 | E87: 10000 | G87: =SUM(C87:F87) -> 30000 | H87: A Greener NYC
A88: Friends of Alice Austen House, Inc. | B88: 13-3248928 | C88: 10000 | D88: 10000 | E88: 10000 | G88: =SUM(C88:F88) -> 30000 | H88: Cultural Immigrant
A89: Midtown Management Group, Inc. | B89: 13-3192793 | C89: 10000 | D89: 10000 | E89: 10000 | G89: =SUM(C89:F89) -> 30000 | H89: Cultural Immigrant
A90: Jewish Board of Family and Children's Servic | B90: 13-5564937 | C90: 10000 | D90: 10000 | E90: 10000 | G90: =SUM(C90:F90) -> 30000 | H90: Domestic Violence ; Local
A91: Pride Center of Staten Island, Inc. | B91: 46-3358895 | C91: 10000 | D91: 10000 | E91: 10000 | G91: =SUM(C91:F91) -> 30000 | H91: Domestic Violence
A92: City University of New York | B92: 13-3893536 | C92: 10000 | D92: 10000 | E92: 10000 | G92: =SUM(C92:F92) -> 30000 | H92: Local
A93: Grace Foundation of New York | B93: 13-4131863 | C93: 20000 | D93: 5000 | E93: 5000 | G93: =SUM(C93:F93) -> 30000 | H93: Local
A94: Friends of Abandoned Cemeteries, Inc. | B94: 13-3176456 | C94: 10000 | D94: 10000 | E94: 10000 | G94: =SUM(C94:F94) -> 30000 | H94: NYC Cleanup
A95: Silver Mount Cemetery Association, Inc. | B95: 13-5579013 | C95: 10000 | D95: 10000 | E95: 10000 | G95: =SUM(C95:F95) -> 30000 | H95: NYC Cleanup
A96: Department of Parks and Recreation | B96: 13-6400434 | C96: 10000 | D96: 10000 | E96: 10000 | G96: =SUM(C96:F96) -> 30000 | H96: Local; Parks Equity Initi
A97: Eagle Academy Foundation, Inc. | B97: 20-1532382 | C97: 10000 | D97: 10000 | E97: 10000 | G97: =SUM(C97:F97) -> 30000 | H97: Youth
A98: Fellowship Baptist Church | B98: 13-2865551 | D98: 15000 | E98: 15000 | G98: =SUM(C98:F98) -> 30000 | H98: Anti-Poverty
A99: Northfield Community LDC of Staten Island, I | B99: 13-2974137 | D99: 15000 | E99: 15000 | G99: =SUM(C99:F99) -> 30000 | H99: Neighborhood Devel
A100: Bee U, Inc. | B100: 88-1156617 | C100: 10000 | D100: 10500 | E100: 5000 | G100: =SUM(C100:F100) -> 25500 | H100: Local
A101: Eden II School for Autistic Children, Inc. | B101: 13-2872916 | C101: 15000 | D101: 5000 | E101: 5000 | G101: =SUM(C101:F101) -> 25000 | H101: Local; Youth
A102: PowerPlay NYC, Inc. | B102: 13-4045021 | C102: 15000 | D102: 5000 | E102: 5000 | G102: =SUM(C102:F102) -> 25000 | H102: Youth
A103: 2020 Vision for Schools, Inc. | B103: 45-3023036 | E103: 25000 | G103: =SUM(C103:F103) -> 25000 | H103: Parks Equity Initi
A104: African Refuge, Inc. | B104: 01-0873188 | E104: 25000 | G104: =SUM(C104:F104) -> 25000 | H104: Parks Equity Initi
A105: Dibra Community Organization, Inc. | B105: — | F105: 25000 | G105: =SUM(C105:F105) -> 25000
A106: University of Notre Dame Alumni Club of Stat | B106: 31-1344537 | C106: 5000 | D106: 5000 | E106: 10000 | G106: =SUM(C106:F106) -> 20000 | H106: Anti-Poverty; Food Pantries
A107: A Chance In Life | B107: 13-1835632 | C107: 10000 | D107: 10000 | G107: =SUM(C107:F107) -> 20000 | H107: Local
A108: Jeremiah Program | B108: 41-1801834 | C108: 10000 | D108: 10000 | G108: =SUM(C108:F108) -> 20000 | H108: Local
A109: Mt. Sinai Center for Community Enrichment, I | B109: 13-4082027 | E109: 20000 | G109: =SUM(C109:F109) -> 20000 | H109: Aging
...

Sheet Missed Items — Pages (Jul 7)
A1: ITEMS THE PDF FOUND THAT THE WORKBOOK SCAN MISSED — WITH SCHEDULE C PAGE TARGETS
A2: 26 rows · $1,703,107 · all now propagated into Master Line Items and Citywide-to-SI (yellow-flagged). Page targets derived from sibling rows in the same initiative; ranges are cluster estimates — confirm against the printed Schedule C before citing.
A4: Initiative | B4: Organization / Program | C4: EIN | D4: Amount | E4: Schedule C page target | F4: Status / note
A5: Welcome NYC | B5: Albanian-American Association of Ulqin, Inc. | C5: EIN PENDING | D5: 25000 | E5: p.151 (sibling: Dibra p.151) | F5: ADDED Jul 7 — PDF basis · was misfiled as Speaker
A6: Welcome NYC | B6: Dibra Community Organization, Inc. – New York City | C6: 27-4684048 | D6: 25000 | E6: p.151 (per Citywide tab) | F6: ADDED Jul 7 — F2 restore: was in Citywide tab, missing from Master
A7: LGBTQIA+ Youth Support and Services | B7: Project Hospitality, Inc. | C7: 13-3234441 | D7: 100000 | E7: p.228 (sibling: Pride Center p.228) | F7: ADDED Jul 7 — PDF basis
A8: Food Access and Benefits | B8: Project Hospitality, Inc. | C8: 13-3234441 | D8: 50000 | E8: search DOHMH/HRA cluster pp.122–171 | F8: ADDED Jul 7 — PDF basis · no sibling ref
A9: Children and Families in NYC Homeless System | B9: Project Hospitality, Inc. | C9: 13-3234441 | D9: 74000 | E9: search DHS/housing cluster pp.130–140 | F9: ADDED Jul 7 — PDF basis · no sibling ref
A10: Access Health Initiative | B10: Community Health Center of Richmond, Inc. | C10: EIN PENDING | D10: 93834 | E10: health cluster pp.122–127 | F10: ADDED Jul 7 — PDF basis
A11: Healthy Beginnings | B11: Community Health Center of Richmond, Inc. | C11: EIN PENDING | D11: 233523 | E11: p.123 (sibling: RMC p.123) | F11: ADDED Jul 7 — PDF basis
A12: MCCAP Initiative | B12: Community Health Center of Richmond, Inc. | C12: EIN PENDING | D12: 82000 | E12: p.125 (sibling: JCC p.125) | F12: ADDED Jul 7 — PDF basis
A13: Older Adults Mental Health | B13: Community Health Center of Richmond, Inc. | C13: EIN PENDING | D13: 50000 | E13: p.162 (sibling: JCC/CHCR p.162) | F13: ADDED Jul 7 — PDF basis
A14: Create New Technology Incubators | B14: City University of New York – College of Staten Island | C14: 13-3893536 (F7: confirm RF-CUNY) | D14: 500000 | E14: economic cluster pp.204–209 | F14: ADDED Jul 7 — PDF basis · EIN ruling F7 open
A15: Autism Awareness | B15: Grace Foundation of New York | C15: 13-4131863 | D15: 107372 | E15: p.156 (sibling: Eden II p.156) | F15: ADDED Jul 7 — PDF basis
A16: Coalition Theaters of Color | B16: Friends of Alice Austen House, Inc. | C16: 13-3248928 | D16: 70000 | E16: p.29 (sibling: Universal Temple p.29) | F16: ADDED Jul 7 — PDF basis
... A30: NYC RISE with Adult Literacy Forward | B30: Liberian Cultural Association, Inc. | C30: EIN PENDING | D30: 25000 | E30: p.18 (sibling: Adult Literacy p.18) | F30: ADDED Jul 7 — PDF basis
B31: TOTAL — MISSED ITEMS | D31: =SUM(D5:D30) -> 1703107
A33: EXACT-PAGE HITS (verify first, fastest wins): p.151 Welcome NYC (Ulqin, Dibra) · p.228 LGBTQIA+ Youth (PH) · p.123/125/162 CHCR trio · p.156 Grace · p.29 Alice Austen · p.170 SICS ×5 · p.163 IlluminArt opioid · p.18 Liberian.
A34: CLUSTER SEARCHES: DOHMH pp.122–171 (PH food/homeless, Atlas ×2, hate crimes) · economic/DSNY/SBS pp.204–209 (CUNY incubators, both BIDs) · youth pp.222–228 (Alice Austen students).
A35: EIN pulls outstanding (4): CHC Richmond · Ulqin · Liberian Cultural · New Dorp DMA — group census locks at 175+4 once pulled.

Sheet EIN Census (Jul 7)
A1: FY27 SI EXPENSE — UNIQUE ORGANIZATION CENSUS BY EIN · UPDATED WITH PDF BASIS (Jul 7)
A2: Basis: Master Line Items incl. 26 added PDF rows ($1,703,107). Category dollars labeled separately per house rule.
A4: EIN | B4: Organization (canonical) | C4: MDI SI-member $ | D4: MDI other-CM $ | E4: SI Delegation $ | F4: Speaker $ | G4: Citywide $ | H4: Expense total $ (this basis) | I4: Lines | J4: Name variants | K4: Sponsors seen
A5: 13-5562256 | B5: Jewish Community Center of Staten Island, Inc. | C5: 225000 | D5: 7000 | F5: 65000 | G5: 1048104 | H5: =SUM(C5:G5) -> 1345104 | I5: 28 | J5: 19 | K5: Carr; Hanks; Morano; Vernikov; —
A6: 47-2787706 | B6: La Colmena NYC, Inc. | G6: 1221666 | H6: =SUM(C6:G6) -> 1221666 | I6: 7 | J6: 3
A7: 46-3358895 | B7: Pride Center of Staten Island, Inc. | C7: 43000 | F7: 80000 | G7: 994375 | H7: =SUM(C7:G7) -> 1117375 | I7: 10 | J7: 5 | K7: Carr; Hanks; Morano; —
A8: 74-3177454 | B8: Richmond Medical Center | C8: 10000 | F8: 350000 | G8: 591797 | H8: =SUM(C8:G8) -> 951797 | I8: 8 | J8: 4 | K8: Carr; SI Delegation; —
A9: 13-3556132 | B9: Community Health Action of Staten Island, Inc. | C9: 65000 | G9: 799553 | H9: =SUM(C9:G9) -> 864553 | I9: 5 | J9: 3 | K9: Carr; Hanks
A10: 13-6400434 | B10: Department of Education | C10: 598500 | F10: 150000 | H10: =SUM(C10:G10) -> 748500 | I10: 91 | J10: 90 | K10: Carr; Hanks; Morano; —
A11: 23-7085239 | B11: New York Center for Interpersonal Development, Inc. | C11: 90000 | F11: 500000 | G11: 80000 | H11: =SUM(C11:G11) -> 670000 | I11: 4 | J11: 3 | K11: Carr; Hanks
A12: 13-3706442 | B12: Staten Island Economic Development Corporation | C12: 290000 | F12: 340000 | H12: =SUM(C12:G12) -> 630000 | I12: 17 | J12: 13 | K12: Carr; Carr+SI Del; Hanks; Morano; Morano
A13: 13-4069282 | B13: Staten Island Chamber of Commerce Foundation, Inc. | C13: 130000 | F13: 100000 | G13: 392765 | H13: =SUM(C13:G13) -> 622765 | I13: 12 | J13: 8 | K13: Carr; Hanks; Morano; SI Delegation; —
A14: 13-5680691 | B14: Staten Island Zoological Society, Inc. | C14: 125000 | F14: 417880 | H14: =SUM(C14:G14) -> 542880 | I14: 9 | J14: 8 | K14: Carr; Carr+Morano+SI Del; Hanks; Morano;
A15: 13-3893536 | B15: City University of New York | C15: 10000 | G15: 500000 | H15: =SUM(C15:G15) -> 510000 | I15: 2 | J15: 2 | K15: (citywide); Hanks
A16: 80-0193388 | B16: Careers & Stewardship Program Snug Harbor Cultural Center an | C16: 100000 | G16: 335000 | H16: =SUM(C16:G16) -> 435000 | I16: 7 | J16: 7 | K16: Carr; Hanks; Morano
A17: 42-1727647 | B17: IlluminArt Productions | C17: 240000 | G17: 155000 | H17: =SUM(C17:G17) -> 395000 | I17: 17 | J17: 14 | K17: (citywide); Carr; Hanks; Morano
A18: 45-0476945 | B18: Sundog Theatre, Inc. | C18: 297500 | G18: 42000 | H18: =SUM(C18:G18) -> 339500 | I18: 19 | J18: 18 | K18: Carr; Hanks; Morano
A19: 20-0404386 | B19: Heights Where to Turn, Inc. | C19: 305000 | H19: =SUM(C19:G19) -> 305000 | I19: 2 | J19: 2 | K19: Carr; Morano
A20: 13-2778244 | B20: Staten Island Community Services Friendship Clubs, Inc. | C20: 195000 | G20: 41665 | H20: =SUM(C20:G20) -> 236665 | I20: 14 | J20: 14 | K20: (citywide); Carr; Hanks; Morano
A21: 13-3234441 | B21: Project Hospitality, Inc. | C21: 5000 | G21: 224000 | H21: =SUM(C21:G21) -> 229000 | I21: 4 | J21: 2 | K21: (citywide); Morano
A22: 13-4131863 | B22: Grace Foundation of New York | C22: 55000 | E22: 10000 | F22: 50000 | G22: 107372 | H22: =SUM(C22:G22) -> 222372 | I22: 8 | J22: 4 | K22: (citywide); Carr; Carr+SI Del; Hanks; Mo
A23: 13-2974137 | B23: Northfield Community LDC of Staten Island, Inc. | G23: 213507 | H23: =SUM(C23:G23) -> 213507 | I23: 3 | J23: 3
A24: 13-2872916 | B24: Eden II School for Autistic Children, Inc. | C24: 50500 | E24: 15000 | F24: 25000 | G24: 109012 | H24: =SUM(C24:G24) -> 199512 | I24: 9 | J24: 7 | K24: Carr; Carr+Morano; Hanks; Morano; SI Del
A25: 13-1985514 | B25: Academy of Innovative Learning (31R065) Staten Island Histor | C25: 125000 | F25: 50000 | H25: =SUM(C25:G25) -> 175000 | I25: 8 | J25: 8 | K25: Carr; Carr+Morano+SI Del; Morano
A26: 13-3561657 | B26: City Parks Foundation | C26: 61000 | F26: 110000 | H26: =SUM(C26:G26) -> 171000 | I26: 4 | J26: 4 | K26: Hanks
A27: 45-3860014 | B27: New York City H2O | C27: 170000 | H27: =SUM(C27:G27) -> 170000 | I27: 8 | J27: 8 | K27: Carr; Hanks; Morano
A28: 13-3263537 | B28: Community Agency for Senior Citizens, Inc. | C28: 155000 | H28: =SUM(C28:G28) -> 155000 | I28: 8 | J28: 7 | K28: Carr; Hanks; Morano
A29: 13-5562286 | B29: Catholic Charities of Staten Island | C29: 150000 | H29: =SUM(C29:G29) -> 150000 | I29: 9 | J29: 8 | K29: Carr; Hanks; Morano
A30: 13-4012789 | B30: Dr. Theodore A. Atlas Foundation, Inc. | C30: 85000 | F30: 30000 | G30: 35000 | H30: =SUM(C30:G30) -> 150000 | I30: 9 | J30: 7 | K30: (citywide); Carr; Hanks
A31: 13-2921483 | B31: United Activities Unlimited, Inc. | C31: 100000 | F31: 50000 | H31: =SUM(C31:G31) -> 150000 | I31: 6 | J31: 2 | K31: Carr; Carr+SI Del; Morano
A32: 13-3335286 | B32: Universal Temple of the Arts, Inc. | C32: 30000 | F32: 50000 | G32: 70000 | H32: =SUM(C32:G32) -> 150000 | I32: 3 | J32: 3 | K32: Hanks
A33: 01-0873188 | B33: African Refuge, Inc. | F33: 50000 | G33: 100000 | H33: =SUM(C33:G33) -> 150000 | I33: 2 | J33: 2 | K33: —
A34: 13-3740011 | B34: Beautification & Horticulture | C34: 105500 | F34: 35000 | H34: =SUM(C34:G34) -> 140500 | I34: 8 | J34: 8 | K34: Carr; Hanks; Morano
A35: 82-4902021 | B35: Canvas Institute | C35: 65000 | F35: 75000 | H35: =SUM(C35:G35) -> 140000 | I35: 6 | J35: 5 | K35: Carr; Hanks; Morano; SI Delegation
A36: 13-3128315 | B36: On Your Mark, Inc. | C36: 70500 | E36: 9000 | F36: 35000 | G36: 25000 | H36: =SUM(C36:G36) -> 139500 | I36: 9 | J36: 7 | K36: Carr; Hanks; Morano; SI Delegation
A37: 13-3248928 | B37: Friends of Alice Austen House, Inc. | C37: 25000 | G37: 107500 | H37: =SUM(C37:G37) -> 132500 | I37: 5 | J37: 3 | K37: (citywide); Carr; Hanks; Morano
A38: 13-6202692 | B38: Chinese American Planning Council, Inc. | G38: 125000 | H38: =SUM(C38:G38) -> 125000 | I38: 2 | J38: 1
A39: 13-3046424 | B39: West Brighton Community Local Development Corporation | C39: 35000 | E39: 13000 | G39: 73070 | H39: =SUM(C39:G39) -> 121070 | I39: 5 | J39: 4 | K39: Hanks; SI Delegation
A40: 13-2738818 | B40: Metropolitan New York Coordinating Council on Jewish | C40: 112500 | H40: =SUM(C40:G40) -> 112500 | I40: 5 | J40: 5 | K40: Carr; Hanks; Morano
A41: 23-7379930 | B41: Staten Island Children's Museum | C41: 91000 | F41: 20000 | H41: =SUM(C41:G41) -> 111000 | I41: 7 | J41: 6 | K41: Carr; Hanks; Morano; —
A42: 92-1134292 | B42: Speaker Hanks Staten Island Immigrant Cen | F42: 50000 | G42: 50000 | H42: =SUM(C42:G42) -> 100000 | I42: 2 | J42: 2 | K42: Hanks
A43: 13-5563010 | B43: 49 Seamen's Society for Children and Families | C43: 35000 | E43: 5000 | G43: 52935 | H43: =SUM(C43:G43) -> 92935 | I43: 5 | J43: 3 | K43: Hanks; Morano; SI Delegation
A44: 32-0144539 | B44: Carl V. Bini Memorial Fund, The | C44: 30000 | E44: 20000 | F44: 40000 | H44: =SUM(C44:G44) -> 90000 | I44: 4 | J44: 3 | K44: Morano; SI Delegation
A45: 13-3524533 | B45: Eger Health Care and Rehabilitation Center | C45: 87500 | H45: =SUM(C45:G45) -> 87500 | I45: 3 | J45: 3 | K45: Carr; Morano
A46: 45-4661688 | B46: Muslim American Society of Brooklyn and Staten Island (CD47) | D46: 85000 | H46: =SUM(C46:G46) -> 85000 | I46: 5 | J46: 4 | K46: Aviles; Santosuosso
A47: 13-2600199 | B47: Legal Services NYC | C47: 80000 | H47: =SUM(C47:G47) -> 80000 | I47: 3 | J47: 3 | K47: Carr; Hanks; Morano
A48: 81-0728516 | B48: Morano, Staten Speaker Island South Shore | C48: 25000 | F48: 45000 | H48: =SUM(C48:G48) -> 70000 | I48: 2 | J48: 2 | K48: Morano; Morano+SI Del
A49: 13-5564127 | B49: 057R Hubert H. Humphrey (31R057) Staten Island Institute of | C49: 65000 | H49: =SUM(C49:G49) -> 65000 | I49: 4 | J49: 4 | K49: Carr; Hanks; Morano
A50: 37-1833463 | B50: Staten Island Urban Center | G50: 64576 | H50: =SUM(C50:G50) -> 64576 | I50: 1 | J50: 1
A51: 26-4411728 | B51: Casa Belvedere, The Italian Cultural Foundation | C51: 42500 | E51: 20000 | H51: =SUM(C51:G51) -> 62500 | I51: 6 | J51: 3 | K51: Carr; Hanks; Morano; SI Delegation
A52: 13-3062419 | B52: Intrepid Museum Foundation, Inc. | C52: 60000 | H52: =SUM(C52:G52) -> 60000 | I52: 3 | J52: 3 | K52: Morano
A53: 13-3047206 | B53: (75R037) Marquis Studios, Ltd. | C53: 60000 | H53: =SUM(C53:G53) -> 60000 | I53: 3 | J53: 3 | K53: Hanks; Morano
A54: 85-2810883 | B54: Justice Innovation, Inc. | C54: 60000 | H54: =SUM(C54:G54) -> 60000 | I54: 2 | J54: 2 | K54: Hanks
A55: 27-3218865 | B55: Ballroom Basix USA, Inc. | C55: 55000 | H55: =SUM(C55:G55) -> 55000 | I55: 4 | J55: 4 | K55: Hanks; Morano
A56: 13-3176456 | B56: Cleanup Series Support | C56: 50000 | H56: =SUM(C56:G56) -> 50000 | I56: 3 | J56: 3 | K56: Carr; Hanks; Morano
A57: 13-3846431 | B57: Homeless, Inc. | C57: 50000 | H57: =SUM(C57:G57) -> 50000 | I57: 2 | J57: 2 | K57: Hanks
A58: 11-2665181 | B58: Jewish Community Council of Greater Coney Island, Inc. | F58: 50000 | H58: =SUM(C58:G58) -> 50000 | I58: 1 | J58: 1 | K58: —
A59: 27-4684048 | B59: Dibra Community Organization, Inc. | F59: 25000 | G59: 25000 | H59: =SUM(C59:G59) -> 50000 | I59: 2 | J59: 2 | K59: (citywide); Hanks
A60: 37-1469112 | B60: United Chinese Association of Brooklyn | G60: 50000 | H60: =SUM(C60:G60) -> 50000 | I60: 1 | J60: 1
A61: 13-4055215 | B61: National Lighthouse Museum | C61: 45000 | H61: =SUM(C61:G61) -> 45000 | I61: 4 | J61: 3 | K61: Carr; Hanks
A62: 20-2732542 | B62: Albert V. Maniscalco (31R046) Staten Island Philharmonic Orc | C62: 42000 | H62: =SUM(C62:G62) -> 42000 | I62: 3 | J62: 3 | K62: Carr; Hanks; Morano
A63: 13-3481845 | B63: Greenbelt Conservancy, Inc. | C63: 40000 | H63: =SUM(C63:G63) -> 40000 | I63: 1 | J63: 1 | K63: Carr
A64: 13-6192346 | B64: Roundabout Theatre Company, Inc. | C64: 40000 | H64: =SUM(C64:G64) -> 40000 | I64: 3 | J64: 3 | K64: Hanks; Morano
A65: 13-3973196 | B65: Mouse, Inc. | C65: 40000 | H65: =SUM(C65:G65) -> 40000 | I65: 2 | J65: 2 | K65: Hanks; Morano
A66: 14-1933279 | B66: Forest Avenue District Management Association, Inc. | C66: 5000 | G66: 35000 | H66: =SUM(C66:G66) -> 40000 | I66: 2 | J66: 2 | K66: (citywide); Hanks
A67: 87-3354678 | B67: Integrated Athletic Initiative Corp | C67: 40000 | H67: =SUM(C67:G67) -> 40000 | I67: 4 | J67: 3 | K67: Carr; Hanks; Morano
A68: 13-6162802 | B68: Staten Island Little League, Inc. | C68: 13500 | F68: 25000 | H68: =SUM(C68:G68) -> 38500 | I68: 3 | J68: 1 | K68: Carr
A69: 13-2720248 | B69: Carmel Richmond Nursing Home | C69: 37000 | H69: =SUM(C69:G69) -> 37000 | I69: 2 | J69: 2 | K69: Carr
A70: 93-1542543 | B70: & Council District 9 Albanian American Association of Staten | C70: 35000 | H70: =SUM(C70:G70) -> 35000 | I70: 2 | J70: 2 | K70: Carr; Morano
A71: 11-2507910 | B71: Federation of Italian American Organizations of Brooklyn, Lt | C71: 34000 | H71: =SUM(C71:G71) -> 34000 | I71: 3 | J71: 2 | K71: Carr
A72: 32-0048308 | B72: Council District 51 Staten Island Youth Soccer League, Inc. | C72: 32500 | H72: =SUM(C72:G72) -> 32500 | I72: 2 | J72: 2 | K72: Carr; Morano
A73: 51-0171818 | B73: District 10 Citizens Committee for New York City, Inc. | C73: 30000 | H73: =SUM(C73:G73) -> 30000 | I73: 2 | J73: 2 | K73: Hanks
A74: 20-5857329 | B74: Richmond County Youth Complex, Inc. | C74: 30000 | H74: =SUM(C74:G74) -> 30000 | I74: 2 | J74: 2 | K74: Carr
A75: 13-5562191 | B75: Children's Aid Society, The | C75: 30000 | H75: =SUM(C75:G75) -> 30000 | I75: 2 | J75: 2 | K75: Hanks
A76: 92-2412852 | B76: Staten Island Industrial Alliance/Northshore Leadership Alli | C76: 30000 | H76: =SUM(C76:G76) -> 30000 | I76: 1 | J76: 1 | K76: Hanks
A77: 33-3459695 | B77: Kresischer Mansion Historical Preservation Society Corp. | C77: 30000 | H77: =SUM(C77:G77) -> 30000 | I77: 4 | J77: 2 | K77: Carr; Hanks; Morano
A78: 61-1682898 | B78: Council District 41 ArtBridge Projects, Inc. | C78: 30000 | H78: =SUM(C78:G78) -> 30000 | I78: 1 | J78: 1 | K78: Morano
A79: 45-2493342 | B79: Council District 15 Grasmere and Cameron Lakes Bluebelt Cons | C79: 30000 | H79: =SUM(C79:G79) -> 30000 | I79: 1 | J79: 1 | K79: Carr
A80: 13-1624015 | B80: Scouts of America | C80: 30000 | H80: =SUM(C80:G80) -> 30000 | I80: 3 | J80: 3 | K80: Carr; Hanks; Morano
A81: 13-5604699 | B81: Wagner College | C81: 5000 | G81: 25000 | H81: =SUM(C81:G81) -> 30000 | I81: 2 | J81: 2 | K81: (citywide); Hanks
A82: 13-3351673 | B82: Noble Maritime Collection, The | C82: 25000 | H82: =SUM(C82:G82) -> 25000 | I82: 3 | J82: 3 | K82: Hanks; Morano
A83: 46-5288351 | B83: Oceanic Hook and Ladder Co. No. 1, Inc. | C83: 25000 | H83: =SUM(C83:G83) -> 25000 | I83: 2 | J83: 1 | K83: Carr
A84: 11-3828185 | B84: Emergency Children's Help Organization, Inc. | C84: 25000 | H84: =SUM(C84:G84) -> 25000 | I84: 3 | J84: 2 | K84: Carr; Hanks; Morano
A85: 13-1624228 | B85: Young Men's Christian Association of Greater New York | C85: 25000 | H85: =SUM(C85:G85) -> 25000 | I85: 3 | J85: 3 | K85: Carr; Hanks; Morano
A86: 06-1725844 | B86: Garibaldi-Meucci Museum | C86: 25000 | H86: =SUM(C86:G86) -> 25000 | I86: 3 | J86: 2 | K86: Carr; Hanks
A87: 90-0730331 | B87: Community Programs | C87: 25000 | H87: =SUM(C87:G87) -> 25000 | I87: 2 | J87: 2 | K87: Carr; Morano
A88: 13-2612524 | B88: Council District 05 Fund for the City of New York, Inc. | C88: 25000 | H88: =SUM(C88:G88) -> 25000 | I88: 2 | J88: 2 | K88: Carr; Hanks
A89: 13-3833390 | B89: Staten Island Sports Hall of Fame, Inc. | C89: 21000 | H89: =SUM(C89:G89) -> 21000 | I89: 3 | J89: 1 | K89: Carr; Hanks; Morano
A90: 27-2918478 | B90: District 46 Billion Oyster Project, Inc. | C90: 20000 | H90: =SUM(C90:G90) -> 20000 | I90: 2 | J90: 2 | K90: Hanks; Morano
A91: 84-1678085 | B91: Advocacy Program | C91: 20000 | H91: =SUM(C91:G91) -> 20000 | I91: 2 | J91: 2 | K91: Morano
A92: 88-2507208 | B92: Adults | C92: 20000 | H92: =SUM(C92:G92) -> 20000 | I92: 2 | J92: 2 | K92: Hanks
A93: 13-2894978 | B93: partnership program Meals on Wheels of Staten Island, Inc. | C93: 20000 | H93: =SUM(C93:G93) -> 20000 | I93: 2 | J93: 2 | K93: Carr; Hanks
... A113: 13-4045021 | B113: PowerPlay NYC, Inc. | C113: 15000 | H113: =SUM(C113:G113) -> 15000 | I113: 2 | J113: 2 | K113: Hanks
A114: 13-2943389 | B114: Richmond Engine Company No. 1 | E114: 15000 | H114: =SUM(C114:G114) -> 15000 | I114: 1 | J114: 1 | K114: SI Delegation
A115: 13-2939069 | B115: Staten Island Ice Hockey Association, Inc. | C115: 10000 | E115: 3000 | H115: =SUM(C115:G115) -> 13000 | I115: 3 | J115: 2 | K115: Carr; Morano; SI Delegation
A116: 01-0611469 | B116: Friends of Firefighters, Inc. | C116: 12500 | H116: =SUM(C116:G116) -> 12500 | I116: 2 | J116: 2 | K116: Carr; Morano
A117: 13-6216919 | B117: Theatre Development Fund, Inc. | C117: 11500 | H117: =SUM(C117:G117) -> 11500 | I117: 1 | J117: 1 | K117: Morano
A118: 45-2871053 | B118: Health Essential Association, Inc. | C118: 10000 | H118: =SUM(C118:G118) -> 10000 | I118: 1 | J118: 1 | K118: Carr
A119: 92-0875945 | B119: TraNa Relief Association | C119: 10000 | H119: =SUM(C119:G119) -> 10000 | I119: 2 | J119: 2 | K119: Morano
A120: 13-1624014 | B120: Girl Scout Council of Greater New York, Inc. | C120: 10000 | H120: =SUM(C120:G120) -> 10000 | I120: 1 | J120: 1 | K120: Morano
...

Sheet Grand Total
A1: FY2027 STATEN ISLAND — CAPITAL + EXPENSE, COMBINED
A2: Capital: FY27 Adopted Section 254 capital changes (CC-verified Jul 1) + adopted capital workbook + office review Jul 2 (St. George add-on; $230K exclusion). Expense: Schedule C Final-3 parsed & reconciled; member figures tie the Council discretionary database.
A4: Component | B4: Amount | C4: Basis / source
A5: CAPITAL — Borough R (11 categories) | B5: 67964000 | C5: Section 254; Parks $22.908M … Higher Ed $500K
A6: CAPITAL — CC1100 SI DOT Trees & Sidewalk (Boro X-coded, SI Parks line D020) | B6: 3536000 | C6: Section 254; Speaker + Morano
A7: CAPITAL — MA1004 St. George Theatre ($5.85M, non-City section II/III — Measure-C-side wallet) | B7: 5850000 | C7: MA1004, PV 0N364, §254 V4 PDF p.67 — DOC-VERIFIED; org total $7,350,000 incl $1.5M CC (Carr/Hanks/Speaker $500K each)
A8: CAPITAL — SI-substantive total | B8: =B5+B6+B7 -> 77350000 | C8: Sum of the three lines above
A9: EXPENSE — MDIs, SI delegation members (printed) | B9: 6638000 | C9: Schedule C Final-3; database-tied
A10: EXPENSE — SI Delegation pot (Boroughwide, p.4) | B10: 120000 | C10: Schedule C Final-3
A11: EXPENSE — Speaker funding to SI | B11: 2817880 | C11: Pool $1.45M + designated $670K + untagged $698K
A12: EXPENSE — MDIs, other CMs to SI orgs | B12: 92000 | C12: MAS Bklyn&SI (bi-borough) + JCC-SI
A13: EXPENSE — Citywide initiatives to SI | B13: 6553360 | C13: 42 initiatives · 55 organization lines; Citywide tab (org-itemized) — rev Jul 6: +$25,000 Dibra/Welcome NYC p.151
A14: EXPENSE — printed SI total | B14: =SUM(B9:B13) -> 16221240 | C14: Scan basis
A15: EXPENSE — SU-CASA (database, unitemized) | B15: 90000 | C15: DB Jul 1; $3.825M pot 100% post-adoption
A16: GRAND — CAPITAL + EXPENSE, ALL-IN | B16: =B8+B14+B15 -> 93661240 | C16: SI-substantive capital + full expense scan + SU-CASA
A18: EXCLUDED & FLAGGED
A19: CC0796 (P.S./I.S. 229, Carr) — Boro-coded R, Brooklyn school codes: currently INSIDE the $71.5M; if Brooklyn, CC total → $71,270,000 | B19: 230000 | C19: DOC-VERIFIED as printed (B:K229 S:K229); Finance confirmation pending; §254 V4
A21: OFFICIAL MEASURES (stated bases — never blend)
A22: Measure A — delegation-controlled (established Jul 1) | B22: 74812000 | C22: Basis: Boro-R capital $67,964,000 + delegation discretionary $6,848,000
A23: Measure B — SI-substantive capital + delegation discretionary (established) | B23: 78348000 | C23: Basis: $71,500,000 + $6,848,000
A24: Measure B — recomputed with St. George add-on (PENDING adoption) | B24: 84198000 | C24: Basis: $77,350,000 + $6,848,000
A25: Measure C — all dollars reaching SI orgs, est. (established) | B25: 84018000 | C25: Basis: $71.5M + $6.848M + citywide-to-SI est $5.67M
A26: Measure C — recomputed with St. George add-on (PENDING adoption) | B26: 89868000 | C26: Basis: established C + $5,850,000
A27: Full-scan combined (this workbook) | B27: =B8+B14+B15 -> 93661240 | C27: Basis: $77.35M capital + $16,196,240 + SU-CASA $90K — broader than Measure C
A29: PROJECTION — ASSUMPTION LINE (not folded into confirmed totals)
A30: Morano SU-CASA assumed at delegation parity: 3 sites × $15,000 | B30: 45000 | C30: Assumption basis: Hanks and Carr each designated exactly 3×$15,000; D51 undesignated as of DB export
A31: PROJECTED GRAND — capital + expense, all-in, if realized | B31: =B16+B30 -> 93706240 | C31: Cascade if realized: delegation discretionary $6,848,000 → $6,893,000; Measures A/B/C each +$45,000 (A → $74,857,000)
A32: §254 context (as printed): Council Additions $853,688,000 · Rescindments ($23,317,000) · Net Change $830,371,000
A34: PDF ALL-FUNDING BASIS — APPLIED Jul 7, 2026 (do not mix with printed-basis lines above)
A35: Capital — SI-substantive (unchanged) | B35: 77350000 | C35: Ties existing three-component basis
A36: Expense — baseline CM pots (PDF allocation basis) | B36: 6773000 | C36: Hanks $2,295,000 · Carr $2,270,000 · Morano $2,208,000
A37: Expense — Speaker, corrected (F1: Ulqin + Project Hospitality removed) | B37: 2817880 | C37: Ties this tab’s prior Speaker line
A38: Expense — Citywide, PDF basis (90 lines) | B38: 8341467 | C38: Prior scan $6,553,360 + 26 added rows − Dibra dup − WB-only $10,000 + Delegation reclass — see Citywide Reconcile
A39: EXPENSE TOTAL — PDF corrected basis | B39: =SUM(B36:B38) -> 17932347 | C39: formula
A40: GRAND TOTAL — PDF corrected basis | B40: =B35+B39 -> 95282347 | C40: Equals printed PDF $95,332,347 less $50,000 F1
A41: GRAND TOTAL — PDF as printed | B41: 95332347 | C41: All-Funding PDF p.1

Sheet Source & Search Guide
A1: WHERE EVERY SI DOLLAR IS SEARCHABLE — PUBLIC SOURCE & SEARCH GUIDE
A2: Each channel in this workbook mapped to its public lookup path, with search keys and caveats. Verified Jul 2, 2026.
A4: What | B4: Where (public source) | C4: How to search | D4: Caveats
A5: Expense — every Schedule C line (MDIs, Speaker, citywide, delegation) | B5: Schedule C PDF — council.nyc.gov/budget/schedule-c/ | C5: By page (this workbook cites each line’s page); Ctrl-F org name or EIN in the PDF | D5: Revisions replace the posted file (Final → Final-3); post-adoption items (e.g., SU-CASA) absent until itemized
A6: Expense — dataset form, filter/sort/export | B6: NYC Open Data — "New York City Council Discretionary Funding" (dataset 4d7f-74pe, data.cityofnewyork.us) | C6: Filter by Council Member, organization, fiscal year; export CSV | D6: Reflects applications/allocations cycle; confirm against Schedule C for adopted status
A7: Expense — award clearance status per org | B7: MOCS Discretionary Award Tracker (nyc.gov/mocs → PASSPort articles) | C7: Search org LEGAL NAME or full EIN WITHOUT the dash; cleared = "Cleared – Contact Contracting Agency" | D7: Updates only every 6–8 weeks; defunded/reallocated awards may not display; Transparency-Resolution awards lag until Council transmits
A8: Expense — in-year changes & SU-CASA-type post-adoption itemization | B8: Transparency Resolutions — Legistar (legistar.council.nyc.gov) | C8: Search "Transparency Resolution" by stated-meeting date; designations list org, EIN, sponsor, amount | D8: This is where the pending SU-CASA names (incl. any Morano designations) will first appear
A9: Expense — actual payments to an org | B9: Checkbook NYC (checkbooknyc.com, Comptroller) | C9: Payee search by org name; filter agency & FY | D9: Shows spending once contracts register — lags designation by months
A10: Capital — every §254 Council addition (CC lines) | B10: §254 Supporting Detail PDF — council.nyc.gov budget page (this file: V4) | C10: By SUB ID (CC####) or PDF page as cited on the §254 tabs; Ctrl-F project title | D10: SPON column carries co-sponsorship in V4; CC0796 caveat noted
A11: Capital — MA/non-City lines (e.g., MA1004 St. George $5.85M) | B11: Same §254 PDF, Sections II & III (non-City detail + by-entity totals) | C11: Section III by ORGANIZATION for true org totals (St. George $7,350,000) | D11: MA lines excluded from the $853,688,000 Council Additions; no sponsor printed
A12: Capital — commitments & spend over time | B12: OMB Adopted Capital Commitment Plan (nyc.gov/omb) · Checkbook NYC capital | C12: Budget line (e.g., PV D477, HL DN404) in OMB; payee/project in Checkbook | D12: Commitment ≠ designation; timing spans years
A13: Capital — non-City org applications | B13: CapGrants portal (council.nyc.gov budget page) | C13: Org-side application records | D13: Application-side only
A14: Internal (not public) | B14: ExportedSearchResults.xlsx — Council Finance export | C14: This workbook’s member tabs; per-EIN, incl. SU-CASA pre-publication | D14: Authoritative for member designations; richer and earlier than any public source — do not cite externally

Sheet SI History FY23–27
A1: STATEN ISLAND SEATS — FIVE-YEAR MEMBER-DESIGNATED HISTORY (FY2023–FY2027)
A2: FY23–26: Council funded-disclosure workbook (all CMs). FY27: Council Finance database export. Same basis — member-designated designations incl. SU-CASA where filed.
A4: Seat / measure | B4: FY2023 | C4: FY2024 | D4: FY2025 | E4: FY2026 | F4: FY2027 | G4: 5-yr total | H4: Note
A5: Hanks (D49) | B5: 2295000 | C5: 2295000 | D5: 2365000 | E5: 2295000 | F5: 2295000 | G5: =SUM(B5:F5) -> 11545000 | H5: FY25 +$70,000 = one-year Food Pantries allocation — the entire bump
A6: Carr (D50) | B6: 2270000 | C6: 2270000 | D6: 2270000 | E6: 2270000 | F6: 2270000 | G6: =SUM(B6:F6) -> 11350000 | H6: Perfectly flat across all five years
A7: D51 seat — Borelli (FY23–25) → Morano (FY26–27) | B7: 2208000 | C7: 2208000 | D7: 2208000 | E7: 2208000 | F7: 2163000 | G7: =SUM(B7:F7) -> 10995000 | H7: Seat allocation identical through the special-election transition; FY27 −$45,000 = unfiled SU-CASA only
A8: THREE-SEAT TOTAL | B8: =SUM(B5:B7) -> 6773000 | C8: =SUM(C5:C7) -> 6773000 | D8: =SUM(D5:D7) -> 6843000 | E8: =SUM(E5:E7) -> 6773000 | F8: =SUM(F5:F7) -> 6728000 | G8: =SUM(B8:F8) -> 33890000 | H8: FY23–26 flat ~$6.77M; FY27 $6.73M pending SU-CASA
A9: SI Delegation pot | B9: 12000 | C9: 120000 | D9: 120000 | E9: 120000 | F9: 120000 | G9: =SUM(B9:F9) -> 492000 | H9: FY27 basis = Boroughwide Needs pot; −$378,213 vs FY26 — FLAGGED (basis check + Finance question pending)
A10: Citywide member-designated total | B10: 116261000 | C10: 116261000 | D10: 117276000 | E10: 118111000 | F10: 109853997 | G10: =SUM(B10:F10) -> 577762997 | H10: FY27 = Finance export subset; FY23–26 = disclosure totals
A11: SI three-seat share of citywide | B11: =B8/B10 -> 0.058256853 | C11: =C8/C10 -> 0.058256853 | D11: =D8/D10 -> 0.058349534 | E11: =E8/E10 -> 0.057344363 | F11: =F8/F10 -> 0.061244927 | H11: ≈ seat share (3/51 = 5.88%); the parity gap lives in citywide pots, not member money
A13: TIER STABILITY (formula placements, all five years): Hanks DoVE $195,000 & Anti-Poverty $50,000 every year; D51 seat DoVE $133,000 & Anti-Poverty $25,000 every year under both Borelli and Morano — the FY27 spreads are historic and structural, not annual discretion. Zero defunded/reallocated rows for any SI member, FY23–26.
A17: Yellow means under evaluation, should all be 120k a year

Sheet SI History — Continuity
A1: CONTINUITY VIEW — HANKS TOP ORGANIZATIONS ACROSS FIVE YEARS, AND THE D51 TRANSITION
A2: D51 smooth-transfer datapoint: Morano carried 74 of his 81 FY2026 organizations directly from Borelli’s FY2025 book — 91% continuity through the special election.
A4: Organization | B4: FY2023 | C4: FY2024 | D4: FY2025 | E4: FY2026 | F4: FY2027 | G4: 5-yr total
A5: Department of Sanitation | B5: 205000 | C5: 200000 | D5: 200000 | E5: 150000 | F5: 180000 | G5: =SUM(B5:F5) -> 935000
A6: Community Agency for Senior Citizens, Inc. | B6: 60000 | C6: 65000 | D6: 90000 | E6: 70000 | F6: 80000 | G6: =SUM(B6:F6) -> 365000
A7: Staten Island Chamber of Commerce Foundation, Inc. | B7: 45000 | C7: 70000 | D7: 50000 | E7: 75000 | F7: 120000 | G7: =SUM(B7:F7) -> 360000
A8: Snug Harbor Cultural Center & Botanical Garden | B8: 70000 | C8: 70000 | D8: 65000 | E8: 65000 | F8: 65000 | G8: =SUM(B8:F8) -> 335000
A9: New York Center for Interpersonal Development, Inc. | B9: 5000 | C9: 80000 | D9: 80000 | E9: 80000 | F9: 80000 | G9: =SUM(B9:F9) -> 325000
A10: Dr. Theodore A. Atlas Foundation, Inc. | B10: 5000 | C10: 35000 | D10: 97500 | E10: 84500 | F10: 80000 | G10: =SUM(B10:F10) -> 302000
A11: IlluminArt Productions | B11: 60000 | C11: 60000 | D11: 55000 | E11: 55000 | F11: 45000 | G11: =SUM(B11:F11) -> 275000
A12: City Parks Foundation | B12: 70000 | C12: 50000 | D12: 25000 | E12: 45000 | F12: 61000 | G12: =SUM(B12:F12) -> 251000
A13: Jewish Community Center of Staten Island, Inc. | B13: 50000 | C13: 50000 | D13: 50000 | E13: 50000 | F13: 50000 | G13: =SUM(B13:F13) -> 250000
A14: Department of Education | B14: 45500 | C14: 46500 | D14: 44000 | E14: 49000 | F14: 49000 | G14: =SUM(B14:F14) -> 234000
A15: Catholic Charities of Staten Island | B15: 55000 | C15: 55000 | D15: 30000 | E15: 30000 | F15: 60000 | G15: =SUM(B15:F15) -> 230000
A16: Seamen's Society for Children and Families | B16: 45000 | C16: 45000 | D16: 75000 | E16: 25000 | F16: 25000 | G16: =SUM(B16:F16) -> 215000
A18: Reading the trends: SI Chamber of Commerce Fdn rising ($45K → $120K, +167% over five years — the economic-development pillar compounding); NYCID stable at $80K since FY24 (plus the $500K Speaker Credible Messengers item on top); Snug Harbor ($65K) and JCC-SI ($50K) flat as institutional anchors; Seamen’s Society tapered after FY25. Supports the FY27 Seed → FY28 Grow succession framework.

Sheet §254 SI Capital (Sec I)
A1: FY 2027 CHANGES TO THE EXECUTIVE CAPITAL BUDGET PURSUANT TO SECTION 254 — CAPITAL PROJECT DETAIL (STATEN ISLAND LINES)
A2: Source: Supporting Detail V4 (uploaded Jul 2) — every Boro-R line plus CC1100 (Boro X, SI-substantive). Exact document style; SPON as printed.
A4: PHILOSOPHY PLAYGROUND RENOVATION
A5: SUB ID | B5: BUDGET LINE | C5: BORO | D5: PROJECT TITLE | E5: FY 2027 | F5: FY 2028 | G5: FY 2029 | H5: FY 2030 | I5: SPON | J5: PDF p.
A6: CC0791 | B6: ED001 | C6: R | D6: I.S.2 TECH UPGRADES B:R002 S:R002 | E6: 75000 | F6: 0 | G6: 0 | H6: 0 | I6: CARR | J6: 28
A7: CC0792 | B7: ED001 | C7: R | D7: I.S. 51 TECH UPGRADES B:R051 S:R051 | E7: 75000 | F7: 0 | G7: 0 | H7: 0 | I7: CARR | J7: 28
A8: CC0793 | B8: ED001 | C8: R | D8: P.S./I.S. 26 PARKING LOT B:R026 S:R026 | E8: 100000 | F8: 0 | G8: 0 | H8: 0 | I8: CARR | J8: 28
A9: CC0794 | B9: ED001 | C9: R | D9: P.S. 30 TECH UPGRADES B:R030 S:R030 | E9: 75000 | F9: 0 | G9: 0 | H9: 0 | I9: CARR | J9: 28
A10: CC0795 | B10: ED001 | C10: R | D10: P.S./I.S. 48 TECH UPGRADES B:R071 S:R048 | E10: 75000 | F10: 0 | G10: 0 | H10: 0 | I10: CARR | J10: 28
A11: CC0796 | B11: ED001 | C11: R | D11: P.S./I.S. 229 TECH UPGRADES B:K229 S:K229 | E11: 230000 | F11: 0 | G11: 0 | H11: 0 | I11: CARR | J11: 28
A12: CC0797 | B12: ED001 | C12: R | D12: P.S. 9 TECH UPGRADES B:R048 S:R009 | E12: 75000 | F12: 0 | G12: 0 | H12: 0 | I12: CARR | J12: 28
A13: CC0798 | B13: ED001 | C13: R | D13: P.S. 11 TECH UPGRADES B:R011 S:R011 | E13: 75000 | F13: 0 | G13: 0 | H13: 0 | I13: CARR | J13: 28
A14: CC0799 | B14: ED001 | C14: R | D14: P.S. 23 TECH UPGRADES B:R023 S:R023 | E14: 75000 | F14: 0 | G14: 0 | H14: 0 | I14: CARR | J14: 28
A15: CC0800 | B15: ED001 | C15: R | D15: P.S. 29 TECH UPGRADES B:R029 S:R029 | E15: 100000 | F15: 0 | G15: 0 | H15: 0 | I15: CARR | J15: 29
A16: CC0801 | B16: ED001 | C16: R | D16: P.S. 38 TECH UPGRADES B:R038 S:R038 | E16: 75000 | F16: 0 | G16: 0 | H16: 0 | I16: CARR | J16: 29
A17: CC0802 | B17: ED001 | C17: R | D17: P.S.39 GYM CONVERSION B:R039 S:R039 | E17: 500000 | F17: 0 | G17: 0 | H17: 0 | I17: CARR | J17: 29
... A52: CC0847 | B52: ED001 | C52: R | D52: I.S. 63 TECH UPGRADE B:R043 S:R063 | E52: 75000 | F52: 0 | G52: 0 | H52: 0 | I52: MORANO | J52: 30
D53: TOTALS FOR PHILOSOPHY PLAYGROUND RENOVATION (47 PROJECTS) | E53: =SUM(E6:E52) -> 7126000
A55: HEALTH AIDE & MEDICAL ASSISTANCE
A56: SUB ID | B56: BUDGET LINE | C56: BORO | D56: PROJECT TITLE | E56: FY 2027 | F56: FY 2028 | G56: FY 2029 | H56: FY 2030 | I56: SPON | J56: PDF p.
A57: CC0896 | B57: ED001 | C57: R | D57: P.S. 019 THE CURTIS SCHOOL TECH UPGRADES B:R019 S:R019 | E57: 75000 | F57: 0 | G57: 0 | H57: 0 | I57: HANKS | J57: 31
A58: CC0897 | B58: ED001 | C58: R | D58: P.S. 044 THOMAS C. BROWN TECH UPGRADE B:R044 S:R044 | E58: 70000 | F58: 0 | G58: 0 | H58: 0 | I58: HANKS | J58: 31
A59: CC0898 | B59: ED001 | C59: R | D59: P.S. 057 HUBERT H. HUMPHREY GYM UPGRADE B:R057 S:R057 | E59: 75000 | F59: 0 | G59: 0 | H59: 0 | I59: HANKS | J59: 31
A60: CC0899 | B60: ED001 | C60: R | D60: I.S. 49 BERTA A. DREYFUS STEAM LAB B:R049 S:R049 | E60: 250000 | F60: 0 | G60: 0 | H60: 0 | I60: HANKS | J60: 31
A61: CC0900 | B61: ED001 | C61: R | D61: THE EAGLE ACADEMY FOR YOUNG MEN OF STATEN ISLAND TECH UPGRADES B:R028 S:R028 | E61: 150000 | F61: 0 | G61: 0 | H61: 0 | I61: HANKS | J61: 31
A62: CC0901 | B62: ED001 | C62: R | D62: STATEN ISLAND SCHOOL OF CIVIC LEADERSHIP TECH UPGRADES B:R861 S:R861 | E62: 150000 | F62: 0 | G62: 0 | H62: 0 | I62: HANKS | J62: 31
D63: TOTALS FOR HEALTH AIDE & MEDICAL ASSISTANCE (6 PROJECTS) | E63: =SUM(E57:E62) -> 770000
A65: AND SOCIAL CHANGE CULINARY ARTS AND
A66: SUB ID | B66: BUDGET LINE | C66: BORO | D66: PROJECT TITLE | E66: FY 2027 | F66: FY 2028 | G66: FY 2029 | H66: FY 2030 | I66: SPON | J66: PDF p.
A67: CC1094 | B67: ED001 | C67: R | D67: P.S.50 PLAYGROUND RENOVATION | E67: 2000000 | F67: 0 | G67: 0 | H67: 0 | I67: SPEAKER CARR | J67: 34
A68: CC1095 | B68: ED001 | C68: R | D68: P.S. 60 PLAYGROUND RENOVATION | E68: 1800000 | F68: 0 | G68: 0 | H68: 0 | I68: SPEAKER CARR | J68: 34
D69: TOTALS FOR AND SOCIAL CHANGE CULINARY ARTS AND (2 PROJECTS) | E69: =SUM(E67:E68) -> 3800000
A71: ECONOMIC DEVELOPMENT
A72: SUB ID | B72: BUDGET LINE | C72: BORO | D72: PROJECT TITLE | E72: FY 2027 | F72: FY 2028 | G72: FY 2029 | H72: FY 2030 | I72: SPON | J72: PDF p.
A73: CC1090 | B73: EDD075 | C73: R | D73: NORTH SHORE ACTION PLAN - TOMPKINSVILLE | E73: 7000000 | F73: 0 | G73: 0 | H73: 0 | I73: SPEAKER HANKS | J73: 37
D74: TOTALS FOR ECONOMIC DEVELOPMENT (1 PROJECTS) | E74: =SUM(E73) -> 7000000
A76: ESPLANADE PROJECT
A77: SUB ID | B77: BUDGET LINE | C77: BORO | D77: PROJECT TITLE | E77: FY 2027 | F77: FY 2028 | G77: FY 2029 | H77: FY 2030 | I77: SPON | J77: PDF p.
A78: CC1092 | B78: EDD075 | C78: R | D78: PIER ONE FISHING PIER CONSTRUCTION | E78: 2500000 | F78: 0 | G78: 0 | H78: 0 | I78: SPEAKER HANKS | J78: 37
D79: TOTALS FOR ESPLANADE PROJECT (1 PROJECTS) | E79: =SUM(E78) -> 2500000
A81: SYSTEM IMPROVEMENTS
A82: SUB ID | B82: BUDGET LINE | C82: BORO | D82: PROJECT TITLE | E82: FY 2027 | F82: FY 2028 | G82: FY 2029 | H82: FY 2030 | I82: SPON | J82: PDF p.
A83: CC0845 | B83: FD109 | C83: R | D83: MARINE 8 GATOR PURCHASE | E83: 55000 | F83: 0 | G83: 0 | H83: 0 | I83: MORANO | J83: 38
A84: CC1117 | B84: FD109 | C84: R | D84: EMS 23 ROSSVILLE COMMAND CAR | E84: 418000 | F84: 0 | G84: 0 | H84: 0 | I84: SPEAKER STATEN ISLAND DELEGATION | J84: 38
D85: TOTALS FOR SYSTEM IMPROVEMENTS (2 PROJECTS) | E85: =SUM(E83:E84) -> 473000
A87: RENOVATIONS
A88: SUB ID | B88: BUDGET LINE | C88: BORO | D88: PROJECT TITLE | E88: FY 2027 | F88: FY 2028 | G88: FY 2029 | H88: FY 2030 | I88: SPON | J88: PDF p.
A89: CC0819 | B89: PVD341 | C89: R | D89: HISTORIC RICHMOND TOWN GALLERY | E89: 250000 | F89: 0 | G89: 0 | H89: 0 | I89: CARR | J89: 56
A90: CC1101 | B90: FD175 | C90: R | D90: BATTALION 23/ENGINE 162/LADDER 82 | E90: 2000000 | F90: 0 | G90: 0 | H90: 0 | I90: SPEAKER MORANO | J90: 39
A91: CC1162 | B91: PWDN402 | C91: R | D91: JEWISH COMMUNITY CENTER OF STATEN ISLAND | E91: 365000 | F91: 0 | G91: 0 | H91: 0 | I91: CARR | J91: 59
D92: TOTALS FOR RENOVATIONS (3 PROJECTS) | E92: =SUM(E89:E91) -> 2615000
A94: HOUSING
A95: SUB ID | B95: BUDGET LINE | C95: BORO | D95: PROJECT TITLE | E95: FY 2027 | F95: FY 2028 | G95: FY 2029 | H95: FY 2030 | I95: SPON | J95: PDF p.
A96: CC1093 | B96: HDD023 | C96: R | D96: VOLUNTEERS OF AMERICA HILLSIDE GROVE | E96: 2000000 | F96: 0 | G96: 0 | H96: 0 | I96: SPEAKER HANKS | J96: 42
D97: TOTALS FOR HOUSING (1 PROJECTS) | E97: =SUM(E96) -> 2000000
A99: CALLEN-LORDE
A100: SUB ID | B100: BUDGET LINE | C100: BORO | D100: PROJECT TITLE | E100: FY 2027 | F100: FY 2028 | G100: FY 2029 | H100: FY 2030 | I100: SPON | J100: PDF p.
A101: CC0890 | B101: HLDN09D | C101: R | D101: VENTURE HOUSE INC | E101: 340000 | F101: 0 | G101: 0 | H101: 0 | I101: HANKS | J101: 43
D102: TOTALS FOR CALLEN-LORDE (1 PROJECTS) | E102: =SUM(E101) -> 340000
A104: CATHETERIZATION
A105: SUB ID | B105: BUDGET LINE | C105: BORO | D105: PROJECT TITLE | E105: FY 2027 | F105: FY 2028 | G105: FY 2029 | H105: FY 2030 | I105: SPON | J105: PDF p.
A106: CC1091 | B106: HLDN404 | C106: R | D106: STATEN ISLAND UNIVERSITY HOSPITAL 501 | E106: 1250000 | F106: 0 | G106: 0 | H106: 0 | I106: SPEAKER HANKS | J106: 43
D107: TOTALS FOR CATHETERIZATION (1 PROJECTS) | E107: =SUM(E106) -> 1250000
A109: SEAVIEW
A110: SUB ID | B110: BUDGET LINE | C110: BORO | D110: PROJECT TITLE | E110: FY 2027 | F110: FY 2028 | G110: FY 2029 | H110: FY 2030 | I110: SPON | J110: PDF p.
A111: CC1147 | B111: HLDN404 | C111: R | D111: STATEN ISLAND UNIVERSITY HOSPITAL PRINCE | E111: 4000000 | F111: 0 | G111: 0 | H111: 0 | I111: SPEAKER | J111: 43
D112: TOTALS FOR SEAVIEW (1 PROJECTS) | E112: =SUM(E111) -> 4000000
A114: CLASSROOM TECHNOLOGY UPGRADES
A115: SUB ID | B115: BUDGET LINE | C115: BORO | D115: PROJECT TITLE | E115: FY 2027 | F115: FY 2028 | G115: FY 2029 | H115: FY 2030 | I115: SPON | J115: PDF p.
A116: CC1146 | B116: HND300 | C116: R | D116: COLLEGE OF STATEN ISLAND PARKING LOT | E116: 500000 | F116: 0 | G116: 0 | H116: 0 | I116: SPEAKER | J116: 45
D117: TOTALS FOR CLASSROOM TECHNOLOGY UPGRADES (1 PROJECTS) | E117: =SUM(E116) -> 500000
A119: HIGHWAYS
A120: SUB ID | B120: BUDGET LINE | C120: BORO | D120: PROJECT TITLE | E120: FY 2027 | F120: FY 2028 | G120: FY 2029 | H120: FY 2030 | I120: SPON | J120: PDF p.
A121: CC0893 | B121: HWD104 | C121: R | D121: RICHMOND TERRACE STREET IMPROVEMENTS | E121: 500000 | F121: 0 | G121: 0 | H121: 0 | I121: HANKS | J121: 48
A122: CC0894 | B122: HWD104 | C122: R | D122: BAY STREET AREA STREET IMPROVEMENTS | E122: 500000 | F122: 0 | G122: 0 | H122: 0 | I122: HANKS | J122: 48
A123: CC1261 | B123: HWD104 | C123: R | D123: CD 49 ROADWAY RESURFACING | E123: 250000 | F123: 0 | G123: 0 | H123: 0 | I123: HANKS | J123: 48
D124: TOTALS FOR HIGHWAYS (3 PROJECTS) | E124: =SUM(E121:E123) -> 1250000
A126: REPLACEMENT
A127: SUB ID | B127: BUDGET LINE | C127: BORO | D127: PROJECT TITLE | E127: FY 2027 | F127: FY 2028 | G127: FY 2029 | H127: FY 2030 | I127: SPON | J127: PDF p.
A128: CC0846 | B128: LND008 | C128: R | D128: SECURITY UPGRADES CD51 | E128: 242000 | F128: 0 | G128: 0 | H128: 0 | I128: MORANO | J128: 49
A129: CC0902 | B129: LND008 | C129: R | D129: NYPL CCTV & ACCESS CONTROL SYSTEMS CD49 | E129: 250000 | F129: 0 | G129: 0 | H129: 0 | I129: HANKS | J129: 49
A130: CC1161 | B130: LND008 | C130: R | D130: NEW YORK PUBLIC LIBRARY TECHNOLOGY REFRESH CD50 | E130: 250000 | F130: 0 | G130: 0 | H130: 0 | I130: CARR | J130: 49
D131: TOTALS FOR REPLACEMENT (3 PROJECTS) | E131: =SUM(E128:E130) -> 742000
A133: UPGRADES
A134: SUB ID | B134: BUDGET LINE | C134: BORO | D134: PROJECT TITLE | E134: FY 2027 | F134: FY 2028 | G134: FY 2029 | H134: FY 2030 | I134: SPON | J134: PDF p.
A135: CC0814 | B135: PD020 | C135: R | D135: OLD TOWN PLAYGROUND RECONSTRUCTION | E135: 150000 | F135: 0 | G135: 0 | H135: 0 | I135: CARR | J135: 53
A136: CC0815 | B136: PD020 | C136: R | D136: GREENBELT RECREATION CENTER SECURITY | E136: 160000 | F136: 0 | G136: 0 | H136: 0 | I136: CARR | J136: 53
D137: TOTALS FOR UPGRADES (2 PROJECTS) | E137: =SUM(E135:E136) -> 310000
A139: CAMERAS
A140: SUB ID | B140: BUDGET LINE | C140: BORO | D140: PROJECT TITLE | E140: FY 2027 | F140: FY 2028 | G140: FY 2029 | H140: FY 2030 | I140: SPON | J140: PDF p.
A141: CC0816 | B141: PD020 | C141: R | D141: WILLOWBROOK POND PARK RENOVATIONS | E141: 777000 | F141: 0 | G141: 0 | H141: 0 | I141: CARR | J141: 53
A142: CC0817 | B142: PD020 | C142: R | D142: OLD TOWN PLAYGROUND NYCHA FIELD | E142: 125000 | F142: 0 | G142: 0 | H142: 0 | I142: CARR | J142: 53
D143: TOTALS FOR CAMERAS (2 PROJECTS) | E143: =SUM(E141:E142) -> 902000
A145: RECONSTRUCTION
A146: SUB ID | B146: BUDGET LINE | C146: BORO | D146: PROJECT TITLE | E146: FY 2027 | F146: FY 2028 | G146: FY 2029 | H146: FY 2030 | I146: SPON | J146: PDF p.
A147: CC0903 | B147: PD020 | C147: R | D147: DAVIS PLAYGROUND RENOVATION | E147: 250000 | F147: 0 | G147: 0 | H147: 0 | I147: HANKS | J147: 53
A148: CC0906 | B148: PD020 | C148: R | D148: TAPPEN PARK PERIMETER RECONSTRUCTION | E148: 400000 | F148: 0 | G148: 0 | H148: 0 | I148: HANKS | J148: 53
A149: CC1100 | B149: PD020 | C149: X | D149: EXPANSION OF SI DOT TREES AND SIDEWALK | E149: 3536000 | F149: 0 | G149: 0 | H149: 0 | I149: SPEAKER MORANO | J149: 53
D150: TOTALS FOR RECONSTRUCTION (3 PROJECTS) | E150: =SUM(E147:E149) -> 4186000
A152: PROGRAM
...

Sheet §254 SI Non-City (II & III)
A1: FY 2027 §254 — NON-CITY CAPITAL (SECTION II) & DETAIL BY NON-CITY ENTITY (SECTION III) — STATEN ISLAND
A3: SUB ID | B3: BUDGET LINE | C3: BORO | D3: PROJECT TITLE / ORGANIZATION | E3: FY 2027 | F3: SPON | G3: PDF p.
A4: SECTION II — the MA wallet (no sponsor; excluded from the $853,688,000 Council Additions)
A5: MA1004 | B5: PV0N364 | C5: R | D5: ST. GEORGE THEATRE RESTORATION, INC. | E5: 5850000 | F5: (none — non-City section) | G5: 67
A7: SECTION III — SI organizations, doc-printed org totals
A8: ST. GEORGE THEATER | D8: PV 0N364 $5,850,000 + PV DN364 $1,500,000 (CC0818 CARR $500K · CC0891 HANKS $500K · CC1098 SPEAKER $500K) | E8: 7350000
A9: STATEN ISLAND UNIVERSITY HOSPITAL | D9: HL DN404 (CC1091 501 Seaview $1,250,000 SPEAKER, HANKS · CC1147 Prince Bay $4,000,000 SPEAKER) | E9: 5250000
A10: ON YOUR MARK, INC. | D10: PW DN318 (CC0889 HANKS) | E10: 870000
A11: STATEN ISLAND JEWISH COMMUNITY CENTER | D11: PW DN402 (CC1162 CARR — vehicle) | E11: 365000
A12: VENTURE HOUSE INC. | D12: HL DN09D (CC0890 HANKS) | E12: 340000
D13: SI non-City org totals | E13: =SUM(E8:E12) -> 14175000
A15: DOCUMENT CONTEXT (as printed): City Council Additions $853,688,000 · Less Rescindments from Prior Capital Budgets ($23,317,000) · Net Change $830,371,000. Section II non-City total $210,677,000 (178 projects). The MA wallet citywide is dominated by cultural institutions (The Kitchen $14.0M · Ballet Hispánico $10.0M · Roundabout $7.0M · St. George $5.85M).

Sheet Capital — By Sponsor Detail
A1: SI CAPITAL BY SPONSOR — EVERY LINE, FROM THE §254 V4 SPON COLUMN (all prior LOCKED items now doc-verified)
A3: HANKS — 22 lines
A4: SUB ID | B4: PROJECT | C4: FY 2027 | D4: SPON (as printed) | E4: PDF p.
A5: CC1090 | B5: NORTH SHORE ACTION PLAN - TOMPKINSVILLE | C5: 7000000 | D5: SPEAKER HANKS | E5: 37
A6: CC1092 | B6: PIER ONE FISHING PIER CONSTRUCTION | C6: 2500000 | D6: SPEAKER HANKS | E6: 37
A7: CC1093 | B7: VOLUNTEERS OF AMERICA HILLSIDE GROVE | C7: 2000000 | D7: SPEAKER HANKS | E7: 42
A8: CC1091 | B8: STATEN ISLAND UNIVERSITY HOSPITAL 501 | C8: 1250000 | D8: SPEAKER HANKS | E8: 43
A9: CC0889 | B9: ON YOUR MARK RECREATIONAL FIELD | C9: 870000 | D9: HANKS | E9: 59
A10: CC0893 | B10: RICHMOND TERRACE STREET IMPROVEMENTS | C10: 500000 | D10: HANKS | E10: 48
A11: CC0894 | B11: BAY STREET AREA STREET IMPROVEMENTS | C11: 500000 | D11: HANKS | E11: 48
A12: CC0891 | B12: ST. GEORGE THEATER ROOF & FACADE | C12: 500000 | D12: HANKS | E12: 58
A13: CC0906 | B13: TAPPEN PARK PERIMETER RECONSTRUCTION | C13: 400000 | D13: HANKS | E13: 53
A14: CC0890 | B14: VENTURE HOUSE INC | C14: 340000 | D14: HANKS | E14: 43
A15: CC0899 | B15: I.S. 49 BERTA A. DREYFUS STEAM LAB B:R049 S:R049 | C15: 250000 | D15: HANKS | E15: 31
A16: CC1261 | B16: CD 49 ROADWAY RESURFACING | C16: 250000 | D16: HANKS | E16: 48
... A26: CC0904 | B26: TREE GUARDS CD49 | C26: 50000 | D26: HANKS | E26: 54
B27: FOOTS TO | C27: =SUM(C5:C26) -> 17750000
A29: CARR — 34 lines
A30: SUB ID | B30: PROJECT | C30: FY 2027 | D30: SPON (as printed) | E30: PDF p.
A31: CC1160 | B31: CLOVE LAKES PLAYGROUND RECONSTRUCTION | C31: 5300000 | D31: SPEAKER CARR | E31: 53
A32: CC1094 | B32: P.S.50 PLAYGROUND RENOVATION | C32: 2000000 | D32: SPEAKER CARR | E32: 34
A33: CC1095 | B33: P.S. 60 PLAYGROUND RENOVATION | C33: 1800000 | D33: SPEAKER CARR | E33: 34
A34: CC1097 | B34: STATEN ISLAND CHILDREN'S MUSEUM | C34: 1000000 | D34: SPEAKER CARR | E34: 56
A35: CC0816 | B35: WILLOWBROOK POND PARK RENOVATIONS | C35: 777000 | D35: CARR | E35: 53
A36: CC0802 | B36: P.S.39 GYM CONVERSION B:R039 S:R039 | C36: 500000 | D36: CARR | E36: 29
A37: CC0818 | B37: ST. GEORGE THEATRE RESTORATION, INC. | C37: 500000 | D37: CARR | E37: 58
A38: CC1098 | B38: ST. GEORGE THEATRE RESTORATION | C38: 500000 | D38: SPEAKER CARR | E38: 58
A39: CC1162 | B39: JEWISH COMMUNITY CENTER OF STATEN ISLAND | C39: 365000 | D39: CARR | E39: 59
A40: CC1161 | B40: NEW YORK PUBLIC LIBRARY TECHNOLOGY REFRESH CD50 | C40: 250000 | D40: CARR | E40: 49
A41: CC0819 | B41: HISTORIC RICHMOND TOWN GALLERY | C41: 250000 | D41: CARR | E41: 56
A42: CC0796 | B42: P.S./I.S. 229 TECH UPGRADES B:K229 S:K229 | C42: 230000 | D42: CARR | E42: 28 | F42: This one is in Brooklyn, do not add
A43: CC0812 | B43: I.S. 24 SECURITY CAMERAS B:R024 S:R024 | C43: 218000 | D43: CARR | E43: 29
A44: CC0815 | B44: GREENBELT RECREATION CENTER SECURITY | C44: 160000 | D44: CARR | E44: 53
A45: CC0813 | B45: P.S.37 TECH UPGRADE B:R840 S:R037 | C45: 150000 | D45: CARR | E45: 29
A46: CC0814 | B46: OLD TOWN PLAYGROUND RECONSTRUCTION | C46: 150000 | D46: CARR | E46: 53
A47: CC0817 | B47: OLD TOWN PLAYGROUND NYCHA FIELD | C47: 125000 | D47: CARR | E47: 53
A48: CC0793 | B48: P.S./I.S. 26 PARKING LOT B:R026 S:R026 | C48: 100000 | D48: CARR | E48: 28
A49: CC0800 | B49: P.S. 29 TECH UPGRADES B:R029 S:R029 | C49: 100000 | D49: CARR | E49: 29
A50: CC0791 | B50: I.S.2 TECH UPGRADES B:R002 S:R002 | C50: 75000 | D50: CARR | E50: 28
A51: CC0792 | B51: I.S. 51 TECH UPGRADES B:R051 S:R051 | C51: 75000 | D51: CARR | E51: 28
A52: CC0794 | B52: P.S. 30 TECH UPGRADES B:R030 S:R030 | C52: 75000 | D52: CARR | E52: 28
A53: CC0795 | B53: P.S./I.S. 48 TECH UPGRADES B:R071 S:R048 | C53: 75000 | D53: CARR | E53: 28
A54: CC0797 | B54: P.S. 9 TECH UPGRADES B:R048 S:R009 | C54: 75000 | D54: CARR | E54: 28
... A64: CC0811 | B64: SUSAN E. WAGNER HIGH SCHOOL TECH UPGRADES B:R460 S:R460 | C64: 75000 | D64: CARR | E64: 29
B65: FOOTS TO | C65: =SUM(C31:C64) -> 15600000
A67: MORANO — 30 lines
A68: SUB ID | B68: PROJECT | C68: FY 2027 | D68: SPON (as printed) | E68: PDF p.
A69: CC1100 | B69: EXPANSION OF SI DOT TREES AND SIDEWALK | C69: 3536000 | D69: SPEAKER MORANO | E69: 53
A70: CC1101 | B70: BATTALION 23/ENGINE 162/LADDER 82 | C70: 2000000 | D70: SPEAKER MORANO | E70: 39
A71: CC0831 | B71: P.S. 69 SUPPLEMENTAL COOLING B:R069 S:R069 | C71: 500000 | D71: MORANO | E71: 29
A72: CC0834 | B72: I.S. 34 AUDITORIUM UPGRADES B:R034 S:R034 | C72: 425000 | D72: MORANO | E72: 30
A73: CC0826 | B73: P.S. 55 AUDITORIUM UPGRADE B:31R055 S:R055 | C73: 360000 | D73: MORANO | E73: 29
A74: CC0830 | B74: P.S. 25 SOUTH RICHMOND H.S VOCATIONAL TRAINING EQUIPMENT B:R025 S:75R025 | C74: 300000 | D74: MORANO | E74: 29
A75: CC0837 | B75: I.S. 75 TECH UPGRADES B:R075 S:R075 | C75: 270000 | D75: MORANO | E75: 30
A76: CC0823 | B76: P.S. 56 THEATER ROOM CONVERSION B:R056 S:R056 | C76: 250000 | D76: MORANO | E76: 29
A77: CC0824 | B77: P.S. 8 TECH UPGRADES B:R008 S:R008 | C77: 250000 | D77: MORANO | E77: 29
A78: CC0841 | B78: P.S. 53 CAFETERIA UPGRADE B:R053 S:R053 | C78: 250000 | D78: MORANO | E78: 30
A79: CC0846 | B79: SECURITY UPGRADES CD51 | C79: 242000 | D79: MORANO | E79: 49
A80: CC0833 | B80: I.S. 24 CAMERA UPGRADE B:R024 S:R024 | C80: 218000 | D80: MORANO | E80: 30
... A98: CC0845 | B98: MARINE 8 GATOR PURCHASE | C98: 55000 | D98: MORANO | E98: 38
B99: FOOTS TO | C99: =SUM(C69:C98) -> 10536000
A101: SI DELEGATION (joint) — 3 lines
A102: SUB ID | B102: PROJECT | C102: FY 2027 | D102: SPON (as printed) | E102: PDF p.
A103: CC1115 | B103: SNUG HARBOR CULTURAL CENTER AND | C103: 4000000 | D103: SPEAKER STATEN ISLAND DELEGATION | E103: 56
A104: CC1116 | B104: STATEN ISLAND ZOOLOGICAL PERIMETER | C104: 3000000 | D104: SPEAKER STATEN ISLAND DELEGATION | E104: 55
A105: CC1117 | B105: EMS 23 ROSSVILLE COMMAND CAR | C105: 418000 | D105: SPEAKER STATEN ISLAND DELEGATION | E105: 38
B106: FOOTS TO | C106: =SUM(C103:C105) -> 7418000
A108: SPEAKER (pure) — 4 lines
A109: SUB ID | B109: PROJECT | C109: FY 2027 | D109: SPON (as printed) | E109: PDF p.
A110: CC1139 | B110: WILLOWBROOK POND PARK RENOVATIONS | C110: 8096000 | D110: SPEAKER | E110: 53
A111: CC1135 | B111: BLOOMINGDALE PARK BASEBALL FIELD | C111: 7600000 | D111: SPEAKER | E111: 53
A112: CC1147 | B112: STATEN ISLAND UNIVERSITY HOSPITAL PRINCE | C112: 4000000 | D112: SPEAKER | E112: 43
A113: CC1146 | B113: COLLEGE OF STATEN ISLAND PARKING LOT | C113: 500000 | D113: SPEAKER | E113: 45
B114: FOOTS TO | C114: =SUM(C110:C113) -> 20196000

Sheet Capital — Allocator
A1: FY27 SI CAPITAL BY ALLOCATOR ($71,500,000 SI-substantive)
A3: Allocator | B3: Amount | C3: Share
A4: Hanks (D49) | B4: 17750000 | C4: =B4/$B$9 -> 0.24825175
A5: Carr (D50) | B5: 15600000 | C5: =B5/$B$9 -> 0.21818182
A6: Morano (D51) | B6: 10536000 | C6: =B6/$B$9 -> 0.14735664
A7: SI Delegation (joint, multi-sponsor) | B7: 7418000 | C7: =B7/$B$9 -> 0.10374825
A8: Speaker (solo) | B8: 20196000 | C8: =B8/$B$9 -> 0.28246154
A9: TOTAL (SI-substantive, incl. CC1100) | B9: =SUM(B4:B8) -> 71500000
A10: + St. George Theatre add-on (allocator section per source doc — cite pending) | B10: 5850000
A11: SI-SUBSTANTIVE CAPITAL | B11: =B9+B10 -> 77350000

Sheet Capital — Category
A1: FY27 SI CAPITAL BY CATEGORY ($67,964,000 Borough R, Section 254)
A3: Category | B3: Amount | C3: Highlights
A4: Parks & Open Space | B4: 22908000 | C4: Willowbrook Pond Park, Bloomingdale Park field, Clove Lakes Playground, Tappen Park, Davis Playground
A5: Education (SCA) | B5: 11696000 | C5: School tech, playgrounds, auditoriums, cooling, STEM labs; P.S. 50 & P.S. 60 playgrounds
A6: Cultural Institutions | B6: 10070000 | C6: Snug Harbor, SI Zoo, SI Children’s Museum, St. George Theatre, Historic Richmond Town
A7: Economic Development (EDC) | B7: 9500000 | C7: North Shore Action Plan / Tompkinsville Esplanade; Pier One Fishing Pier
A8: Health / H+H | B8: 5590000 | C8: SIUH Prince’s Bay, SIUH 501 Seaview, Venture House
A9: Fire / Public Safety | B9: 2473000 | C9: Battalion 23 / Engine 162 / Ladder 82; EMS 23 Rossville command car
A10: Housing & Human Services | B10: 2000000 | C10: Volunteers of America Hillside Grove
A11: Highways / DOT | B11: 1250000
A12: Public Buildings (DCAS) | B12: 1235000
A13: Libraries (NYPL) | B13: 742000 | C13: Technology refresh, CCTV/access control, security
A14: Higher Education | B14: 500000 | C14: College of Staten Island parking renovation
A15: TOTAL Borough R | B15: =SUM(B4:B14) -> 67964000
A16: + CC1100 SI DOT Trees & Sidewalk (Boro X-coded) | B16: 3536000
A17: + St. George Theatre (separate section) | B17: 5850000
A18: SI-SUBSTANTIVE CAPITAL | B18: =B15+B16+B17 -> 77350000
A19: EXCLUDED: $230,000 school project labeled Staten Island carrying Brooklyn school codes — suspected City coding typo; not added; confirmation query pending.

Sheet Capital — Named Wins
A1: FY27 NAMED CAPITAL WINS (Section 254, CC-series verified Jul 1)
A3: Project | B3: Amount
A4: St. George Theatre (separate section — office review Jul 2) | B4: 5850000
A5: Willowbrook Pond Park renovations | B5: 8096000
A6: Bloomingdale Park baseball field renovation | B6: 7600000
A7: North Shore Action Plan / Tompkinsville Esplanade | B7: 7000000
A8: Clove Lakes Playground reconstruction | B8: 5300000
A9: Snug Harbor Cultural Center & Botanical Garden | B9: 4000000
A10: SIUH Prince’s Bay renovation | B10: 4000000
A11: Staten Island Zoo perimeter renovations | B11: 3000000
A12: Pier One Fishing Pier construction | B12: 2500000
A13: Battalion 23 / Engine 162 / Ladder 82 renovation | B13: 2000000
A14: Volunteers of America Hillside Grove | B14: 2000000
A15: SIUH 501 Seaview (Speaker, Hanks — office source Jul 2) | B15: 1250000
... A17: On Your Mark recreational field | B17: 870000
A18: Named wins subtotal (subset of category totals) | B18: =SUM(B4:B17) -> 54466000
A19: Project sub-IDs (CC-series) and Section 254 page cites available on re-upload of the Section 254 PDF.

Sheet MDI Pot Matrix
A1: MDIs — EVERY POT, WITH SCHEDULE C LOCATION
A3: MDI pot | B3: Sched C ref | C3: Hanks $ | D3: # | E3: Carr $ | F3: # | G3: Morano $ | H3: # | I3: Delegation $
A4: Local Initiatives | B4: App B pp.27–149 | C4: 400000 | D4: 76 | E4: 400000 | F4: 45 | G4: 400000 | H4: 61 | I4: =C4+E4+G4 -> 1200000
A5: CASA (after-school) | B5: p.29 | C5: 340000 | D5: 17 | E5: 340000 | F5: 17 | G5: 340000 | H5: 17 | I5: =C5+E5+G5 -> 1020000
A6: NYC Cleanup | B6: p.108 | C6: 280000 | D6: 6 | E6: 280000 | F6: 5 | G6: 280000 | H6: 8 | I6: =C6+E6+G6 -> 840000
A7: DoVE | B7: p.74 | C7: 195000 | D7: 11 | E7: 195000 | F7: 4 | G7: 133000 | H7: 9 | I7: =C7+E7+G7 -> 523000
A8: Youth Discretionary | B8: App C pp.150–193 | C8: 150000 | D8: 18 | E8: 150000 | F8: 17 | G8: 150000 | H8: 12 | I8: =C8+E8+G8 -> 450000
A9: Support Our Older Adults | B9: p.172 | C9: 150000 | D9: 10 | E9: 150000 | F9: 6 | G9: 150000 | H9: 6 | I9: =C9+E9+G9 -> 450000
A10: Cultural Immigrant | B10: p.59 | C10: 145000 | D10: 11 | E10: 145000 | F10: 11 | G10: 145000 | H10: 11 | I10: =C10+E10+G10 -> 435000
A11: Aging Discretionary | B11: App A pp.1–26 | C11: 110000 | D11: 8 | E11: 110000 | F11: 8 | G11: 110000 | H11: 9 | I11: =C11+E11+G11 -> 330000
A12: Community Safety | B12: p.21 | C12: 100000 | D12: 2 | E12: 100000 | F12: 8 | G12: 100000 | H12: 8 | I12: =C12+E12+G12 -> 300000
A13: A Greener NYC | B13: p.97 | C13: 100000 | D13: 7 | E13: 100000 | F13: 5 | G13: 100000 | H13: 6 | I13: =C13+E13+G13 -> 300000
A14: Digital Inclusion | B14: p.9 | C14: 90000 | D14: 4 | E14: 90000 | F14: 2 | G14: 90000 | H14: 5 | I14: =C14+E14+G14 -> 270000
A15: Parks Equity | B15: p.188 | C15: 90000 | D15: 5 | E15: 90000 | F15: 5 | G15: 90000 | H15: 8 | I15: =C15+E15+G15 -> 270000
... A17: Neighborhood Dev Grant | B17: p.209 | C17: 50000 | D17: 4 | E17: 50000 | F17: 3 | G17: 50000 | H17: 3 | I17: =C17+E17+G17 -> 150000
A18: PRINTED MDI TOTAL | C18: =SUM(C4:C17) -> 2250000 | D18: =SUM(D4:D17) -> 183 | E18: =SUM(E4:E17) -> 2225000 | F18: =SUM(F4:F17) -> 138 | G18: =SUM(G4:G17) -> 2163000 | H18: =SUM(H4:H17) -> 166 | I18: =SUM(I4:I17) -> 6638000
A19: SU-CASA (pending post-adoption) | B19: p.73 | C19: 45000 | E19: 45000 | G19: 0 | I19: 90000
A20: ALL-IN MDI (= database) | C20: =C18+C19 -> 2295000 | E20: =E18+E19 -> 2270000 | G20: =G18+G19 -> 2163000 | I20: =I18+I19 -> 6728000
A22: PROJECTION — Morano SU-CASA at parity (3 × $15,000; ASSUMPTION, not confirmed) | G22: 45000 | I22: 45000
A23: PROJECTED ALL-IN MDI (if realized) | C23: 2295000 | E23: 2270000 | G23: 2208000 | I23: 6773000

Sheet Speaker — Pool Items
A1: SPEAKER-POOL ITEMS TO SI (of $86,522,049 pool) — with Schedule C location
A3: Attributed to | B3: Organization — Program | C3: Amount | D3: Sched C ref
A4: Hanks | B4: NYCID — Credible Messengers of Staten Island | C4: 500000 | D4: Speaker itemization (PDF p.281)
A5: Hanks | B5: Universal Temple of the Arts — Love In Bloom | C5: 50000 | D5: Speaker itemization (PDF p.290)
A6: Hanks | B6: On Your Mark | C6: 35000 | D6: Speaker itemization (PDF p.283)
A7: Hanks | B7: Dr. Theodore A. Atlas Foundation | C7: 30000 | D7: Speaker itemization (PDF p.271)
A8: Hanks | B8: Dibra Community Organization | C8: 25000 | D8: Speaker itemization (PDF p.270)
A9: Carr | B9: Pride Center of Staten Island | C9: 50000 | D9: Speaker itemization (PDF p.284)
A10: Carr | B10: Lifestyles for the Disabled — Adaptive Sports | C10: 35000 | D10: Speaker itemization (PDF p.278)
A11: Carr | B11: Staten Island Little League | C11: 25000 | D11: Speaker itemization (PDF p.277)
A12: Carr | B12: JCC of Staten Island — development program | C12: 25000 | D12: Speaker itemization (PDF p.288)
A13: Morano | B13: Carl V. Bini Memorial Fund | C13: 40000 | D13: Speaker itemization (PDF p.265)
A14: Carr+Morano+SI Del | B14: SI Zoological Society — Education & Animal Care | C14: 260000 | D14: Speaker itemization (PDF p.288)
A15: Morano+SI Del | B15: SIEDC — Economic Development, 51st District | C15: 200000 | D15: Speaker itemization (PDF p.288)
... A19: SI Delegation | B19: SI Chamber of Commerce Foundation | C19: 25000 | D19: Speaker itemization (PDF p.288)
B20: TOTAL — 16 items | C20: =SUM(C4:C19) -> 1450000

Sheet Speaker — Designated Locals
A1: SPEAKER-DESIGNATED LOCALS TO SI (of Speaker $16,139,000 local block)
A3: Attributed to | B3: Organization — Program | C3: Amount | D3: Sched C ref
A4: Hanks | B4: CityParks Foundation — SummerStage / CityParks Play | C4: 110000 | D4: App B p.54
A5: Hanks | B5: Staten Island Immigrant Center | C5: 50000 | D5: App B p.136
A6: Hanks | B6: JCC of Staten Island — Adult Day Care | C6: 25000 | D6: App B p.88
A7: Carr | B7: DSNY — 50th District | C7: 100000 | D7: App B p.68
A8: Carr+SI Del | B8: SIEDC — 50th District | C8: 140000 | D8: App B p.136
A9: Carr+SI Del | B9: Grace Foundation of New York | C9: 50000 | D9: App B p.79
A10: Carr+Morano+SI Del | B10: SI Historical Society — Historic Richmond Town | C10: 50000 | D10: App B p.136
A11: Morano+SI Del | B11: South Shore District Management Association | C11: 45000 | D11: App B p.134
A12: SI Delegation | B12: Richmond Medical Center — SAFE Program | C12: 100000 | D12: App B p.128
B13: TOTAL — 9 items | C13: =SUM(C4:C12) -> 670000

Sheet Speaker — Untagged SI
A1: SPEAKER ITEMS TO SI ORGS — NO MEMBER TAG
A3: Organization — Program | B3: Amount | C3: Sched C ref | D3: Initiative (where labeled)
A4: Richmond Medical Center - Elizabeth W. Pouch Center for | B4: 250000 | C4: Speaker itemization (PDF p.286)
A5: Staten Island Zoological Society, Inc. - SCI Network NYC | B5: 157880 | C5: Speaker itemization (PDF p.289)
A6: Staten Island Chamber of Commerce Foundation, Inc. - 49th Council District | B6: 75000 | C6: Speaker itemization (PDF p.288)
A7: African Refuge, Inc. - Community and Police Mental Health | B7: 50000 | C7: Speaker itemization (PDF p.260)
A8: City University of New York - College of Staten Island - Breast Cancer Res | B8: 50000 | C8: Speaker itemization (PDF p.267)
A9: Jewish Community Council of Greater Coney Island, Inc. - Staten Island Com | B9: 50000 | C9: Speaker itemization (PDF p.277)
A10: Pride Center of Staten Island, Inc. | B10: 30000 | C10: Speaker itemization (PDF p.284)
A11: Staten Island Children's Museum | B11: 20000 | C11: Speaker itemization (PDF p.288)
A12: Jewish Community Center of Staten Island, Inc. - 2027 Sunrise Day Camp | B12: 15000 | C12: App B p.88
A13: TOTAL — 9 items | B13: =SUM(B4:B12) -> 697880

Sheet Master Line Items
A1: EVERY SI DOLLAR IN SCHEDULE C FINAL-3 — WITH INITIATIVE/MDI AND PAGE
A3: Category | B3: MDI pot / Initiative | C3: Sponsor / Attribution | D3: Organization — Program | E3: EIN | F3: Amount | G3: Sched C ref | H3: Flag | I3: Where to search (public)
A4: MDI (SI member) | B4: A Greener NYC | C4: Carr | D4: Greenbelt Conservancy, Inc. – Nature Discovery Series | E4: 13-3481845 | F4: 40000 | G4: p.103 | I4: Sched C PDF (council.nyc.gov) · Open Data 4d7f-74pe · MOCS Award Tracker (EIN) · Checkbook NYC (payments)
A5: MDI (SI member) | B5: A Greener NYC | C5: Morano | D5: District 13 New York City H2O – Volunteer Cleanups & Stewardship | E5: 45-3860014 | F5: 35000 | G5: p.104 | I5: Sched C PDF (council.nyc.gov) · Open Data 4d7f-74pe · MOCS Award Tracker (EIN) · Checkbook NYC (payments)
A6: MDI (SI member) | B6: A Greener NYC | C6: Hanks | D6: Outreach - Council District 13 City Parks Foundation – CityParks Play, CityParks Learn & | E6: 13-3561657 | F6: 25000 | G6: p.100 | I6: Sched C PDF (council.nyc.gov) · Open Data 4d7f-74pe · MOCS Award Tracker (EIN) · Checkbook NYC (payments)
A7: MDI (SI member) | B7: A Greener NYC | C7: Hanks | D7: District 10 Citizens Committee for New York City, Inc. – Council District | E7: 51-0171818 | F7: 20000 | G7: p.100 | I7: Sched C PDF (council.nyc.gov) · Open Data 4d7f-74pe · MOCS Award Tracker (EIN) · Checkbook NYC (payments)
A8: MDI (SI member) | B8: A Greener NYC | C8: Morano | D8: Beautification & Horticulture - Kings Highway BID Lifestyles for the Disabled, Inc. – Hort | E8: 13-3740011 | F8: 20000 | G8: p.103 | I8: Sched C PDF (council.nyc.gov) · Open Data 4d7f-74pe · MOCS Award Tracker (EIN) · Checkbook NYC (payments)
A9: MDI (SI member) | B9: A Greener NYC | C9: Carr | D9: Department of Education – Staten Island Borough Office | E9: 13-6400434 | F9: 15000 | G9: p.101 | I9: Sched C PDF (council.nyc.gov) · Open Data 4d7f-74pe · MOCS Award Tracker (EIN) · Checkbook NYC (payments)
A10: MDI (SI member) | B10: A Greener NYC | C10: Carr | D10: New York City H2O – Clean-Up Education Program | E10: 45-3860014 | F10: 15000 | G10: p.104 | I10: Sched C PDF (council.nyc.gov) · Open Data 4d7f-74pe · MOCS Award Tracker (EIN) · Checkbook NYC (payments)
A11: MDI (SI member) | B11: A Greener NYC | C11: Carr | D11: Council District 45 Snug Harbor Cultural Center and Botanical Garden – Green | E11: 80-0193388 | F11: 15000 | G11: p.106 | I11: Sched C PDF (council.nyc.gov) · Open Data 4d7f-74pe · MOCS Award Tracker (EIN) · Checkbook NYC (payments)
A12: MDI (SI member) | B12: A Greener NYC | C12: Carr | D12: Staten Island Economic Development Corporation | E12: 13-3706442 | F12: 15000 | G12: p.106 | I12: Sched C PDF (council.nyc.gov) · Open Data 4d7f-74pe · MOCS Award Tracker (EIN) · Checkbook NYC (payments)
A13: MDI (SI member) | B13: A Greener NYC | C13: Morano | D13: Staten Island Historical Society – Educational Programming | E13: 13-1985514 | F13: 15000 | G13: p.106 | I13: Sched C PDF (council.nyc.gov) · Open Data 4d7f-74pe · MOCS Award Tracker (EIN) · Checkbook NYC (payments)
A14: MDI (SI member) | B14: A Greener NYC | C14: Hanks | D14: Events - Council District 10 Waterfront Alliance, Inc. – Education & Programming - | E14: 13-4355067 | F14: 15000 | G14: p.106 | I14: Sched C PDF (council.nyc.gov) · Open Data 4d7f-74pe · MOCS Award Tracker (EIN) · Checkbook NYC (payments)
A15: MDI (SI member) | B15: A Greener NYC | C15: Morano | D15: District 46 Billion Oyster Project, Inc. – Educational Programming - | E15: 27-2918478 | F15: 10000 | G15: p.99 | I15: Sched C PDF (council.nyc.gov) · Open Data 4d7f-74pe · MOCS Award Tracker (EIN) · Checkbook NYC (payments)
... A40: MDI (SI member) | B40: Aging Discretionary | C40: Morano | D40: Noble Maritime Collection, The - Council District 51 | E40: 133351673 | F40: 10000 | G40: App A p.18 | I40: Sched C PDF (council.nyc.gov) · Open Data 4d7f-74pe · MOCS Award Tracker (EIN) · Checkbook NYC (payments)
A41: MDI (SI member) | B41: Aging Discretionary | C41: Carr | D41: Federation of Italian American Organizations of Brooklyn, Ltd. | E41: 112507910 | F41: 9000 | G41: App A p.8 | H41: Brooklyn-based org (printed designation) | I41: Sched C PDF (council.nyc.gov) · Open Data 4d7f-74pe · MOCS Award Tracker (EIN) · Checkbook NYC (payments)
A42: MDI (SI member) | B42: Aging Discretionary | C42: Carr | D42: Lifestyles for the Disabled, Inc. | E42: 133740011 | F42: 8000 | G42: App A p.15 | I42: Sched C PDF (council.nyc.gov) · Open Data 4d7f-74pe · MOCS Award Tracker (EIN) · Checkbook NYC (payments)
A43: MDI (SI member) | B43: Aging Discretionary | C43: Morano | D43: Jewish Community Center of Staten Island, Inc. - Senior Olympics | E43: 135562256 | F43: 5000 | G43: App A p.14 | I43: Sched C PDF (council.nyc.gov) · Open Data 4d7f-74pe · MOCS Award Tracker (EIN) · Checkbook NYC (payments)
A44: MDI (SI member) | B44: Aging Discretionary | C44: Morano | D44: South Shore Artists Foundation - Senior Programs - Council Fund | E44: 842895424 | F44: 5000 | G44: App A p.23 | I44: Sched C PDF (council.nyc.gov) · Open Data 4d7f-74pe · MOCS Award Tracker (EIN) · Checkbook NYC (payments)
A45: MDI (SI member) | B45: Aging Discretionary | C45: Morano | D45: TraNa Relief Association | E45: 920875945 | F45: 5000 | G45: App A p.24 | I45: Sched C PDF (council.nyc.gov) · Open Data 4d7f-74pe · MOCS Award Tracker (EIN) · Checkbook NYC (payments)
A46: MDI (SI member) | B46: Aging Discretionary | C46: Carr | D46: United Hands Organization, Inc. | E46: 932643668 | F46: 5000 | G46: App A p.24 | I46: Sched C PDF (council.nyc.gov) · Open Data 4d7f-74pe · MOCS Award Tracker (EIN) · Checkbook NYC (payments)
A47: MDI (SI member) | B47: Anti-Poverty Initiative | C47: Hanks | D47: Dr. Theodore A. Atlas Foundation, Inc. - Food Distribution - | E47: 134012789 | F47: 30000 | G47: PDF p.12 (member listing) | I47: Sched C PDF (council.nyc.gov) · Open Data 4d7f-74pe · MOCS Award Tracker (EIN) · Checkbook NYC (payments)
A48: MDI (SI member) | B48: Anti-Poverty Initiative | C48: Carr | D48: Staten Island Zoological Society, Inc. | E48: 135680691 | F48: 20000 | G48: PDF p.20 (member listing) | I48: Sched C PDF (council.nyc.gov) · Open Data 4d7f-74pe · MOCS Award Tracker (EIN) · Checkbook NYC (payments)
A49: MDI (SI member) | B49: Anti-Poverty Initiative | C49: Hanks | D49: Citizens Committee for New York City, Inc. | E49: 510171818 | F49: 10000 | G49: PDF p.10 (member listing) | I49: Sched C PDF (council.nyc.gov) · Open Data 4d7f-74pe · MOCS Award Tracker (EIN) · Checkbook NYC (payments)
A50: MDI (SI member) | B50: Anti-Poverty Initiative | C50: Morano | D50: Staten Island Children's Museum - Arts Residency - Council | E50: 237379930 | F50: 10000 | G50: PDF p.20 (member listing) | I50: Sched C PDF (council.nyc.gov) · Open Data 4d7f-74pe · MOCS Award Tracker (EIN) · Checkbook NYC (payments)
A51: MDI (SI member) | B51: Anti-Poverty Initiative | C51: Morano | D51: HSS Screening and Early Detection, Inc. | E51: 473436880 | F51: 7500 | G51: PDF p.14 (member listing) | I51: Sched C PDF (council.nyc.gov) · Open Data 4d7f-74pe · MOCS Award Tracker (EIN) · Checkbook NYC (payments)
A52: MDI (SI member) | B52: Anti-Poverty Initiative | C52: Morano | D52: Metropolitan New York Coordinating Council on Jewish | E52: 132738818 | F52: 7500 | G52: PDF p.15 (member listing) | I52: Sched C PDF (council.nyc.gov) · Open Data 4d7f-74pe · MOCS Award Tracker (EIN) · Checkbook NYC (payments)
A53: MDI (SI member) | B53: Anti-Poverty Initiative | C53: Carr | D53: Grace Foundation of New York | E53: 134131863 | F53: 5000 | G53: PDF p.13 (member listing) | I53: Sched C PDF (council.nyc.gov) · Open Data 4d7f-74pe · MOCS Award Tracker (EIN) · Checkbook NYC (payments)
... A68: MDI (SI member) | B68: Community Safety and Victim Services Ini | C68: Morano | D68: Emergency Children's Help Organization, Inc. - Emergency Assistance Program | E68: 113828185 | F68: 10000 | G68: PDF p.53 (member listing) | I68: Sched C PDF (council.nyc.gov) · Open Data 4d7f-74pe · MOCS Award Tracker (EIN) · Checkbook NYC (payments)
A69: MDI (SI member) | B69: Community Safety and Victim Services Ini | C69: Carr | D69: Federation of Italian American Organizations of Brooklyn, Ltd. | E69: 112507910 | F69: 10000 | G69: PDF p.54 (member listing) | H69: Brooklyn-based org (printed designation) | I69: Sched C PDF (council.nyc.gov) · Open Data 4d7f-74pe · MOCS Award Tracker (EIN) · Checkbook NYC (payments)
A70: MDI (SI member) | B70: Community Safety and Victim Services Ini | C70: Morano | D70: Girl Scout Council of Greater New York, Inc. - Troop 75312 | E70: 131624014 | F70: 10000 | G70: PDF p.54 (member listing) | I70: Sched C PDF (council.nyc.gov) · Open Data 4d7f-74pe · MOCS Award Tracker (EIN) · Checkbook NYC (payments)
A71: MDI (SI member) | B71: Community Safety and Victim Services Ini | C71: Morano | D71: Police Department - 123rd Precinct | E71: 136400434 | F71: 10000 | G71: PDF p.59 (member listing) | I71: Sched C PDF (council.nyc.gov) · Open Data 4d7f-74pe · MOCS Award Tracker (EIN) · Checkbook NYC (payments)
A72: MDI (SI member) | B72: Community Safety and Victim Services Ini | C72: Carr | D72: Richmond County Youth Complex, Inc. | E72: 205857329 | F72: 10000 | G72: PDF p.60 (member listing) | I72: Sched C PDF (council.nyc.gov) · Open Data 4d7f-74pe · MOCS Award Tracker (EIN) · Checkbook NYC (payments)
A73: MDI (SI member) | B73: Community Safety and Victim Services Ini | C73: Morano | D73: Young Men's Christian Association of Greater New York - Counseling & Programming - Council | E73: 131624228 | F73: 10000 | G73: PDF p.63 (member listing) | I73: Sched C PDF (council.nyc.gov) · Open Data 4d7f-74pe · MOCS Award Tracker (EIN) · Checkbook NYC (payments)
A74: MDI (SI member) | B74: Cultural After-School Adventure (CASA) | C74: Hanks | D74: Ballroom Basix USA, Inc. | E74: 27-3218865 | F74: 20000 | G74: p.32 | I74: Sched C PDF (council.nyc.gov) · Open Data 4d7f-74pe · MOCS Award Tracker (EIN) · Checkbook NYC (payments)
A75: MDI (SI member) | B75: Cultural After-School Adventure (CASA) | C75: Morano | D75: Canvas Institute – Intermediate School 72R Rocco Laurie | E75: 82-4902021 | F75: 20000 | G75: p.35 | I75: Sched C PDF (council.nyc.gov) · Open Data 4d7f-74pe · MOCS Award Tracker (EIN) · Checkbook NYC (payments)
A76: MDI (SI member) | B76: Cultural After-School Adventure (CASA) | C76: Hanks | D76: Canvas Institute – Public School 016R John J. Driscoll (31R016) | E76: 82-4902021 | F76: 20000 | G76: p.35 | I76: Sched C PDF (council.nyc.gov) · Open Data 4d7f-74pe · MOCS Award Tracker (EIN) · Checkbook NYC (payments)
A77: MDI (SI member) | B77: Cultural After-School Adventure (CASA) | C77: Hanks | D77: Center for Educational Innovation – Public School 016R John J. | E77: 13-4113613 | F77: 20000 | G77: p.36 | I77: Sched C PDF (council.nyc.gov) · Open Data 4d7f-74pe · MOCS Award Tracker (EIN) · Checkbook NYC (payments)
A78: MDI (SI member) | B78: Cultural After-School Adventure (CASA) | C78: Hanks | D78: Children's Aid Society, The – Curtis High School (31R450) | E78: 13-5562191 | F78: 20000 | G78: p.36 | I78: Sched C PDF (council.nyc.gov) · Open Data 4d7f-74pe · MOCS Award Tracker (EIN) · Checkbook NYC (payments)
A79: MDI (SI member) | B79: Cultural After-School Adventure (CASA) | C79: Carr | D79: IlluminArt Productions – Intermediate School 2R George L. | E79: 42-1727647 | F79: 20000 | G79: p.41 | I79: Sched C PDF (council.nyc.gov) · Open Data 4d7f-74pe · MOCS Award Tracker (EIN) · Checkbook NYC (payments)
A80: MDI (SI member) | B80: Cultural After-School Adventure (CASA) | C80: Morano | D80: Egbert (31R002) IlluminArt Productions – Marsh Avenue School for | E80: 42-1727647 | F80: 20000 | G80: p.41 | I80: Sched C PDF (council.nyc.gov) · Open Data 4d7f-74pe · MOCS Award Tracker (EIN) · Checkbook NYC (payments)
A81: MDI (SI member) | B81: Cultural After-School Adventure (CASA) | C81: Hanks | D81: Expeditionary Learning (31R063) IlluminArt Productions – Public School 019R The Curtis Sch | E81: 42-1727647 | F81: 20000 | G81: p.41 | I81: Sched C PDF (council.nyc.gov) · Open Data 4d7f-74pe · MOCS Award Tracker (EIN) · Checkbook NYC (payments)
... A206: MDI (SI member) | B206: Local Initiatives | C206: Morano | D206: Staten Island Children's Museum - Arts Residency - | E206: 237379930 | F206: 16000 | G206: App B p.136 | I206: Sched C PDF (council.nyc.gov) · Open Data 4d7f-74pe · MOCS Award Tracker (EIN) · Checkbook NYC (payments)
A207: MDI (SI member) | B207: Local Initiatives | C207: Carr | D207: Federation of Italian American Organizations of Brooklyn, Ltd. - Concerts - Dyker Heights | E207: 112507910 | F207: 15000 | G207: App B p.74 | H207: Brooklyn-based org (printed designation) | I207: Sched C PDF (council.nyc.gov) · Open Data 4d7f-74pe · MOCS Award Tracker (EIN) · Checkbook NYC (payments)
A208: MDI (SI member) | B208: Local Initiatives | C208: Hanks | D208: Literacy Partners, Inc. - Council District 49 | E208: 510180665 | F208: 15000 | G208: App B p.94 | I208: Sched C PDF (council.nyc.gov) · Open Data 4d7f-74pe · MOCS Award Tracker (EIN) · Checkbook NYC (payments)
A209: MDI (SI member) | B209: Local Initiatives | C209: Morano | D209: Museum of Maritime Navigation and Communication | E209: 900730331 | F209: 15000 | G209: App B p.102 | I209: Sched C PDF (council.nyc.gov) · Open Data 4d7f-74pe · MOCS Award Tracker (EIN) · Checkbook NYC (payments)
A210: MDI (SI member) | B210: Local Initiatives | C210: Carr | D210: Staten Island Chamber of Commerce Foundation, Inc. | E210: 134069282 | F210: 15000 | G210: App B p.136 | I210: Sched C PDF (council.nyc.gov) · Open Data 4d7f-74pe · MOCS Award Tracker (EIN) · Checkbook NYC (payments)
A211: MDI (SI member) | B211: Local Initiatives | C211: Carr | D211: Staten Island Economic Development Corporation - Health & Wellness Expo | E211: 133706442 | F211: 15000 | G211: App B p.136 | I211: Sched C PDF (council.nyc.gov) · Open Data 4d7f-74pe · MOCS Award Tracker (EIN) · Checkbook NYC (payments)
A212: MDI (SI member) | B212: Local Initiatives | C212: Carr | D212: Staten Island Economic Development Corporation - | E212: 133706442 | F212: 15000 | G212: App B p.136 | I212: Sched C PDF (council.nyc.gov) · Open Data 4d7f-74pe · MOCS Award Tracker (EIN) · Checkbook NYC (payments)
A213: MDI (SI member) | B213: Local Initiatives | C213: Morano | D213: On Your Mark, Inc. - Art Program | E213: 133128315 | F213: 14500 | G213: App B p.117 | I213: Sched C PDF (council.nyc.gov) · Open Data 4d7f-74pe · MOCS Award Tracker (EIN) · Checkbook NYC (payments)
A214: MDI (SI member) | B214: Local Initiatives | C214: Hanks | D214: Department of Transportation - Council District 49 | E214: 136400434 | F214: 14000 | G214: App B p.69 | I214: Sched C PDF (council.nyc.gov) · Open Data 4d7f-74pe · MOCS Award Tracker (EIN) · Checkbook NYC (payments)
A215: MDI (SI member) | B215: Local Initiatives | C215: Morano | D215: Theatre Development Fund, Inc. - School Programs - Council District 51 | E215: 136216919 | F215: 11500 | G215: App B p.138 | I215: Sched C PDF (council.nyc.gov) · Open Data 4d7f-74pe · MOCS Award Tracker (EIN) · Checkbook NYC (payments)
A216: MDI (SI member) | B216: Local Initiatives | C216: Hanks | D216: A Chance In Life - Council District 49 | E216: 131835632 | F216: 10000 | G216: App B p.27 | I216: Sched C PDF (council.nyc.gov) · Open Data 4d7f-74pe · MOCS Award Tracker (EIN) · Checkbook NYC (payments)
A217: MDI (SI member) | B217: Local Initiatives | C217: Hanks | D217: Ballroom Basix USA, Inc. - Public School 020R Port Richmond (31R020) | E217: 273218865 | F217: 10000 | G217: App B p.35 | I217: Sched C PDF (council.nyc.gov) · Open Data 4d7f-74pe · MOCS Award Tracker (EIN) · Checkbook NYC (payments)
A218: MDI (SI member) | B218: Local Initiatives | C218: Hanks | D218: Bee U, Inc. - Community Workshops - Council District 49 | E218: 881156617 | F218: 10000 | G218: App B p.36 | I218: Sched C PDF (council.nyc.gov) · Open Data 4d7f-74pe · MOCS Award Tracker (EIN) · Checkbook NYC (payments)
A219: MDI (SI member) | B219: Local Initiatives | C219: Hanks | D219: City University of New York - College of Staten Island - | E219: 133893536 | F219: 10000 | G219: App B p.54 | I219: Sched C PDF (council.nyc.gov) · Open Data 4d7f-74pe · MOCS Award Tracker (EIN) · Checkbook NYC (payments)
... A247: MDI (SI member) | B247: Local Initiatives | C247: Hanks | D247: Art Lab, Inc. - Community Events - Council District 49 | E247: 132977495 | F247: 5000 | G247: App B p.33 | I247: Sched C PDF (council.nyc.gov) · Open Data 4d7f-74pe · MOCS Award Tracker (EIN) · Checkbook NYC (payments)
A248: MDI (SI member) | B248: Local Initiatives | C248: Carr | D248: Brooklyn Alliance, Inc. - Council District 50 | E248: 112145956 | F248: 5000 | G248: App B p.41 | H248: Brooklyn-based org (printed designation) | I248: Sched C PDF (council.nyc.gov) · Open Data 4d7f-74pe · MOCS Award Tracker (EIN) · Checkbook NYC (payments)
A249: MDI (SI member) | B249: Local Initiatives | C249: Carr | D249: Canvas Institute | E249: 824902021 | F249: 5000 | G249: App B p.46 | I249: Sched C PDF (council.nyc.gov) · Open Data 4d7f-74pe · MOCS Award Tracker (EIN) · Checkbook NYC (payments)
A250: MDI (SI member) | B250: Local Initiatives | C250: Hanks | D250: Casa Belvedere, The Italian Cultural Foundation - Nonno's Community Garden - Council Distr | E250: 264411728 | F250: 5000 | G250: App B p.48 | I250: Sched C PDF (council.nyc.gov) · Open Data 4d7f-74pe · MOCS Award Tracker (EIN) · Checkbook NYC (payments)
A251: MDI (SI member) | B251: Local Initiatives | C251: Morano | D251: CrimsonRise, Inc. | E251: 871249856 | F251: 5000 | G251: App B p.60 | I251: Sched C PDF (council.nyc.gov) · Open Data 4d7f-74pe · MOCS Award Tracker (EIN) · Checkbook NYC (payments)
A252: MDI (SI member) | B252: Local Initiatives | C252: Hanks | D252: Department of Education - District 31 Region 7 - | E252: 136400434 | F252: 5000 | G252: App B p.62 | I252: Sched C PDF (council.nyc.gov) · Open Data 4d7f-74pe · MOCS Award Tracker (EIN) · Checkbook NYC (payments)
A253: MDI (SI member) | B253: Local Initiatives | C253: Hanks | D253: Department of Education - Port Richmond High School | E253: 136400434 | F253: 5000 | G253: App B p.63 | I253: Sched C PDF (council.nyc.gov) · Open Data 4d7f-74pe · MOCS Award Tracker (EIN) · Checkbook NYC (payments)
A254: MDI (SI member) | B254: Local Initiatives | C254: Hanks | D254: Department of Education - Port Richmond High School | E254: 136400434 | F254: 5000 | G254: App B p.63 | I254: Sched C PDF (council.nyc.gov) · Open Data 4d7f-74pe · MOCS Award Tracker (EIN) · Checkbook NYC (payments)
A255: MDI (SI member) | B255: Local Initiatives | C255: Hanks | D255: Department of Education - Port Richmond High School (31R445) - Girls Cross Country/Track & | E255: 136400434 | F255: 5000 | G255: App B p.63 | I255: Sched C PDF (council.nyc.gov) · Open Data 4d7f-74pe · MOCS Award Tracker (EIN) · Checkbook NYC (payments)
A256: MDI (SI member) | B256: Local Initiatives | C256: Carr | D256: Department of Education - Public School 11R (31R011) | E256: 136400434 | F256: 5000 | G256: App B p.63 | I256: Sched C PDF (council.nyc.gov) · Open Data 4d7f-74pe · MOCS Award Tracker (EIN) · Checkbook NYC (payments)
A257: MDI (SI member) | B257: Local Initiatives | C257: Carr | D257: Department of Education - Public School 46R (31R046) | E257: 136400434 | F257: 5000 | G257: App B p.65 | I257: Sched C PDF (council.nyc.gov) · Open Data 4d7f-74pe · MOCS Award Tracker (EIN) · Checkbook NYC (payments)
A258: MDI (SI member) | B258: Local Initiatives | C258: Carr | D258: Department of Parks and Recreation - Port-A-Sans | E258: 136400434 | F258: 5000 | G258: App B p.68 | I258: Sched C PDF (council.nyc.gov) · Open Data 4d7f-74pe · MOCS Award Tracker (EIN) · Checkbook NYC (payments)
A259: MDI (SI member) | B259: Local Initiatives | C259: Hanks | D259: Department of Youth and Community Development | E259: 136400434 | F259: 5000 | G259: App B p.69 | I259: Sched C PDF (council.nyc.gov) · Open Data 4d7f-74pe · MOCS Award Tracker (EIN) · Checkbook NYC (payments)
A260: MDI (SI member) | B260: Local Initiatives | C260: Hanks | D260: Dr. Theodore A. Atlas Foundation, Inc. - Council District 49 | E260: 134012789 | F260: 5000 | G260: App B p.70 | I260: Sched C PDF (council.nyc.gov) · Open Data 4d7f-74pe · MOCS Award Tracker (EIN) · Checkbook NYC (payments)
... A491: MDI (other CM) | B491: Citywide Initiative | C491: Santosuosso | D491: Muslim American Society of Brooklyn and Staten Island — case management (CD47) | E491: 454661688 | F491: 40000 | G491: PDF p.58 (member listing) | I491: Sched C PDF (council.nyc.gov) · Open Data 4d7f-74pe · MOCS Award Tracker (EIN) · Checkbook NYC (payments)
A492: MDI (other CM) | B492: Citywide Initiative | C492: Aviles | D492: Muslim American Society of Brooklyn and Staten Island (CD47) | E492: 45-4661688 | F492: 15000 | G492: p.68 | H492: bi-borough org | I492: Sched C PDF (council.nyc.gov) · Open Data 4d7f-74pe · MOCS Award Tracker (EIN) · Checkbook NYC (payments)
A493: MDI (other CM) | B493: Citywide Initiative | C493: Santosuosso | D493: Muslim American Society of Brooklyn and Staten Island (CD47) | E493: 45-4661688 | F493: 10000 | G493: p.68 | H493: bi-borough org | I493: Sched C PDF (council.nyc.gov) · Open Data 4d7f-74pe · MOCS Award Tracker (EIN) · Checkbook NYC (payments)
A494: MDI (other CM) | B494: Local Initiatives | C494: Santosuosso | D494: Muslim American Society of Brooklyn and Staten Island — Youth & Family (CD47) | E494: 454661688 | F494: 15000 | G494: App B p.102 | H494: bi-borough org | I494: Sched C PDF (council.nyc.gov) · Open Data 4d7f-74pe · MOCS Award Tracker (EIN) · Checkbook NYC (payments)
A495: MDI (other CM) | B495: Youth Discretionary | C495: Vernikov | D495: JCC of Staten Island — Sunrise Day Camp | E495: 135562256 | F495: 7000 | G495: App C p.173 | I495: Sched C PDF (council.nyc.gov) · Open Data 4d7f-74pe · MOCS Award Tracker (EIN) · Checkbook NYC (payments)
A496: MDI (other CM) | B496: Youth Discretionary | C496: Santosuosso | D496: Muslim American Society of Brooklyn and Staten Island — Youth Programs (CD47) | E496: 454661688 | F496: 5000 | G496: App C p.177 | H496: bi-borough org | I496: Sched C PDF (council.nyc.gov) · Open Data 4d7f-74pe · MOCS Award Tracker (EIN) · Checkbook NYC (payments)
A497: SI Delegation | B497: Boroughwide Needs Initiative | C497: SI Delegation | D497: Carl V. Bini Memorial Fund, The - Concert Series | E497: 320144539 | F497: 20000 | G497: PDF p.25 (member listing) | I497: Sched C PDF (council.nyc.gov) · Open Data 4d7f-74pe · MOCS Award Tracker (EIN) · Checkbook NYC (payments)
A498: SI Delegation | B498: Boroughwide Needs Initiative | C498: SI Delegation | D498: Eden II School for Autistic Children, Inc. | E498: 132872916 | F498: 15000 | G498: PDF p.26 (member listing) | I498: Sched C PDF (council.nyc.gov) · Open Data 4d7f-74pe · MOCS Award Tracker (EIN) · Checkbook NYC (payments)
A499: SI Delegation | B499: Boroughwide Needs Initiative | C499: SI Delegation | D499: Richmond Engine Company No. 1 | E499: 132943389 | F499: 15000 | G499: PDF p.29 (member listing) | I499: Sched C PDF (council.nyc.gov) · Open Data 4d7f-74pe · MOCS Award Tracker (EIN) · Checkbook NYC (payments)
A500: SI Delegation | B500: Boroughwide Needs Initiative | C500: SI Delegation | D500: West Brighton Community Local Development Corporation | E500: 133046424 | F500: 13000 | G500: PDF p.31 (member listing) | I500: Sched C PDF (council.nyc.gov) · Open Data 4d7f-74pe · MOCS Award Tracker (EIN) · Checkbook NYC (payments)
A501: SI Delegation | B501: Boroughwide Needs Initiative | C501: SI Delegation | D501: Camelot of Staten Island, Inc. | E501: 237091329 | F501: 10000 | G501: PDF p.25 (member listing) | I501: Sched C PDF (council.nyc.gov) · Open Data 4d7f-74pe · MOCS Award Tracker (EIN) · Checkbook NYC (payments)
A502: SI Delegation | B502: Boroughwide Needs Initiative | C502: SI Delegation | D502: Casa Belvedere, The Italian Cultural Foundation | E502: 264411728 | F502: 10000 | G502: PDF p.25 (member listing) | I502: Sched C PDF (council.nyc.gov) · Open Data 4d7f-74pe · MOCS Award Tracker (EIN) · Checkbook NYC (payments)
A503: SI Delegation | B503: Boroughwide Needs Initiative | C503: SI Delegation | D503: Club | E503: 264411728 | F503: 10000 | G503: PDF p.25 (member listing) | I503: Sched C PDF (council.nyc.gov) · Open Data 4d7f-74pe · MOCS Award Tracker (EIN) · Checkbook NYC (payments)
A504: SI Delegation | B504: Boroughwide Needs Initiative | C504: SI Delegation | D504: Grace Foundation of New York | E504: 134131863 | F504: 10000 | G504: PDF p.27 (member listing) | I504: Sched C PDF (council.nyc.gov) · Open Data 4d7f-74pe · MOCS Award Tracker (EIN) · Checkbook NYC (payments)
A505: SI Delegation | B505: Boroughwide Needs Initiative | C505: SI Delegation | D505: On Your Mark, Inc. | E505: 133128315 | F505: 9000 | G505: PDF p.29 (member listing) | I505: Sched C PDF (council.nyc.gov) · Open Data 4d7f-74pe · MOCS Award Tracker (EIN) · Checkbook NYC (payments)
A506: SI Delegation | B506: Boroughwide Needs Initiative | C506: SI Delegation | D506: Seamen's Society for Children and Families | E506: 135563010 | F506: 5000 | G506: PDF p.29 (member listing) | I506: Sched C PDF (council.nyc.gov) · Open Data 4d7f-74pe · MOCS Award Tracker (EIN) · Checkbook NYC (payments)
A507: SI Delegation | B507: Boroughwide Needs Initiative | C507: SI Delegation | D507: Staten Island Ice Hockey Association, Inc. | E507: 132939069 | F507: 3000 | G507: PDF p.30 (member listing) | I507: Sched C PDF (council.nyc.gov) · Open Data 4d7f-74pe · MOCS Award Tracker (EIN) · Checkbook NYC (payments)
A508: Speaker | B508: designated local | C508: Carr+SI Del | D508: Carr, Staten Staten Island Economic Development Corporation - | E508: 133706442 | F508: 140000 | G508: App B p.136 | I508: Sched C PDF (council.nyc.gov) · Open Data 4d7f-74pe · MOCS Award Tracker (EIN) · Checkbook NYC (payments)
... A541: Speaker | B541: pool item (SI org, general) | C541: — | D541: Staten Island Children's Museum | E541: 237379930 | F541: 20000 | G541: Speaker itemization (PDF p.288) | I541: Sched C PDF (council.nyc.gov) · Open Data 4d7f-74pe · MOCS Award Tracker (EIN) · Checkbook NYC (payments)
A542: Citywide initiative | B542: AAPI Community Support | D542: Chinese American Planning Council, Inc. – To Serve Staten Island | E542: 13-6202692 | F542: 50000 | G542: p.6 | I542: Sched C PDF (council.nyc.gov) · Open Data 4d7f-74pe · MOCS Award Tracker (EIN) · Checkbook NYC (payments)
A543: Citywide initiative | B543: Adult Literacy Initiative | D543: Jewish Community Center of Staten Island, Inc. | E543: 13-5562256 | F543: 400628 | G543: p.18 | I543: Sched C PDF (council.nyc.gov) · Open Data 4d7f-74pe · MOCS Award Tracker (EIN) · Checkbook NYC (payments)
A544: Citywide initiative | B544: Artificial Intelligence Community Engage | D544: Jewish Community Center of Staten Island, Inc. | E544: 13-5562256 | F544: 36000 | G544: p.7 | I544: Sched C PDF (council.nyc.gov) · Open Data 4d7f-74pe · MOCS Award Tracker (EIN) · Checkbook NYC (payments)
A545: Citywide initiative | B545: Autism Awareness | D545: Eden II School for Autistic Children, Inc. | E545: 13-2872916 | F545: 109012 | G545: p.156 | I545: Sched C PDF (council.nyc.gov) · Open Data 4d7f-74pe · MOCS Award Tracker (EIN) · Checkbook NYC (payments)
A546: Citywide initiative | B546: Autism Awareness | D546: Jewish Community Center of Staten Island, Inc. | E546: 13-5562256 | F546: 50000 | G546: p.156 | I546: Sched C PDF (council.nyc.gov) · Open Data 4d7f-74pe · MOCS Award Tracker (EIN) · Checkbook NYC (payments)
A547: Citywide initiative | B547: Autism Awareness | D547: On Your Mark, Inc. | E547: 13-3128315 | F547: 25000 | G547: p.156 | I547: Sched C PDF (council.nyc.gov) · Open Data 4d7f-74pe · MOCS Award Tracker (EIN) · Checkbook NYC (payments)
A548: Citywide initiative | B548: Cancer Services | D548: Richmond Medical Center | E548: 74-3177454 | F548: 49375 | G548: p.122 | I548: Sched C PDF (council.nyc.gov) · Open Data 4d7f-74pe · MOCS Award Tracker (EIN) · Checkbook NYC (payments)
A549: Citywide initiative | B549: Chamber on the Go and Small Business Ass | D549: Staten Island Chamber of Commerce Foundation, Inc. | E549: 13-4069282 | F549: 130265 | G549: p.204 | I549: Sched C PDF (council.nyc.gov) · Open Data 4d7f-74pe · MOCS Award Tracker (EIN) · Checkbook NYC (payments)
A550: Citywide initiative | B550: Citywide Young Adult Entrepreneurship Pr | D550: Staten Island Chamber of Commerce Foundation, Inc. | E550: 13-4069282 | F550: 200000 | G550: p.227 | I550: Sched C PDF (council.nyc.gov) · Open Data 4d7f-74pe · MOCS Award Tracker (EIN) · Checkbook NYC (payments)
A551: Citywide initiative | B551: Coalition Theaters of Color | D551: Universal Temple of the Arts, Inc. | E551: 13-3335286 | F551: 70000 | G551: p.29 | I551: Sched C PDF (council.nyc.gov) · Open Data 4d7f-74pe · MOCS Award Tracker (EIN) · Checkbook NYC (payments)
A552: Citywide initiative | B552: Community Composting at Cultural Institu | D552: Snug Harbor Cultural Center & Botanical Garden | E552: 80-0193388 | F552: 335000 | G552: p.108 | I552: Sched C PDF (council.nyc.gov) · Open Data 4d7f-74pe · MOCS Award Tracker (EIN) · Checkbook NYC (payments)
...

Sheet Citywide to SI
A1: CITYWIDE INITIATIVES TO SI — EVERY ORGANIZATION, ITEMIZED (FY27 Schedule C Final-3)
A2: All 55 organization lines behind the 42 SI-reaching citywide initiatives. Off-Island organizations delivering on SI are shaded gold. Foots to the $6,553,360 citywide-to-SI expense line on Grand Total (B13). Rev Jul 6: Dibra Community Organization $25,000 added under Welcome NYC (p.151, DYCD 260, asylum-seeker services) — previously missed; distinct from Dibra’s $25,000 Speaker pool item (p.270).
A3: Channel note: this tab is CITYWIDE-INITIATIVE dollars only. Speaker-pool and member dollars are on their own tabs. Dibra appears in BOTH: $25,000 here (Welcome NYC, p.151) AND $25,000 on “Speaker — Pool Items” (p.270) — two distinct printed lines. Dibra FY27 total incl. Hanks Youth MDI: $65,000.
A4: Initiative | B4: Organization — Program | C4: EIN | D4: Amount | E4: Org base / SI designation | F4: Sched C ref
A5: Day Laborer Workforce Initiative | B5: La Colmena, Inc. | C5: 47-2787706 | D5: 646666 | E5: SI-based org | F5: p.206
A6: Day Laborer Workforce Initiative | B6: African Refuge, Inc. | C6: 01-0873188 | D6: 100000 | E6: SI-based org | F6: p.206
B7: Subtotal — Day Laborer Workforce Initiative (2 lines) | D7: 746666
A8: HIV/AIDS Pathways to Care | B8: Community Health Action of Staten Island, Inc. | C8: 13-3556132 | D8: 363752 | E8: SI-based org | F8: p.124
A9: HIV/AIDS Pathways to Care | B9: Jewish Community Center of Staten Island, Inc. | C9: 13-5562256 | D9: 101338 | E9: SI-based org | F9: p.124
B10: Subtotal — HIV/AIDS Pathways to Care (2 lines) | D10: 465090
A11: LGBTQIA+ Community Services | B11: Pride Center of Staten Island, Inc. | C11: 46-3358895 | D11: 444375 | E11: SI-based org | F11: p.17
B12: Subtotal — LGBTQIA+ Community Services (1 line) | D12: 444375
A13: Adult Literacy Initiative | B13: Jewish Community Center of Staten Island, Inc. | C13: 13-5562256 | D13: 400628 | E13: SI-based org | F13: p.18
B14: Subtotal — Adult Literacy Initiative (1 line) | D14: 400628
A15: Opioid Prevention and Treatment | B15: Community Health Action of Staten Island, Inc. | C15: 13-3556132 | D15: 350000 | E15: SI-based org | F15: p.163
B16: Subtotal — Opioid Prevention and Treatment (1 line) | D16: 350000
A17: Community Composting at Cultural Institutions | B17: Snug Harbor Cultural Center & Botanical Garden | C17: 80-0193388 | D17: 335000 | E17: SI-based org | F17: p.108
B18: Subtotal — Community Composting at Cultural Institutions (1 line) | D18: 335000
A19: Trans Equity Programs | B19: Pride Center of Staten Island, Inc. | C19: 46-3358895 | D19: 320000 | E19: SI-based org | F19: p.20
B20: Subtotal — Trans Equity Programs (1 line) | D20: 320000
A21: Court-Involved Youth Mental Health Initiative | B21: Richmond Medical Center | C21: 74-3177454 | D21: 259000 | E21: SI-based org | F21: p.158
B22: Subtotal — Court-Involved Youth Mental Health Initiative (1 line) | D22: 259000
A23: Violence Prevention and Intervention for Young People | B23: New York Center for Interpersonal Development, Inc. | C23: 23-7085239 | D23: 80000 | E23: SI-based org | F23: p.201
A24: Violence Prevention and Intervention for Young People | B24: IlluminArt Productions – Port Richmond High School (31R445) | C24: 42-1727647 | D24: 40000 | E24: SI-based org | F24: p.201
A25: Violence Prevention and Intervention for Young People | B25: IlluminArt Productions – Susan E. Wagner High School (31R460) | C25: 42-1727647 | D25: 40000 | E25: SI-based org | F25: p.201
A26: Violence Prevention and Intervention for Young People | B26: Sundog Theatre, Inc. – Curtis High School (31R450) | C26: 45-0476945 | D26: 18000 | E26: SI-based org | F26: p.202
A27: Violence Prevention and Intervention for Young People | B27: Sundog Theatre, Inc. – Intermediate School 49R - Berta A. Dreyfus (31R049) | C27: 45-0476945 | D27: 18000 | E27: SI-based org | F27: p.202
A28: Violence Prevention and Intervention for Young People | B28: Sundog Theatre, Inc. | C28: 45-0476945 | D28: 6000 | E28: SI-based org | F28: p.202
B29: Subtotal — Violence Prevention and Intervention for Young People (6 lines) | D29: 202000
A30: Citywide Young Adult Entrepreneurship Program | B30: Staten Island Chamber of Commerce Foundation, Inc. | C30: 13-4069282 | D30: 200000 | E30: SI-based org | F30: p.227
B31: Subtotal — Citywide Young Adult Entrepreneurship Program (1 line) | D31: 200000
A32: Community Interpreter Bank | B32: La Colmena NYC, Inc. | C32: 47-2787706 | D32: 100000 | E32: SI-based org | F32: p.8
A33: Community Interpreter Bank | B33: Staten Island Immigrant Center – To Serve Staten Island | C33: 92-1134292 | D33: 50000 | E33: SI-based org | F33: p.8
A34: Community Interpreter Bank | B34: United Chinese Association of Brooklyn – To Serve Staten Island | C34: 37-1469112 | D34: 50000 | E34: Brooklyn org — printed “To Serve Staten Island” | F34: p.8
B35: Subtotal — Community Interpreter Bank (3 lines) | D35: 200000
A36: Autism Awareness | B36: Eden II School for Autistic Children, Inc. | C36: 13-2872916 | D36: 109012 | E36: SI-based org | F36: p.156
A37: Autism Awareness | B37: Jewish Community Center of Staten Island, Inc. | C37: 13-5562256 | D37: 50000 | E37: SI-based org | F37: p.156
A38: Autism Awareness | B38: On Your Mark, Inc. | C38: 13-3128315 | D38: 25000 | E38: SI-based org | F38: p.156
B39: Subtotal — Autism Awareness (3 lines) | D39: 184012
A40: Social Adult Day Care | B40: Jewish Community Center of Staten Island, Inc. | C40: 13-5562256 | D40: 167284 | E40: SI-based org | F40: p.171
B41: Subtotal — Social Adult Day Care (1 line) | D41: 167284
A42: Legal Services for Day Laborers and Domestic Workers | B42: La Colmena NYC, Inc. | C42: 47-2787706 | D42: 150000 | E42: SI-based org | F42: p.148
B43: Subtotal — Legal Services for Day Laborers and Domestic Workers (1 line) | D43: 150000
A44: Chamber on the Go and Small Business Assistance | B44: Staten Island Chamber of Commerce Foundation, Inc. | C44: 13-4069282 | D44: 130265 | E44: SI-based org | F44: p.204
B45: Subtotal — Chamber on the Go and Small Business Assistance (1 line) | D45: 130265
A46: LGBTQIA+ Youth Support and Services | B46: Pride Center of Staten Island, Inc. | C46: 46-3358895 | D46: 130000 | E46: SI-based org | F46: p.228
B47: Subtotal — LGBTQIA+ Youth Support and Services (1 line) | D47: 130000
A48: Construction Site Safety Training | B48: La Colmena NYC, Inc. | C48: 47-2787706 | D48: 125000 | E48: SI-based org | F48: p.205
B49: Subtotal — Construction Site Safety Training (1 line) | D49: 125000
A50: Community Housing Preservation Strategies | B50: Northfield Community LDC of Staten Island, Inc. – HPI | C50: 13-2974137 | D50: 61000 | E50: SI-based org | F50: p.134
A51: Community Housing Preservation Strategies | B51: Northfield Community LDC of Staten Island, Inc. – CCC | C51: 13-2974137 | D51: 54257 | E51: SI-based org | F51: p.134
B52: Subtotal — Community Housing Preservation Strategies (2 lines) | D52: 115257
A53: Developmental, Psychological and Behavioral Health Services | B53: Richmond Medical Center | C53: 74-3177454 | D53: 107103 | E53: SI-based org | F53: p.158
B54: Subtotal — Developmental, Psychological and Behavioral Health Services (1 line) | D54: 107103
A55: Culturally Specific Gender Based Violence Services | B55: Staten Island Community Job Center, Inc. | C55: 47-2787706 | D55: 100000 | E55: SI-based org | F55: p.222
B56: Subtotal — Culturally Specific Gender Based Violence Services (1 line) | D56: 100000
A57: Initiative to Combat Sexual Assault | B57: Richmond Medical Center | C57: 74-3177454 | D57: 100000 | E57: SI-based org | F57: p.24
B58: Subtotal — Initiative to Combat Sexual Assault (1 line) | D58: 100000
A59: LGBTQIA+ Older Adult Services in Every Borough | B59: Pride Center of Staten Island, Inc. | C59: 46-3358895 | D59: 100000 | E59: SI-based org | F59: p.168
B60: Subtotal — LGBTQIA+ Older Adult Services in Every Borough (1 line) | D60: 100000
A61: Community Land Trust | B61: Northfield Community LDC of Staten Island, Inc. | C61: 13-2974137 | D61: 98250 | E61: SI-based org | F61: p.135
B62: Subtotal — Community Land Trust (1 line) | D62: 98250
A63: Naturally Occurring Retirement Communities (NORCs) | B63: Jewish Community Center of Staten Island, Inc. – Stapleton NORC | C63: 13-5562256 | D63: 96421 | E63: SI-based org | F63: p.169
B64: Subtotal — Naturally Occurring Retirement Communities (NORCs) (1 line) | D64: 96421
A65: Viral Hepatitis Prevention | B65: Community Health Action of Staten Island, Inc. | C65: 13-3556132 | D65: 85801 | E65: SI-based org | F65: p.127
B66: Subtotal — Viral Hepatitis Prevention (1 line) | D66: 85801
A67: MCCAP Initiative | B67: Jewish Community Center of Staten Island, Inc. | C67: 13-5562256 | D67: 82000 | E67: SI-based org | F67: p.125
B68: Subtotal — MCCAP Initiative (1 line) | D68: 82000
A69: Healthy Beginnings | B69: Richmond Medical Center | C69: 74-3177454 | D69: 76319 | E69: SI-based org | F69: p.123
B70: Subtotal — Healthy Beginnings (1 line) | D70: 76319
A71: Legal Services for AAPI Communities | B71: Chinese American Planning Council, Inc. – To Serve Staten Island | C71: 13-6202692 | D71: 75000 | E71: Citywide org (Manhattan HQ) — printed “To Serve Staten Island” | F71: p.147
B72: Subtotal — Legal Services for AAPI Communities (1 line) | D72: 75000
A73: Welcome NYC | B73: La Colmena NYC, Inc. | C73: 47-2787706 | D73: 50000 | E73: SI-based org | F73: p.151
A74: Welcome NYC | B74: Dibra Community Organization, Inc. – New York City Asylum Seekers services | C74: 27-4684048 | D74: 25000 | E74: SI-based org | F74: p.151
B75: Subtotal — Welcome NYC (2 lines) | D75: 75000
A76: MWBE Leadership Associations | B76: West Brighton Community Local Development Corporation | C76: 13-3046424 | D76: 73070 | E76: SI-based org | F76: p.209
B77: Subtotal — MWBE Leadership Associations (1 line) | D77: 73070
A78: Coalition Theaters of Color | B78: Universal Temple of the Arts, Inc. | C78: 13-3335286 | D78: 70000 | E78: SI-based org | F78: p.29
B79: Subtotal — Coalition Theaters of Color (1 line) | D79: 70000
A80: Young Women's Leadership Development | B80: Staten Island Urban Center | C80: 37-1833463 | D80: 64576 | E80: SI-based org | F80: p.225
B81: Subtotal — Young Women's Leadership Development (1 line) | D81: 64576
A82: Five Borough Chamber Alliance | B82: Staten Island Chamber of Commerce Foundation, Inc. | C82: 13-4069282 | D82: 62500 | E82: SI-based org | F82: p.207
B83: Subtotal — Five Borough Chamber Alliance (1 line) | D83: 62500
A84: Elie Wiesel Holocaust Survivors | B84: Jewish Community Center of Staten Island, Inc. | C84: 13-5562256 | D84: 56100 | E84: SI-based org | F84: p.167
B85: Subtotal — Elie Wiesel Holocaust Survivors (1 line) | D85: 56100
A86: Support for Victims of Human Trafficking | B86: Seamen's Society for Children and Families | C86: 13-5563010 | D86: 52935 | E86: SI-based org | F86: p.25
B87: Subtotal — Support for Victims of Human Trafficking (1 line) | D87: 52935
A88: AAPI Community Support | B88: Chinese American Planning Council, Inc. – To Serve Staten Island | C88: 13-6202692 | D88: 50000 | E88: Citywide org (Manhattan HQ) — printed “To Serve Staten Island” | F88: p.6
B89: Subtotal — AAPI Community Support (1 line) | D89: 50000
A90: Immigrant Rights Workshops | B90: La Colmena NYC, Inc. | C90: 47-2787706 | D90: 50000 | E90: SI-based org | F90: p.145
B91: Subtotal — Immigrant Rights Workshops (1 line) | D91: 50000
A92: Older Adults Mental Health | B92: Jewish Community Center of Staten Island, Inc. | C92: 13-5562256 | D92: 50000 | E92: SI-based org | F92: p.162
B93: Subtotal — Older Adults Mental Health (1 line) | D93: 50000
A94: Cancer Services | B94: Richmond Medical Center | C94: 74-3177454 | D94: 49375 | E94: SI-based org | F94: p.122
B95: Subtotal — Cancer Services (1 line) | D95: 49375
A96: Artificial Intelligence Community Engagement | B96: Jewish Community Center of Staten Island, Inc. | C96: 13-5562256 | D96: 36000 | E96: SI-based org | F96: p.7
B97: Subtotal — Artificial Intelligence Community Engagement (1 line) | D97: 36000
A98: Cultural Immigrant Initiative | B98: School 019R The Curtis School (31R019) Northern Manhattan Arts Alliance – Arts Programming | C98: 26-1997496 | D98: 10000 | E98: Manhattan org — SI school program (31R019 Curtis) | F98: p.69
B99: Subtotal — Cultural Immigrant Initiative (1 line) | D99: 10000
A100: Older Adult Centers, Programs, and Services | B100: Jewish Community Center of Staten Island, Inc. – Stapleton Senior Center | C100: 13-5562256 | D100: 8333 | E100: SI-based org | F100: p.170
...

Sheet SI Delegation Pot (11)
A1: SI DELEGATION — BOROUGHWIDE NEEDS ($120,000 / 11), Sched C p.4 listing
A3: Organization | B3: EIN | C3: Amount | D3: Sched C ref
A4: Carl V. Bini Memorial Fund, The - Concert Series | B4: 320144539 | C4: 20000 | D4: PDF p.25
A5: Eden II School for Autistic Children, Inc. | B5: 132872916 | C5: 15000 | D5: PDF p.26
A6: Richmond Engine Company No. 1 | B6: 132943389 | C6: 15000 | D6: PDF p.29
A7: West Brighton Community Local Development Corporation | B7: 133046424 | C7: 13000 | D7: PDF p.31
A8: Camelot of Staten Island, Inc. | B8: 237091329 | C8: 10000 | D8: PDF p.25
A9: Casa Belvedere, The Italian Cultural Foundation | B9: 264411728 | C9: 10000 | D9: PDF p.25
A10: Casa Belvedere — (program line) | B10: 264411728 | C10: 10000 | D10: PDF p.25
A11: Grace Foundation of New York | B11: 134131863 | C11: 10000 | D11: PDF p.27
A12: On Your Mark, Inc. | B12: 133128315 | C12: 9000 | D12: PDF p.29
A13: Seamen's Society for Children and Families | B13: 135563010 | C13: 5000 | D13: PDF p.29
A14: Staten Island Ice Hockey Association, Inc. | B14: 132939069 | C14: 3000 | D14: PDF p.30
B15: TOTAL | C15: =SUM(C4:C14) -> 120000

Sheet Hanks — All Orgs (DB)
A1: CM HANKS — EVERY FUNDED ORGANIZATION, FY27 (Council discretionary database — authoritative)
A2: Source: ExportedSearchResults.xlsx (Council Finance export, 8,597 rows). Green rows = SU-CASA (database-only; not yet printed in Schedule C). Award-letter re-foot should use these per-EIN amounts.
A4: MDI pot | B4: Organization (Legal Name) | C4: EIN | D4: Amount | E4: Program / Site
A5: A GREENER NYC
B6: City Parks Foundation | C6: 133561657 | D6: 25000 | E6: CityParks Play, CityParks Learn & CityParks Build - Council District 4
B7: Citizens Committee for New York City, Inc. | C7: 510171818 | D7: 20000 | E7: Council District 49
B8: Waterfront Alliance, Inc. | C8: 134355067 | D8: 15000 | E8: Education & Programming - Council District 49
B9: Billion Oyster Project, Inc. | C9: 272918478 | D9: 10000 | E9: School Network
B10: Snug Harbor Cultural Center and Botanical Garden | C10: 800193388 | D10: 10000 | E10: Green Workforce Development & Education Program - Council District 49
B11: Jewish Community Center of Staten Island, Inc. | C11: 135562256 | D11: 10000 | E11: Career Readiness Program
B12: New York City H2O | C12: 453860014 | D12: 10000 | E12: Water Ecology & Engineering Programming - Council District 49
A13: AGING
B14: Community Agency for Senior Citizens, Inc. | C14: 133263537 | D14: 15000 | E14: Cassidy Coles Older Adult Center
B15: Community Agency for Senior Citizens, Inc. | C15: 133263537 | D15: 15000 | E15: New Lane Older Adult Center
B16: Jewish Community Center of Staten Island, Inc. | C16: 135562256 | D16: 15000 | E16: Stapleton Older Adult Center
B17: Staten Island Community Services Friendship Clubs, Inc. | C17: 132778244 | D17: 15000 | E17: Todt Hill Friendship Club
B18: Catholic Charities of Staten Island | C18: 135562286 | D18: 15000 | E18: West Brighton Senior Center
B19: Catholic Charities of Staten Island | C19: 135562286 | D19: 15000 | E19: Anderson Neighborhood Senior Center
B20: Center For Hope Services, Inc. | C20: 882507208 | D20: 10000 | E20: Age-Friendly Care Program - Council District 49
B21: Lifestyles for the Disabled, Inc. | C21: 133740011 | D21: 10000 | E21: Serving Our Seniors - Council District 49
A22: ANTI-POVERTY
B23: Dr. Theodore A. Atlas Foundation, Inc. | C23: 134012789 | D23: 30000 | E23: Food Distribution - Council District 49
B24: Citizens Committee for New York City, Inc. | C24: 510171818 | D24: 10000 | E24: nan
B25: University of Notre Dame Alumni Club of Staten Island | C25: 311344537 | D25: 5000 | E25: Bread of Life Food Drive - Council District 49.
B26: Mrs. Fairy Grandz, Inc. | C26: 331833069 | D26: 5000 | E26: nan
A27: COMMUNITY SAFETY AND VICTIM SERVICES
B28: New York Center for Interpersonal Development, Inc. | C28: 237085239 | D28: 80000 | E28: Council District 49
B29: Dr. Theodore A. Atlas Foundation, Inc. | C29: 134012789 | D29: 7500 | E29: nan
B30: Dr. Theodore A. Atlas Foundation, Inc. | C30: 134012789 | D30: 7500 | E30: nan
B31: Emergency Children's Help Organization, Inc. | C31: 113828185 | D31: 5000 | E31: Emergency Assistance Program - Council District 49
A32: CULTURAL AFTER-SCHOOL ADVENTURE (CASA)
B33: Roundabout Theatre Company, Inc. | C33: 136192346 | D33: 20000 | E33: Port Richmond High School (31R445)
B34: Staten Island Institute of Arts and Sciences | C34: 135564127 | D34: 20000 | E34: Public School 013R L. Lindemeyer (31R013)
B35: Children's Aid Society, The | C35: 135562191 | D35: 20000 | E35: Curtis High School (31R450)
B36: National Lighthouse Museum | C36: 134055215 | D36: 20000 | E36: The Harbor View School (31R059)
B37: IlluminArt Productions | C37: 421727647 | D37: 20000 | E37: Public School 019R The Curtis School (31R019)
B38: Projectivity Group, Inc. | C38: 475358971 | D38: 20000 | E38: Public School 044R Thomas C. Brown (31R044)
B39: Center for Educational Innovation | C39: 134113613 | D39: 20000 | E39: P.S 016 John J. Driscoll(31R016) & P.S 59 The Harbor View School(31R05
B40: Canvas Institute | C40: 824902021 | D40: 20000 | E40: Public School 016R John J. Driscoll (31R016)
B41: Snug Harbor Cultural Center and Botanical Garden | C41: 800193388 | D41: 20000 | E41: Public School 21R Margaret Emery-Elm Park (31R021)
B42: Sundog Theatre, Inc. | C42: 450476945 | D42: 20000 | E42: Public School 74R Future Leaders Elementary School (31R074)
B43: Staten Island Children's Museum | C43: 237379930 | D43: 20000 | E43: Public School 65R The Academy of Innovative Learning (31R065)
B44: Staten Island Institute of Arts and Sciences | C44: 135564127 | D44: 20000 | E44: Public School 057R Hubert H. Humphrey (31R057)
... B49: Marquis Studios, Ltd. | C49: 133047206 | D49: 20000 | E49: Public School 045R John Tyler (31R045)
A50: CULTURAL IMMIGRANT INITIATIVE
B51: Universal Temple of the Arts, Inc. | C51: 133335286 | D51: 30000 | E51: Council District 49
B52: Snug Harbor Cultural Center and Botanical Garden | C52: 800193388 | D52: 20000 | E52: Asian Cultural Programs
B53: Casa Belvedere, The Italian Cultural Foundation | C53: 264411728 | D53: 15000 | E53: nan
B54: Noble Maritime Collection, The | C54: 133351673 | D54: 10000 | E54: La Capitana Dice Program
B55: Ballroom Basix USA, Inc. | C55: 273218865 | D55: 10000 | E55: nan
B56: National Lighthouse Museum | C56: 134055215 | D56: 10000 | E56: nan
B57: Canvas Institute | C57: 824902021 | D57: 10000 | E57: Council District 49
B58: Midtown Management Group, Inc. | C58: 133192793 | D58: 10000 | E58: The Waverly Academy of Empowered Learners (31R084)
B59: Friends of Alice Austen House, Inc. | C59: 133248928 | D59: 10000 | E59: Public School 020R Port Richmond (31R020)
B60: Jewish Community Center of Staten Island, Inc. | C60: 135562256 | D60: 10000 | E60: nan
B61: IlluminArt Productions | C61: 421727647 | D61: 10000 | E61: Cultural Immigrant Programming
A62: DIGITAL INCLUSION AND LITERACY INITIATIVE
B63: Staten Island Industrial Alliance/Northshore Leadership Alliance Corp. | C63: 922412852 | D63: 30000 | E63: Workforce Training Hub District 49
B64: Mouse, Inc. | C64: 133973196 | D64: 20000 | E64: Intermediate School 027R (31R027) & Staten Island School of Civic Lead
B65: PowerMyLearning, Inc. | C65: 133935309 | D65: 20000 | E65: Public School 21R Margaret Emery-Elm Park (31R021)
B66: West Brighton Community Local Development Corporation | C66: 133046424 | D66: 20000 | E66: Small Business Technical Assistance Program
A67: DOMESTIC VIOLENCE AND EMPOWERMENT (DOVE) INITIATIVE
B68: Justice Innovation, Inc. | C68: 852810883 | D68: 50000 | E68: Council District 49
B69: Legal Services NYC | C69: 132600199 | D69: 25000 | E69: Council District 49
B70: Community Health Action of Staten Island, Inc. | C70: 133556132 | D70: 20000 | E70: Council District 49
B71: Metropolitan New York Coordinating Council on Jewish Poverty, Inc. | C71: 132738818 | D71: 20000 | E71: Council District 49
B72: Legal Aid Society | C72: 135562265 | D72: 20000 | E72: Council District 49
B73: Seamen's Society for Children and Families | C73: 135563010 | D73: 15000 | E73: nan
B74: Community Agency for Senior Citizens, Inc. | C74: 133263537 | D74: 10000 | E74: Council District 49
B75: Pride Center of Staten Island, Inc. | C75: 463358895 | D75: 10000 | E75: Council District 49
B76: Seamen's Society for Children and Families | C76: 135563010 | D76: 10000 | E76: Council District 49
B77: Jewish Board of Family and Children's Services, Inc. | C77: 135564937 | D77: 10000 | E77: Council Disitrict 49
B78: Arab-American Family Support Center, Inc., The | C78: 113167245 | D78: 5000 | E78: Council District 49
A79: LOCAL
B80: Staten Island Chamber of Commerce Foundation, Inc. | C80: 134069282 | D80: 30000 | E80: nan
B81: Staten Island Economic Development Corporation | C81: 133706442 | D81: 25000 | E81: Council District 49
B82: Safe Horizon, Inc. | C82: 132946970 | D82: 24000 | E82: nan
B83: Richmond County Orchestra, Inc. | C83: 134063615 | D83: 20000 | E83: Curtis High School (31R450)
B84: Staten Island Zoological Society, Inc. | C84: 135680691 | D84: 20000 | E84: Education Programming & Animal Care
B85: City Parks Foundation | C85: 133561657 | D85: 16000 | E85: SummerStage Council District 49
B86: Dr. Theodore A. Atlas Foundation, Inc. | C86: 134012789 | D86: 15000 | E86: Council District 49
B87: Literacy Partners, Inc. | C87: 510180665 | D87: 15000 | E87: Council District 49
B88: Maker Park Radio, Inc. | C88: 821397822 | D88: 15000 | E88: Council District 49
B89: Albanian-American Association of Ulqin, Inc. | C89: 881042164 | D89: 15000 | E89: Council District 49
B90: Ballroom Basix USA, Inc. | C90: 273218865 | D90: 10000 | E90: Public School 020R Port Richmond (31R020)
B91: Bee U, Inc. | C91: 881156617 | D91: 10000 | E91: Community Workshops - Council District 49
... B150: Department of Education | C150: 136400434 | D150: 1000 | E150: The Harbor View School (31R059)
A151: NYC CLEANUP
B152: Department of Sanitation | C152: 136400434 | D152: 180000 | E152: Litter Basket Service & Manual Litter Patrol
B153: Staten Island Chamber of Commerce Foundation, Inc. | C153: 134069282 | D153: 50000 | E153: nan
B154: Staten Island Chamber of Commerce Foundation, Inc. | C154: 134069282 | D154: 30000 | E154: nan
B155: Friends of Abandoned Cemeteries, Inc. | C155: 133176456 | D155: 10000 | E155: Council District 49
B156: Silver Mount Cemetery Association, Inc. | C156: 135579013 | D156: 10000 | E156: nan
A157: NEIGHBORHOOD DEVELOPMENT GRANT INITIATIVE
B158: Staten Island Economic Development Corporation | C158: 133706442 | D158: 15000 | E158: Rosebank Merchants Association - Council District 49
B159: Staten Island Economic Development Corporation | C159: 133706442 | D159: 15000 | E159: Port Richmond Merchants Association - Council District 49
B160: West Brighton Community Local Development Corporation | C160: 133046424 | D160: 10000 | E160: Business Attraction/Business Retention - West Brighton
B161: Staten Island Chamber of Commerce Foundation, Inc. | C161: 134069282 | D161: 10000 | E161: Downtown Staten Island BID Formation - Council District 49
A162: PARKS EQUITY INITIATIVE
B163: Association of Community Employment Programs for the Homeless, Inc. | C163: 133846431 | D163: 30000 | E163: Tappen Park Clean Up - Council District 49
...

Sheet Carr — All Orgs (DB)
A1: CM CARR — EVERY FUNDED ORGANIZATION, FY27 (Council discretionary database — authoritative)
A2: Source: ExportedSearchResults.xlsx (Council Finance export, 8,597 rows). Green rows = SU-CASA (database-only; not yet printed in Schedule C). Award-letter re-foot should use these per-EIN amounts.
A4: MDI pot | B4: Organization (Legal Name) | C4: EIN | D4: Amount | E4: Program / Site
A5: A GREENER NYC
B6: Greenbelt Conservancy, Inc. | C6: 133481845 | D6: 40000 | E6: Nature Discovery Series
B7: New York City H2O | C7: 453860014 | D7: 15000 | E7: Clean-Up Education Program
B8: Snug Harbor Cultural Center and Botanical Garden | C8: 800193388 | D8: 15000 | E8: Green Careers & Stewardship Program
B9: Staten Island Economic Development Corporation | C9: 133706442 | D9: 15000 | E9: nan
B10: Department of Education | C10: 136400434 | D10: 15000 | E10: Staten Island Borough Office
A11: AGING
B12: Staten Island Community Services Friendship Clubs, Inc. | C12: 132778244 | D12: 35000 | E12: New Dorp Beach Friendship Club
B13: Carmel Richmond Nursing Home | C13: 132720248 | D13: 17000 | E13: nan
B14: Jewish Community Center of Staten Island, Inc. | C14: 135562256 | D14: 16000 | E14: nan
B15: Health Essential Association, Inc. | C15: 452871053 | D15: 10000 | E15: nan
B16: Meals on Wheels of Staten Island, Inc. | C16: 132894978 | D16: 10000 | E16: nan
B17: Federation of Italian American Organizations of Brooklyn, Ltd. | C17: 112507910 | D17: 9000 | E17: nan
B18: Lifestyles for the Disabled, Inc. | C18: 133740011 | D18: 8000 | E18: nan
B19: United Hands Organization, Inc. | C19: 932643668 | D19: 5000 | E19: nan
A20: ANTI-POVERTY
B21: Staten Island Zoological Society, Inc. | C21: 135680691 | D21: 20000 | E21: nan
B22: Grace Foundation of New York | C22: 134131863 | D22: 5000 | E22: nan
A23: COMMUNITY SAFETY AND VICTIM SERVICES
B24: Dr. Theodore A. Atlas Foundation, Inc. | C24: 134012789 | D24: 15000 | E24: nan
B25: Oceanic Hook and Ladder Co. No. 1, Inc. | C25: 465288351 | D25: 15000 | E25: nan
B26: Young Israel of Staten Island | C26: 132618386 | D26: 15000 | E26: nan
B27: United Activities Unlimited, Inc. | C27: 132921483 | D27: 15000 | E27: nan
B28: Canvas Institute | C28: 824902021 | D28: 10000 | E28: nan
B29: Emergency Children's Help Organization, Inc. | C29: 113828185 | D29: 10000 | E29: Emergency Assistance Program
B30: Federation of Italian American Organizations of Brooklyn, Ltd. | C30: 112507910 | D30: 10000 | E30: nan
B31: Richmond County Youth Complex, Inc. | C31: 205857329 | D31: 10000 | E31: nan
A32: CULTURAL AFTER-SCHOOL ADVENTURE (CASA)
B33: IlluminArt Productions | C33: 421727647 | D33: 20000 | E33: Intermediate School 2R George L. Egbert (31R002)
B34: IlluminArt Productions | C34: 421727647 | D34: 20000 | E34: Public School 23R Richmondtown (31R023)
B35: IlluminArt Productions | C35: 421727647 | D35: 20000 | E35: Stephanie A. Vierno School, Public School 41R (31R041)
B36: NIA Community Services Network, Inc. | C36: 112697931 | D36: 20000 | E36: Public School 52R John C. Thompson (31R052)
B37: Snug Harbor Cultural Center and Botanical Garden | C37: 800193388 | D37: 20000 | E37: Intermediate School 51R Edwin Markham (31R051)
B38: Staten Island Children's Museum | C38: 237379930 | D38: 20000 | E38: Public School 38R George Cromwell (31R038)
B39: Staten Island Children's Museum | C39: 237379930 | D39: 20000 | E39: Public School 29R Bardwell (31R029)
B40: Staten Island Historical Society | C40: 131985514 | D40: 20000 | E40: Public School 54R Charles W. Leng (31R054)
B41: Staten Island Institute of Arts and Sciences | C41: 135564127 | D41: 20000 | E41: Public School 46R Albert V. Maniscalco (31R046)
B42: Staten Island Zoological Society, Inc. | C42: 135680691 | D42: 20000 | E42: Naples Street Elementary School (31R009)
B43: Staten Island Zoological Society, Inc. | C43: 135680691 | D43: 20000 | E43: Public School 30R Westerleigh (31R030)
B44: Staten Island Zoological Society, Inc. | C44: 135680691 | D44: 20000 | E44: Public School 39R Francis J. Murphy Jr. (31R039)
... B49: Sundog Theatre, Inc. | C49: 450476945 | D49: 20000 | E49: Public School 50R Frank Hankinson (31R050)
A50: CULTURAL IMMIGRANT INITIATIVE
B51: Sundog Theatre, Inc. | C51: 450476945 | D51: 22500 | E51: nan
B52: Jacques Marchais Center of Tibetan Art, Inc. | C52: 237280740 | D52: 20000 | E52: nan
B53: St. George Theatre Restoration, Inc. | C53: 200985637 | D53: 18000 | E53: nan
B54: Casa Belvedere, The Italian Cultural Foundation | C54: 264411728 | D54: 12500 | E54: nan
B55: Staten Island Philharmonic Orchestra, Inc. | C55: 202732542 | D55: 12000 | E55: nan
B56: Friends of Alice Austen House, Inc. | C56: 133248928 | D56: 10000 | E56: nan
B57: IlluminArt Productions | C57: 421727647 | D57: 10000 | E57: nan
B58: Museum of Maritime Navigation and Communication | C58: 900730331 | D58: 10000 | E58: nan
B59: National Lighthouse Museum | C59: 134055215 | D59: 10000 | E59: nan
B60: Richmond Choral Society | C60: 132921818 | D60: 10000 | E60: nan
B61: Garibaldi-Meucci Museum | C61: 061725844 | D61: 10000 | E61: nan
A62: DIGITAL INCLUSION AND LITERACY INITIATIVE
B63: Jewish Community Center of Staten Island, Inc. | C63: 135562256 | D63: 45000 | E63: Council District 50
B64: United Activities Unlimited, Inc. | C64: 132921483 | D64: 45000 | E64: nan
A65: DOMESTIC VIOLENCE AND EMPOWERMENT (DOVE) INITIATIVE
B66: Community Agency for Senior Citizens, Inc. | C66: 133263537 | D66: 55000 | E66: nan
B67: Metropolitan New York Coordinating Council on Jewish Poverty, Inc. | C67: 132738818 | D67: 50000 | E67: Council District 50
B68: Community Health Action of Staten Island, Inc. | C68: 133556132 | D68: 45000 | E68: nan
B69: Legal Services NYC | C69: 132600199 | D69: 45000 | E69: nan
A70: LOCAL
B71: Staten Island Economic Development Corporation | C71: 133706442 | D71: 25000 | E71: New Dorp BID
B72: Staten Island Economic Development Corporation | C72: 133706442 | D72: 25000 | E72: Richmond Road Merchants Association
B73: Staten Island Economic Development Corporation | C73: 133706442 | D73: 20000 | E73: General Operating Support & Business Assistance
B74: Staten Island Historical Society | C74: 131985514 | D74: 20000 | E74: nan
B75: Noble Maritime Collection, The | C75: 133351673 | D75: 20000 | E75: nan
B76: Albanian American Association of Staten Islan Inc. | C76: 931542543 | D76: 15000 | E76: nan
B77: Federation of Italian American Organizations of Brooklyn, Ltd. | C77: 112507910 | D77: 15000 | E77: Concerts - Dyker Heights Park - Council District 50
B78: Richmond County Youth Complex, Inc. | C78: 205857329 | D78: 15000 | E78: Field Maintenance
B79: Staten Island Chamber of Commerce Foundation, Inc. | C79: 134069282 | D79: 15000 | E79: nan
B80: Staten Island Economic Development Corporation | C80: 133706442 | D80: 15000 | E80: Health & Wellness Expo
B81: Staten Island Economic Development Corporation | C81: 133706442 | D81: 15000 | E81: Victory Blvd Business District Corridor
B82: Community Resources Staten Island, Inc. | C82: 135660279 | D82: 10000 | E82: nan
... B114: Staten Island Little League, Inc. | C114: 136162802 | D114: 3000 | E114: nan
A115: NYC CLEANUP
B116: Where to Turn, Inc. | C116: 200404386 | D116: 200000 | E116: nan
B117: Department of Sanitation | C117: 136400434 | D117: 30000 | E117: Council District 50
B118: Friends of Abandoned Cemeteries, Inc. | C118: 133176456 | D118: 30000 | E118: Council District 50
B119: United Activities Unlimited, Inc. | C119: 132921483 | D119: 15000 | E119: nan
B120: Moore Catholic High School | C120: 270672195 | D120: 5000 | E120: nan
A121: NEIGHBORHOOD DEVELOPMENT GRANT INITIATIVE
B122: Staten Island Economic Development Corporation | C122: 133706442 | D122: 20000 | E122: New Dorp Lane Business Improvement District
B123: Staten Island Economic Development Corporation | C123: 133706442 | D123: 20000 | E123: Victory Boulevard Merchants Association
B124: Staten Island Economic Development Corporation | C124: 133706442 | D124: 10000 | E124: Victory Boulevard Merchants
A125: PARKS EQUITY INITIATIVE
B126: Grasmere and Cameron Lakes Bluebelt Conservancy, Inc. | C126: 452493342 | D126: 30000 | E126: Council District 50
B127: Staten Island Youth Soccer League, Inc. | C127: 320048308 | D127: 20000 | E127: Oakwood Fields
B128: Boy Scouts of America - Greater New York Council | C128: 131624015 | D128: 15000 | E128: William H. Pouch Camp
B129: Fund for the City of New York, Inc. | C129: 132612524 | D129: 15000 | E129: Freshkills Park
B130: Department of Parks and Recreation | C130: 136400434 | D130: 10000 | E130: Westerleigh Park - Council District 50
A131: SU-CASA
B132: Snug Harbor Cultural Center and Botanical Garden | C132: 800193388 | D132: 15000 | E132: New Dorp Beach OAC
B133: Staten Island Historical Society | C133: 131985514 | D133: 15000 | E133: Archcare at Carmel Richmond
B134: Sundog Theatre, Inc. | C134: 450476945 | D134: 15000 | E134: Todt Hill OAC
A135: SUPPORT OUR OLDER ADULTS
B136: Lifestyles for the Disabled, Inc. | C136: 133740011 | D136: 40000 | E136: nan
...

Sheet Morano — All Orgs (DB)
A1: CM MORANO — EVERY FUNDED ORGANIZATION, FY27 (Council discretionary database — authoritative)
A2: Source: ExportedSearchResults.xlsx (Council Finance export, 8,597 rows). Green rows = SU-CASA (database-only; not yet printed in Schedule C). Award-letter re-foot should use these per-EIN amounts.
A4: MDI pot | B4: Organization (Legal Name) | C4: EIN | D4: Amount | E4: Program / Site
A5: A GREENER NYC
B6: New York City H2O | C6: 453860014 | D6: 35000 | E6: Volunteer Cleanups & Stewardship Events - Council District 51
B7: Lifestyles for the Disabled, Inc. | C7: 133740011 | D7: 20000 | E7: Horticulture & Woodcraft Workshop
B8: Staten Island Historical Society | C8: 131985514 | D8: 15000 | E8: Educational Programming
B9: Billion Oyster Project, Inc. | C9: 272918478 | D9: 10000 | E9: Educational Programming - Council District 51
B10: Conference House Association, Inc. | C10: 136162071 | D10: 10000 | E10: Historic Conference House Tours & Cultural Events
B11: Tottenville Historical Society | C11: 841678085 | D11: 10000 | E11: nan
A12: AGING
B13: Staten Island Community Services Friendship Clubs, Inc. | C13: 132778244 | D13: 20000 | E13: Mt. Loretto Friendship Club - Senior Services
B14: Staten Island Community Services Friendship Clubs, Inc. | C14: 132778244 | D14: 20000 | E14: Great Kills Friendship Club - Senior Services
B15: Eger Health Care and Rehabilitation Center | C15: 133524533 | D15: 17500 | E15: Better Life More Living
B16: Metropolitan New York Coordinating Council on Jewish Poverty, Inc. | C16: 132738818 | D16: 15000 | E16: nan
B17: Lifestyles for the Disabled, Inc. | C17: 133740011 | D17: 12500 | E17: Older Adults Services
B18: Noble Maritime Collection, The | C18: 133351673 | D18: 10000 | E18: Council District 51
B19: Jewish Community Center of Staten Island, Inc. | C19: 135562256 | D19: 5000 | E19: Senior Olympics
B20: South Shore Artists Foundation | C20: 842895424 | D20: 5000 | E20: Senior Programs - Council District 51
B21: TraNa Relief Association | C21: 920875945 | D21: 5000 | E21: nan
A22: ANTI-POVERTY
B23: Staten Island Children's Museum | C23: 237379930 | D23: 10000 | E23: Arts Residency - Council District 51
B24: HSS Screening and Early Detection, Inc. | C24: 473436880 | D24: 7500 | E24: nan
B25: Metropolitan New York Coordinating Council on Jewish Poverty, Inc. | C25: 132738818 | D25: 7500 | E25: Council District 51
A26: COMMUNITY SAFETY AND VICTIM SERVICES
B27: IlluminArt Productions | C27: 421727647 | D27: 20000 | E27: Council District 51
B28: Sundog Theatre, Inc. | C28: 450476945 | D28: 17500 | E28: nan
B29: Catholic Charities of Staten Island | C29: 135562286 | D29: 12500 | E29: Catholic Youth Organization (CYO)
B30: Emergency Children's Help Organization, Inc. | C30: 113828185 | D30: 10000 | E30: Emergency Assistance Program
B31: Young Men's Christian Association of Greater New York | C31: 131624228 | D31: 10000 | E31: Counseling & Programming - Council District 51
B32: Police Department | C32: 136400434 | D32: 10000 | E32: 123rd Precinct
B33: Girl Scout Council of Greater New York, Inc. | C33: 131624014 | D33: 10000 | E33: Troop 75312
B34: Carl V. Bini Memorial Fund, The | C34: 320144539 | D34: 10000 | E34: nan
A35: CULTURAL AFTER-SCHOOL ADVENTURE (CASA)
B36: Canvas Institute | C36: 824902021 | D36: 20000 | E36: Intermediate School 72R Rocco Laurie (31R072)
B37: Sundog Theatre, Inc. | C37: 450476945 | D37: 20000 | E37: Public School 6R Corporal Allan F. Kivlehan School (31R006)
B38: Sundog Theatre, Inc. | C38: 450476945 | D38: 20000 | E38: Public School 5R Huguenot (31R005)
B39: Sundog Theatre, Inc. | C39: 450476945 | D39: 20000 | E39: Public School 55R Henry M. Boehm School (31R055)
B40: Sundog Theatre, Inc. | C40: 450476945 | D40: 20000 | E40: Public School 53R The Barbara Esselborn School (31R053)
B41: Sundog Theatre, Inc. | C41: 450476945 | D41: 20000 | E41: Intermediate School 7R Elias Bernstein (31R007)
B42: Sundog Theatre, Inc. | C42: 450476945 | D42: 20000 | E42: Intermediate School 034R Tottenville (31R034)
B43: Staten Island Historical Society | C43: 131985514 | D43: 20000 | E43: Public School 36R J. C. Drumgoole (31R036)
B44: Staten Island Historical Society | C44: 131985514 | D44: 20000 | E44: Public School 1R Tottenville (31R001)
B45: Marquis Studios, Ltd. | C45: 133047206 | D45: 20000 | E45: The David Marquis School of the Arts (75R037)
B46: Intrepid Museum Foundation, Inc. | C46: 133062419 | D46: 20000 | E46: Public School 53R The Barbara Esselborn School (31R053)
B47: Intrepid Museum Foundation, Inc. | C47: 133062419 | D47: 20000 | E47: Intermediate School 24R Myra S. Barnes (31R024)
... B52: Marquis Studios, Ltd. | C52: 133047206 | D52: 20000 | E52: The David Marquis School of the Arts (75R037)
A53: CULTURAL IMMIGRANT INITIATIVE
B54: New York City H2O | C54: 453860014 | D54: 25000 | E54: Culture & Environmental Education Walking Tours
B55: Intrepid Museum Foundation, Inc. | C55: 133062419 | D55: 20000 | E55: Schools - Council District 51
B56: Ballroom Basix USA, Inc. | C56: 273218865 | D56: 15000 | E56: Council District 51
B57: Snug Harbor Cultural Center and Botanical Garden | C57: 800193388 | D57: 15000 | E57: nan
B58: Tottenville Historical Society | C58: 841678085 | D58: 10000 | E58: nan
B59: Casa Belvedere, The Italian Cultural Foundation | C59: 264411728 | D59: 10000 | E59: nan
B60: Albanian American Association of Staten Islan Inc. | C60: 931542543 | D60: 10000 | E60: Cultural Services
B61: Roundabout Theatre Company, Inc. | C61: 136192346 | D61: 10000 | E61: School Programming - Council District 51
B62: Staten Island Historical Society | C62: 131985514 | D62: 10000 | E62: nan
B63: Staten Island Philharmonic Orchestra, Inc. | C63: 202732542 | D63: 10000 | E63: Council District 51
B64: Sundog Theatre, Inc. | C64: 450476945 | D64: 10000 | E64: School Programming - Council District 51
A65: DIGITAL INCLUSION AND LITERACY INITIATIVE
B66: IlluminArt Productions | C66: 421727647 | D66: 20000 | E66: Council District 51
B67: Jewish Community Center of Staten Island, Inc. | C67: 135562256 | D67: 20000 | E67: Council District 51
B68: Mouse, Inc. | C68: 133973196 | D68: 20000 | E68: Council District 51
B69: Sundog Theatre, Inc. | C69: 450476945 | D69: 20000 | E69: Smart Money Kids Program - Public School 005R Huguenot (31R005)
B70: United Activities Unlimited, Inc. | C70: 132921483 | D70: 10000 | E70: nan
A71: DOMESTIC VIOLENCE AND EMPOWERMENT (DOVE) INITIATIVE
B72: District Attorney-Richmond | C72: 136400434 | D72: 25000 | E72: nan
B73: IlluminArt Productions | C73: 421727647 | D73: 20000 | E73: nan
B74: Metropolitan New York Coordinating Council on Jewish Poverty, Inc. | C74: 132738818 | D74: 20000 | E74: Council District 51
B75: Pride Center of Staten Island, Inc. | C75: 463358895 | D75: 18000 | E75: Domestic Violence Programming
B76: Seamen's Society for Children and Families | C76: 135563010 | D76: 10000 | E76: Council District 51
B77: Community Agency for Senior Citizens, Inc. | C77: 133263537 | D77: 10000 | E77: nan
B78: Legal Services NYC | C78: 132600199 | D78: 10000 | E78: nan
B79: Stella Orton Home Care Agency, Inc. | C79: 133137595 | D79: 10000 | E79: nan
B80: Police Department | C80: 136400434 | D80: 10000 | E80: 123rd Precinct
A81: LOCAL
B82: Staten Island Economic Development Corporation | C82: 133706442 | D82: 40000 | E82: nan
B83: Grace Foundation of New York | C83: 134131863 | D83: 25000 | E83: nan
B84: Staten Island Children's Museum | C84: 237379930 | D84: 16000 | E84: Arts Residency - Council District 51
B85: Museum of Maritime Navigation and Communication | C85: 900730331 | D85: 15000 | E85: nan
B86: On Your Mark, Inc. | C86: 133128315 | D86: 14500 | E86: Art Program
B87: Theatre Development Fund, Inc. | C87: 136216919 | D87: 11500 | E87: School Programs - Council District 51
B88: Louie's Legacy Animal Rescue, Inc. | C88: 270805279 | D88: 10000 | E88: nan
B89: On Your Mark, Inc. | C89: 133128315 | D89: 10000 | E89: Project Teamwork
B90: On Your Mark, Inc. | C90: 133128315 | D90: 10000 | E90: Special Athletics
B91: Volunteer Heart Resuscitation Unit & Ambulance Corp. of SI., Inc. | C91: 136628436 | D91: 10000 | E91: nan
B92: Working in Support of Education, Inc. | C92: 134024627 | D92: 8000 | E92: Council District 51
B93: Eden II School for Autistic Children, Inc. | C93: 132872916 | D93: 8000 | E93: Adult Day Hab Programs
... B142: Department of Parks and Recreation | C142: 136400434 | D142: 1500 | E142: Urban Park Rangers - Council District 51
A143: NYC CLEANUP
B144: Where to Turn, Inc. | C144: 200404386 | D144: 105000 | E144: nan
B145: Department of Sanitation | C145: 136400434 | D145: 45000 | E145: Litter Basket Services - Council District 51
B146: New York City H2O | C146: 453860014 | D146: 40000 | E146: Council District 51
B147: South Shore District Management Association, Inc. | C147: 810728516 | D147: 25000 | E147: Council District 51
B148: Department of Sanitation | C148: 136400434 | D148: 20000 | E148: Mechanical Broom Service - Council District 51
B149: Staten Island Historical Society | C149: 131985514 | D149: 20000 | E149: Council District 51
B150: United Activities Unlimited, Inc. | C150: 132921483 | D150: 15000 | E150: nan
B151: Friends of Abandoned Cemeteries, Inc. | C151: 133176456 | D151: 10000 | E151: Council District 51
A152: NEIGHBORHOOD DEVELOPMENT GRANT INITIATIVE
B153: ArtBridge Projects, Inc. | C153: 611682898 | D153: 30000 | E153: Public Art & Business Development - Council District 51
...

Sheet DB↔Schedule C Tie-Out
A1: DATABASE ↔ SCHEDULE C FINAL-3 — EIN-LEVEL TIE-OUT (same basis: excl. Speaker items & SU-CASA)
A3: Member | B3: EINs | C3: Tied exactly | D3: Adjacency swaps (net $0) | E3: DB total | F3: PDF printed total | G3: Verdict
A4: Hanks | B4: 94 | C4: 79 | D4: 15 | E4: 2250000 | F4: 2250000 | G4: EXACT TIE — totals identical; swaps are PDF wrap-attribution, netting to $0
A5: Carr | B5: 85 | C5: 77 | D5: 8 | E5: 2225000 | F5: 2225000 | G5: EXACT TIE — totals identical; swaps are PDF wrap-attribution, netting to $0
A6: Morano | B6: 78 | C6: 78 | D6: 0 | E6: 2163000 | F6: 2163000 | G6: EXACT TIE — totals identical; swaps are PDF wrap-attribution, netting to $0
A8: Deltas fully explained: Speaker-pool items live outside DB member rows (NYCID $500K, Pride $50K, Bini $40K, Lifestyles $35K); SU-CASA rows exist in DB only (Hanks 3×$15K, Carr 3×$15K, Morano 0). For the 133 award letters: the database per-EIN amounts on the member tabs are the re-foot source of record; the handful of PDF adjacency swaps (Hanks 15 EINs, Carr 8, Morano 0) confirm the PDF should not be the letter source.

Sheet §254 Capital Structure
A1: FY27 §254 CAPITAL — SUPER-SPECIFIC STRUCTURE & VERIFICATION STATUS
A3: Attribution (CC lines only) | B3: Lines | C3: Amount | D3: Verification
A4: Hanks (D49) | B4: 22 | C4: 17750000 | D4: Ties adopted capital workbook exactly; §254 line-verified in prior session
A5: Carr (D50) | B5: 34 | C5: 15600000 | D5: Ties adopted capital workbook exactly; §254 line-verified in prior session
A6: Morano (D51) | B6: 30 | C6: 10536000 | D6: Ties adopted capital workbook exactly; §254 line-verified in prior session
A7: SI Delegation (tri-member) | B7: 3 | C7: 7418000 | D7: Ties adopted capital workbook exactly; §254 line-verified in prior session
A8: Speaker (pure, citywide → SI) | B8: 4 | C8: 20196000 | D8: Ties adopted capital workbook exactly; §254 line-verified in prior session
A9: GRAND — SI §254 CC additions | B9: =SUM(B4:B8) -> 93 | C9: =SUM(C4:C8) -> 71500000
A11: SUB-CUTS (arithmetic verified this session)
A12: • Three-member combined (Hanks+Carr+Morano): $43,886,000. Members + delegation pot (all SI-member-controlled): $51,304,000.
A13: • Pure member capital with Speaker co-sponsor credits stripped: exactly $5,000,000 per member ($15,000,000) — the uniform member allocation, which validates the attribution method.
A14: • Speaker-involved capital (solo + co-sponsored): $56,500,000 = 79.0% of the SI total — the Speaker relationship is the delegation’s capital engine.
A16: TWO WALLETS — CC vs MA (verified against the §254 book in the prior session; cite pins pending re-upload)
A17: • "CC" lines = new FY27 Council additions: sponsor-coded (HANKS/CARR/SPEAK), Section I, roll up to the official $853,688,000 Council Additions total. All 93 SI lines / $71.5M are CC.
A18: • "MA" lines = non-City sections (II/III), no sponsor, EXCLUDED from the $853.688M; budget-line format "0N364" (leading zero = pre-existing non-City lump-sum line). Citywide MA package ~$71M, all cultural: Roundabout $7M · The Kitchen $14M · Ballet Hispánico $10M · St. George Theatre $5.85M — the Administration/DCLA side of the adoption handshake.
A19: • Charter §254 requires Council increases be "stated separately and distinctly" — Section I does that; MA lines are not Council additions, hence outside it.
A20: • MA1004 — St. George Theatre $5,850,000, Boro R, 0N364: counts toward "all dollars reaching SI orgs" (Measure-C side), NOT toward Measures A/B. St. George’s true FY27 org total = $7,350,000 ($1.5M Council CC + $5.85M MA) — the number the theatre will cite.
A22: CC0796 CAVEAT — INSIDE THE $71.5M
A23: • CC0796 (P.S./I.S. 229, $230,000, Carr) is Boro-coded R but carries Brooklyn school codes. It is currently INSIDE the adopted $71.5M under Carr; if confirmed Brooklyn, SI CC total drops to $71,270,000 (Carr to $15,370,000) and the SI-substantive-with-MA figure to $77,120,000. Suspected City coding typo — mirrors CC1100 (Boro-X-coded but SI-substantive) in reverse.
A25: THREE QUESTIONS FOR COUNCIL FINANCE
... A28: • 3. Should MA-line dollars count in the Council’s own borough-equity math, or CC lines only? And: confirm CC0796’s true borough.

Sheet All CMs — Summary
A1: ALL 51 COUNCIL MEMBERS + DELEGATIONS — FY27 MEMBER-DESIGNATED FUNDS (database export, complete)
A2: Completeness audit: export = 8,597 rows / $109,855,084; real designations 7,327 / $109,853,997; 1,270 penny placeholders (CBO-Defunded markers + Speaker’s Initiative $0.01 rows — Speaker dollars are NOT in this export; see Schedule C Speaker tabs). All 51 members present; all 5 borough delegations present; 2,031 distinct organizations / 1,972 EINs.
A4: Member / Delegation | B4: Designations | C4: Total $ | D4: Rank
A5: P. Sanchez | B5: 135 | C5: 2360000 | D5: 1
A6: Brooks-Powers | B6: 181 | C6: 2355000 | D6: 2
A7: Hankerson | B7: 132 | C7: 2335000 | D7: 3
A8: Feliz | B8: 103 | C8: 2330000 | D8: 4
A9: J. Sanchez | B9: 103 | C9: 2330000 | D9: 5
A10: Thomas-Henry | B10: 92 | C10: 2325000 | D10: 6
A11: Williams | B11: 170 | C11: 2325000 | D11: 7
A12: Aldebol | B12: 121 | C12: 2310000 | D12: 8
A13: Riley | B13: 104 | C13: 2310000 | D13: 9
A14: Gutierrez | B14: 156 | C14: 2305000 | D14: 10
A15: Banks | B15: 163 | C15: 2305000 | D15: 11
A16: Abreu | B16: 168 | C16: 2305000 | D16: 12
... A55: Maloney | B55: 123 | C55: 785000 | D55: 51
A56: Brooklyn Delegation | B56: 62 | C56: 620000 | D56: —
A57: Queens Delegation | B57: 40 | C57: 540000 | D57: —
A58: Manhattan Delegation | B58: 16 | C58: 380000 | D58: —
A59: Bronx Delegation | B59: 33 | C59: 340000 | D59: —
A60: Staten Island Delegation | B60: 11 | C60: 120000 | D60: —
A61: TOTAL | B61: =SUM(B5:B60) -> 7327 | C61: =SUM(C5:C60) -> 1.09854e+08

Sheet All CMs — Org Register (DB)
A1: EVERY ORGANIZATION FUNDED BY EVERY COUNCIL MEMBER — FY27 (7,327 designations, database export)
A3: Member / Delegation | B3: MDI pot | C3: Organization (Legal Name) | D3: EIN | E3: Amount | F3: Program
A4: Abreu | B4: A Greener NYC | C4: West Harlem Environmental Action, Inc. | D4: 133800068 | E4: 35000 | F4: None
A5: Abreu | B5: A Greener NYC | C5: Citizens Committee for New York City, Inc. | D5: 510171818 | E5: 30000 | F5: None
A6: Abreu | B6: A Greener NYC | C6: Big Initiatives Incorporated | D6: 465083170 | E6: 20000 | F6: None
A7: Abreu | B7: A Greener NYC | C7: Horticultural Society of New York, The | D7: 130854930 | E7: 15000 | F7: None
A8: Abreu | B8: Aging | C8: Blue Card, Inc., The | D8: 131623910 | E8: 15000 | F8: Council District 7
A9: Abreu | B9: Aging | C9: West Side Federation for Senior and Supportive Housing, Inc. | D9: 132926433 | E9: 13000 | F9: Council District 7
A10: Abreu | B10: Aging | C10: Morningside Retirement and Health Services, Inc. | D10: 136206256 | E10: 12500 | F10: NORC Program - Council District 7
A11: Abreu | B11: Aging | C11: Service Program for Older People (SPOP), Inc. | D11: 132947616 | E11: 10000 | F11: Mental Healthcare Services Program - Council District 7
A12: Abreu | B12: Aging | C12: Riverstone Senior Life Services, Inc. | D12: 133355074 | E12: 10000 | F12: Riverstone Memory Center - Council District 7
A13: Abreu | B13: Aging | C13: Presbyterian Senior Services, Inc. | D13: 131981482 | E13: 10000 | F13: Manhattanville Senior Center- Council District 7
A14: Abreu | B14: Aging | C14: Harlem Advocates for Seniors, Inc. | D14: 811966114 | E14: 10000 | F14: Council District 7
A15: Abreu | B15: Aging | C15: ARC XVI Fort Washington, Inc. | D15: 132745426 | E15: 10000 | F15: Council District 7
... A7330: Zhuang | B7330: Youth | C7330: Chinese American Social Services Center, Inc. | D7330: 474279061 | E7330: 1000 | F7330: Youth Programs - Council District 43
D7331: TOTAL | E7331: =SUM(E4:E7330) -> 109853997

Sheet Speaker Reconcile (Jul 7)
A1: SPEAKER FUNDING TO SI — PDF vs CORRECTED (RULING: Ulqin & Project Hospitality are NOT Speaker items)
A3: Sponsor tag | B3: Agency | C3: Organization — Program | D3: Amount | E3: Status
A4: (blank) | B4: DHMH | C4: African Refuge, Inc. - Community and Police Mental Health Collaboration | D4: 50000 | E4: Retained
A5: (blank) | B5: DYCD | C5: Albanian-American Association of Ulqin, Inc. | D5: 25000 | E5: REMOVED — not Speaker (ruling Jul 7)
A6: Staten Island | B6: DYCD | C6: Canvas Institute - Media mentorship programs for local youth | D6: 75000 | E6: Retained
A7: Morano | B7: DYCD | C7: Carl V. Bini Memorial Fund, The | D7: 40000 | E7: Retained
A8: (blank) | B8: CUNY | C8: City University of New York - College of Staten Island - Breast Cancer Research | D8: 50000 | E8: Retained
A9: Hanks | B9: DYCD | C9: Dibra Community Organization, Inc. | D9: 25000 | E9: Retained
A10: Hanks | B10: DYCD | C10: Dr. Theodore A. Atlas Foundation, Inc. | D10: 30000 | E10: Retained
A11: Carr, Morano | B11: DHMH | C11: Eden II School for Autistic Children, Inc. - Family Support Programs | D11: 25000 | E11: Retained
A12: Carr | B12: DFTA | C12: Jewish Community Center of Staten Island, Inc. - Senior Skill Development Program | D12: 25000 | E12: Retained
A13: (blank) | B13: DYCD | C13: Jewish Community Council of Greater Coney Island, Inc. - Staten Island Community Shuttle | D13: 50000 | E13: Retained
A14: Carr | B14: DHMH | C14: Lifestyles for the Disabled, Inc. - Adaptive Sports Program | D14: 35000 | E14: Retained
A15: Hanks | B15: DYCD | C15: New York Center for Interpersonal Development, Inc. - Credible Messengers (CMSI) | D15: 500000 | E15: Retained
... A39: Hanks | B39: SBS | C39: Staten Island Immigrant Center, Inc. | D39: 50000 | E39: Retained
C40: PDF Speaker total (All-Funding PDF, stale) | D40: =SUM(D4:D39) -> 2867880
C41: Less: removed per ruling (Ulqin $25,000 + Project Hospitality $25,000) | D41: =-SUMIF(E4:E39,"REMOVED*",D4:D39) -> -50000
C42: CORRECTED SPEAKER TOTAL — ties to Grand Total tab $2,817,880 | D42: =D40+D41 -> 2817880
C44: Note: the Expense-only PDF shows Speaker $2,182,880 because it omits 10 rows ($685,000) present in the All-Funding PDF — see Discrepancy Log F4.

Sheet Citywide Reconcile (Jul 7)
A1: CITYWIDE-TO-SI — PDF ALL-FUNDING ($8,341,467) vs WORKBOOK BASIS ($6,553,360): FULL DECOMPOSITION
A2: Two different scan bases. Never merge. The decomposition below ties to the penny.
A4: Component | B4: Amount | C4: Note
A5: Workbook Citywide-to-SI basis (55 org lines, 42 initiatives) | B5: 6553360 | C5: Citywide to SI tab; Grand Total basis
A6: + Boroughwide Needs block — classified as SI Delegation pot in workbook | B6: 120000 | C6: 11 rows; PDF lists them under Citywide; category difference, not missing money
A7: + PDF-only organization dollars (13 org groups, detail below) | B7: 1678107 | C7: Includes IlluminArt partial Δ$75,000
A8: − Workbook-only row (Northfield/Curtis School $10,000) | B8: -10000 | C8: In workbook citywide, absent from PDF
A9: EQUALS: PDF All-Funding citywide total | B9: 8341467 | C9: Ties exactly
A10: Formula check | B10: =SUM(B5:B8) -> 8341467
A12: PDF-ONLY ORGANIZATION DETAIL (absent from workbook citywide basis)
A13: Organization | B13: PDF $ | C13: EIN elsewhere in Master? | D13: EIN | E13: New group?
A14: City University of New York | B14: 500000 | C14: YES | D14: 133893536 | E14: no — already counted
A15: Community Health Center of Richmond, Inc. | B15: 459357 | C15: no | D15: EIN PENDING | E15: YES — potential +1 group
A16: Project Hospitality, Inc. | B16: 224000 | C16: YES | D16: 133234441 | E16: no — already counted
A17: Friends of Alice Austen House, Inc. | B17: 107500 | C17: YES | D17: 133248928 | E17: no — already counted
A18: Grace Foundation of New York | B18: 107372 | C18: YES | D18: 134131863 | E18: no — already counted
A19: Staten Island Community Services Friendship Clubs, Inc. | B19: 41665 | C19: YES | D19: 132778244 | E19: no — already counted
A20: Dr. Theodore A. Atlas Foundation, Inc. | B20: 35000 | C20: YES | D20: 134012789 | E20: no — already counted
A21: Forest Avenue District Management Association, Inc. | B21: 35000 | C21: YES | D21: 141933279 | E21: no — already counted
A22: Wagner College | B22: 25000 | C22: YES | D22: 135604699 | E22: no — already counted
A23: Albanian-American Association of Ulqin, Inc. | B23: 25000 | C23: no | D23: EIN PENDING | E23: YES — potential +1 group
A24: Liberian Cultural Association, Inc. | B24: 25000 | C24: no | D24: EIN PENDING | E24: YES — potential +1 group
A25: New Dorp District Management Association, Inc. | B25: 18213 | C25: no | D25: EIN PENDING | E25: YES — potential +1 group
A26: IlluminArt Productions — partial: PDF $155,000 vs WB $80,000 (Δ$75,000 = Opioid $50,000 + Hate Crimes $25,000 rows absent from WB)

Sheet Discrepancy Log (Jul 7)
A1: FY27 SI — DISCREPANCY LOG · Jul 7, 2026 · sources: All-Funding PDF, Expense PDF, Cap & Expense workbook
A3: # | B3: Finding | C3: Amount | D3: Ruling / Action needed
A4: F1 | B4: Albanian-American Assoc. of Ulqin + Project Hospitality listed under SPEAKER in both PDFs — RULED NOT SPEAKER (Omar, Jul 7). Corrected Speaker = $2,817,880, ties Grand Total tab. | C4: 50000 | D4: RESOLVED — remove from Speaker in both PDFs; regenerate
A5: F2 | B5: Dibra Community Organization (Welcome NYC, citywide) present in Citywide-to-SI tab but MISSING from Master Line Items — explains Master $16,196,240 vs printed $16,221,240. | C5: 25000 | D5: ACTION — add Dibra row to Master Line Items
A6: F3 | B6: Ulqin Welcome NYC citywide row present in PDF, absent from workbook citywide AND Master. If the Schedule C printed source shows it, group count rises to 176+. | C6: 25000 | D6: RULING NEEDED — verify against Schedule C p.151 area
A7: F4 | B7: Speaker totals differ between the two PDFs: All-Funding $2,867,880 vs Expense-only $2,182,880. Δ = 10 rows (City Parks Fdn $110K, DSNY $100K, Grace $50K, JCC Sunrise $15K, JCC SADC $25K, RMC SAFE $100K, South Shore DMA $45K, SIEDC-50th $140K, SI Historical Society $50K, SI Immigrant Center $50K). Workbook corrected total $2,817,880 confirms all 10 ARE Speaker. | C7: 685000 | D7: RESOLVED by workbook — Expense-only PDF is incomplete; regenerate
A8: F5 | B8: Project Hospitality citywide dollars in PDF (3 lines: LGBTQIA+ Youth $100K, Food Access $50K, Homeless System $74K) absent from workbook citywide basis. | C8: 224000 | D8: RULING NEEDED — accounting inclusion is separate from the standing delivery-partner exclusion
A9: F6 | B9: Community Health Center of Richmond: $459,357 across 4 citywide lines in PDF, no EIN anywhere in Master. Largest EIN-pending group. | C9: 459357 | D9: ACTION — pull EIN, add to census if verified
A10: F7 | B10: CUNY appears under two EINs: 13-3893536 (Research Foundation lines) and 13-6400434 (NYC government EIN on one line). One entity count requires a ruling on which EIN governs. | D10: RULING NEEDED — likely RF-CUNY 13-3893536
A11: F8 | B11: Boroughwide Needs $120,000 (11 rows) classified Citywide in PDF but SI Delegation pot in workbook. Category mapping difference only; dollars tie. | C11: 120000 | D11: RESOLVED — note basis on any total that moves
A12: F9 | B12: Workbook-only citywide row: Northfield/Curtis School $10,000 not in PDF citywide list. | C12: 10000 | D12: ACTION — verify Sched C ref; add to PDF on regen
A13: F10 | B13: Expense totals across the three artifacts: All-Funding PDF $17,982,347 · Expense PDF $17,297,347 · Workbook printed SI $16,221,240 (+$90,000 SU-CASA DB). Three different bases — label separately, never mix. | D13: STANDING RULE

Sheet Corrected Totals (Jul 7)
